Workbook

Sheet README
B2: M4Di Operational Intelligence (OI) Tool — Phase 0
B3: ROM Estimating & Predevelopment Cost Intelligence Platform
B4: Version 1.0 | March 2026 | © M4Di, Inc. | CONFIDENTIAL
B6: RECOMMENDED WORKFLOW
B7: 1 | C7: ASSUMPTIONS | D7: Enter yellow input cells: project name, date, region, and all markup percentages.
B8: 2 | C8: REGIONAL FACTORS | D8: Review or update the regional labor basket and select your pricing region.
B9: 3 | C9: UNIT PRICE LIBRARY | D9: Verify or add unit prices for your project scope. Craig populates the Baseline Region.
B10: 4 | C10: TAKEOFF | D10: Enter quantities by floor/zone. The tool auto-applies adjusted unit costs.
B11: 5 | C11: EQUIPMENT ALLOWANCES | D11: Document owner-selection-dependent equipment allowances with basis of design.
B12: 6 | C12: FLOOR SUMMARY | D12: Review auto-calculated floor totals with markups. No data entry required.
B13: 7 | C13: BID SUMMARY | D13: Executive ROM with full cost stack. Use for board presentations and funder packages.
B14: 8 | C14: SF BENCHMARK | D14: Compare project $/SF against M4Di historical database and facility type ranges.
B15: 9 | C15: HISTORICAL DB | D15: CRITICAL: Enter every completed project. This is M4Di's proprietary data asset.
B16: 10 | C16: OWNER SELECTIONS | D16: Track owner decisions affecting allowance-sensitive items.
B17: 11 | C17: ALLOWANCE LOG | D17: Living log of all open allowances. Export monthly for ALDi gate reporting.
B18: 12 | C18: CLARIFICATIONS | D18: Document scope inclusions, exclusions, and risk flags for client delivery.
B21: COLOR CODING LEGEND (Industry Standard)
B22: SAMPLE | C22: Blue text / yellow background | D22: Hardcoded user inputs — values you enter or change
B23: SAMPLE | C23: Black text / white background | D23: Calculated formulas — do not overwrite
B24: SAMPLE | C24: Green text / light green background | D24: Cross-sheet links — pulling from another tab
B25: SAMPLE | C25: Red text | D25: External links to other files
B26: SAMPLE | C26: Yellow background | D26: Cells requiring attention or decision
B28: PROPRIETARY NOTICE: This workbook and its methodology, unit price library, regional factor weights, and historical database are proprietary to M4Di, Inc. Unauthorized distribution or reproduction is prohibited. © 2026 M4Di, Inc. All rights reserved.

Sheet ASSUMPTIONS
B1: PROJECT ASSUMPTIONS & CONTROLS
B2: Input | C2: Value | E2: Notes
B3: Project Name | C3: M-Well Community Health Campus | E3: Use a short, consistent project code (e.g., WHACC-2026).
B4: Estimate Date | E4: Enter as MM/DD/YYYY. Update with each revision.
B5: Estimate Type | C5: ROM / Conceptual | E5: ROM / Conceptual | Schematic | Design Development | GMP
B6: Project Type | C6: Adaptive Reuse | E6: Interior Improvement | Adaptive Reuse | New Construction | Mixed-Use
B7: Client / Owner | C7: M-Well Medical Group | E7: Legal entity name of the owner organization.
B8: Site Address | C8: 3110 Philadelphia Pike, Claymont, DE 19703 | E8: Full property address for zoning lookup reference.
B9: Total Gross Area (SF) | C9: 27452 | E9: Total gross building SF affected by the scope.
B10: Base Region | C10: Delaware | E10: Delaware = M4Di baseline. All unit prices sourced from Delaware competitive bid market.
B11: Selected Pricing Region | C11: New Castle/Wilmington | E11: Must match a region defined in REGIONAL FACTORS sheet.
B12: Weighted Trade Labor Factor | C12: =IFERROR(INDEX('REGIONAL FACTORS'!H$4:H$20,MATCH(C11,'REGIONAL FACTORS'!A$4:A$20,0)),1) -> 1 | E12: Auto-pulled from REGIONAL FACTORS. 1.000x = Delaware baseline. Philadelphia Metro ≈ 1.145x.
B13: COST ESCALATION
B14: ENR Construction Cost Index (CCI) Escalation % | C14: 0.027 | E14: Source: ENR CCI Q1 2026. Update quarterly. Applies to all labor-heavy items.
B15: ENR Building Cost Index (BCI) Escalation % | C15: 0.043 | E15: Source: ENR BCI Q1 2026. Update quarterly. Applies to material-heavy items.
B16: Blended Escalation Rate | C16: =AVERAGE(C14,C15) -> 0.035 | E16: Formula: average of CCI and BCI. Used in unit price adjusted cost calculation.
B17: Material / Market Factor | C17: 1 | E17: Adjust for procurement pressure, bid climate volatility, or material shortages. 1.000x = neutral.
B18: MARKUPS & CONTINGENCIES
B19: General Conditions % | C19: 0.08 | E19: Typical range: 6%–10%. Covers on-site supervision, temporary facilities, insurance.
B20: Overhead & Profit (OH&P) % | C20: 0.1 | E20: Typical range: 8%–12%. Applied to subtotal after GC.
B21: Design Contingency % | C21: 0.12 | E21: Reduce to 8% at SD; 5% at DD; 0% at GMP. Reflects design development risk.
B22: Existing Conditions Contingency % | C22: 0.1 | E22: Higher for gut renovations (12%–15%). Covers concealed conditions and substrate damage.
B23: Equipment / Owner Selection Contingency % | C23: 0.08 | E23: Reduce as owner selections are confirmed. Set to 0% when all allowances are locked.
B24: Bid / Permit / Bonds % | C24: 0.02 | E24: Covers permitting fees, bid bonds, performance bonds. Adjust for municipality.
B25: Sales Tax % | C25: 0 | E25: Delaware: 0%. Adjust for other jurisdictions. Apply only to taxable material costs if split.
B26: Total Contingency % | C26: =C21+C22+C23 -> 0.3 | E26: Sum of all contingency lines. For reference only.
B28: QUICK REFERENCE TOTALS (auto-calculated from BID SUMMARY)
B29: Base Building Subtotal | C29: ='BID SUMMARY'!C3 -> 0
B30: Equipment Allowances | C30: ='BID SUMMARY'!C4 -> Amount
B31: Subtotal Before Markups | C31: ='BID SUMMARY'!C5 -> 5411956.7
B32: General Conditions | C32: ='BID SUMMARY'!C6 -> 473719.5
B33: OH&P | C33: ='BID SUMMARY'!C7 -> 5885676.2
B34: Total Contingencies | C34: ='BID SUMMARY'!C8 -> 470854.1
B35: Bid / Permit / Bonds | C35: ='BID SUMMARY'!C9 -> 635653.03
B36: TOTAL PROJECT ROM | C36: ='BID SUMMARY'!C10 -> 2097655
B37: FEE SCHEDULE CONTROLS (feeds SOFT COSTS sheet)
B38: AIA Project Type Code | C38: C | E38: A=warehouse, B=office, C=school/fitness (M4Di default), D=clinic/theater, E=hospital/research.
B39: Renovation Project? | C39: Yes | E39: Yes adds renovation premium to base architecture fee. WHACC = Yes.

Sheet REGIONAL FACTORS
B1: REGIONAL MARKET FACTORS — Public Data-Based Labor Basket
B2: Region | C2: Carpenters $/hr | D2: Laborers $/hr | E2: Electricians $/hr | F2: Painters $/hr | G2: Concrete Finishers $/hr | H2: Drywall/Ceiling $/hr | I2: Weighted Labor Basket | J2: Region Factor vs. Delaware | K2: Trade | L2: Weight
B3: Delaware | C3: 29.3 | D3: 22.57 | E3: 30.93 | F3: 23.48 | G3: 25.47 | H3: 25.32 | I3: =C3*$L$3+D3*$L$4+E3*$L$5+F3*$L$6+G3*$L$7+H3*$L$8 -> 26.172 | J3: =1 -> 1 | K3: Carpenters | L3: 0.3 | M3: Baseline — Delaware statewide OEWS wages. Source: BLS OEWS 2024, State=DE.
B4: New Castle/Wilmington | C4: 29.5 | D4: 22.5 | E4: 30.5 | F4: 22.9 | G4: 25.3 | H4: 25.2 | I4: =C4*$L$3+D4*$L$4+E4*$L$5+F4*$L$6+G4*$L$7+H4*$L$8 -> 26.03 | J4: =I4/I$3 -> 0.99457435 | K4: Laborers | L4: 0.2 | M4: New Castle County sub-market proxy. Slightly above state average for urban premium.
B5: Philadelphia Metro | C5: 31.47 | D5: 27.82 | E5: 37.24 | F5: 26.36 | G5: 30.83 | H5: 28.7 | I5: =C5*$L$3+D5*$L$4+E5*$L$5+F5*$L$6+G5*$L$7+H5*$L$8 -> 29.954 | J5: =I5/I$3 -> 1.1445056 | K5: Electricians | L5: 0.1 | M5: Philadelphia-Camden-Wilmington MSA. Source: BLS OEWS 2024, MSA=37980.
B6: New Jersey | C6: 35.16 | D6: 34.27 | E6: 38.51 | F6: 31.16 | G6: 34.78 | H6: 29.5 | I6: =C6*$L$3+D6*$L$4+E6*$L$5+F6*$L$6+G6*$L$7+H6*$L$8 -> 33.913 | J6: =I6/I$3 -> 1.2957741 | K6: Painters | L6: 0.2 | M6: NJ statewide OEWS 2024, all industries. Higher union density drives premium.
B7: Baltimore Area | C7: 28.74 | D7: 22.99 | E7: 33.83 | F7: 27.86 | G7: 26.34 | H7: 24.13 | I7: =C7*$L$3+D7*$L$4+E7*$L$5+F7*$L$6+G7*$L$7+H7*$L$8 -> 27.222 | J7: =I7/I$3 -> 1.0401192 | K7: Concrete Finishers | L7: 0.1 | M7: Baltimore-Columbia-Towson MSA proxy. Source: BLS OEWS 2024, MSA=12580.
B8: Washington DC Metro | C8: 34.5 | D8: 27.1 | E8: 40.2 | F8: 29.5 | G8: 31.2 | H8: 30.4 | I8: =C8*$L$3+D8*$L$4+E8*$L$5+F8*$L$6+G8*$L$7+H8*$L$8 -> 31.85 | J8: =I8/I$3 -> 1.2169494 | K8: Drywall/Ceiling | L8: 0.1 | M8: DC-VA-MD-WV MSA. Source: BLS OEWS 2024, MSA=47900. High labor market tightness.
B9: Custom | C9: 0 | D9: 0 | E9: 0 | F9: 0 | G9: 0 | H9: 0 | I9: =C9*$L$3+D9*$L$4+E9*$L$5+F9*$L$6+G9*$L$7+H9*$L$8 -> 0 | J9: =I9/I$3 -> 0 | K9: TOTAL | L9: =SUM(L3:L8) -> 1 | M9: Enter custom wage rates. Factor auto-calculates vs. Delaware baseline.
B11: NOTE: Weighted Labor Basket is an internal blended labor-only ROM index using BLS OEWS wage data and the trade weightings shown at right. It is not a full construction location factor. ENR City Cost Indexes should be used for full project-level location adjustment when available.

Sheet UNIT PRICE LIBRARY
B2: M4Di™ UNIT PRICE LIBRARY — IDD Residential + Community Health Facility · M-Well Community Health Campus · Phase 1: School Renovation · New Castle County / Wilmington, Delaware · 2026 Pricing
B3: All base unit prices reflect New Castle County / Wilmington Delaware competitive bid market. Regional Factor and Escalation Factor apply automatically. Adjusted Unit Price feeds TAKEOFF via VLOOKUP on Cost Code. Blue/yellow input cells = overrideable. Do not modify columns I–K (formulas). Scope items aligned to M-Well Phase 1: 27,452 SF 2-story school → IDD R-4 residential + IDD licensing standards.
B4: B | C4: Div | D4: Cost Code | E4: Spec Section | F4: Bid Package | G4: Scope Item | H4: Unit | I4: Base Unit Price (Baseline Region) | J4: Region Factor | K4: Escalation Factor | L4: Adjusted Unit Price | M4: Owner Selection Sensitive? | N4: Source / Basis
B5: DIV 02 — DEMOLITION & SITE PREPARATION
C6: 02 | D6: DEM-01 | E6: 02 41 19 | G6: Selective demolition – interior non-structural partitions | H6: SF | I6: 4.5 | J6: =ASSUMPTIONS!C12 -> 1 | K6: =1+ASSUMPTIONS!C16 -> 1.035 | L6: =I6*J6*K6 -> 4.6575 | M6: No | N6: Per SF GFA. Includes debris removal and haul-off. Range $3–7/SF for school renovation.
C7: 02 | D7: DEM-02 | E7: 02 41 19 | G7: Selective demolition – existing ceilings and soffits | H7: SF | I7: 3.25 | J7: =ASSUMPTIONS!C12 -> 1 | K7: =1+ASSUMPTIONS!C16 -> 1.035 | L7: =I7*J7*K7 -> 3.36375 | M7: No | N7: ACT grid + tile or drywall ceiling removal. Includes sorting for recycling.
C8: 02 | D8: DEM-03 | E8: 02 41 13 | G8: Selective demolition – existing doors, frames, hardware | H8: EA | I8: 285 | J8: =ASSUMPTIONS!C12 -> 1 | K8: =1+ASSUMPTIONS!C16 -> 1.035 | L8: =I8*J8*K8 -> 294.975 | M8: No | N8: Per opening. Includes careful removal to protect openings for reuse or patching.
C9: 02 | D9: DEM-04 | E9: 02 41 19 | G9: Selective demolition – existing flooring (VCT/tile/carpet) | H9: SF | I9: 2.75 | J9: =ASSUMPTIONS!C12 -> 1 | K9: =1+ASSUMPTIONS!C16 -> 1.035 | L9: =I9*J9*K9 -> 2.84625 | M9: No | N9: Includes adhesive scraping and surface prep for new flooring. Hazmat survey assumed complete.
C10: 02 | D10: HAZ-01 | E10: 02 82 13 | G10: Asbestos abatement – floor tile and mastic (pre-1980 school) | H10: SF | I10: 18 | J10: =ASSUMPTIONS!C12 -> 1 | K10: =1+ASSUMPTIONS!C16 -> 1.035 | L10: =I10*J10*K10 -> 18.63 | M10: No | N10: Per SF affected area. Includes air monitoring, NESHAP notification, disposal. NCC licensed contractor.
C11: 02 | D11: HAZ-02 | E11: 02 83 13 | G11: Lead paint abatement – encapsulation or removal | H11: SF | I11: 6.5 | J11: =ASSUMPTIONS!C12 -> 1 | K11: =1+ASSUMPTIONS!C16 -> 1.035 | L11: =I11*J11*K11 -> 6.7275 | M11: No | N11: Per SF surface area. Method TBD by industrial hygienist report. Allowance pending Phase I ESA.
B12: DIV 03 — CONCRETE
C13: 03 | D13: CON-01 | E13: 03 30 00 | G13: Concrete slab patch / repair (existing slab anomalies) | H13: SF | I13: 22 | J13: =ASSUMPTIONS!C12 -> 1 | K13: =1+ASSUMPTIONS!C16 -> 1.035 | L13: =I13*J13*K13 -> 22.77 | M13: No | N13: Assumes 15% of floor area requires patching. Full slab replacement priced separately if needed.
C14: 03 | D14: CON-02 | E14: 03 30 00 | G14: Concrete housekeeping pad – mechanical equipment | H14: CY | I14: 450 | J14: =ASSUMPTIONS!C12 -> 1 | K14: =1+ASSUMPTIONS!C16 -> 1.035 | L14: =I14*J14*K14 -> 465.75 | M14: No | N14: Formed, reinforced, poured, finished. Per CY. For mechanical and plumbing equipment bases.
C15: 03 | D15: CON-03 | E15: 03 30 00 | G15: Elevator pit – concrete liner and sump | H15: LS | I15: 18500 | J15: =ASSUMPTIONS!C12 -> 1 | K15: =1+ASSUMPTIONS!C16 -> 1.035 | L15: =I15*J15*K15 -> 19147.5 | M15: No | N15: Lump sum allowance. Excavation, forming, waterproofing, pit drain. Coordinate with elevator supplier.
B16: DIV 04 — MASONRY
C17: 04 | D17: MAS-01 | E17: 04 22 00 | G17: CMU infill – existing openings to be closed | H17: SF | I17: 32 | J17: =ASSUMPTIONS!C12 -> 1 | K17: =1+ASSUMPTIONS!C16 -> 1.035 | L17: =I17*J17*K17 -> 33.12 | M17: No | N17: New CMU to match existing, includes mortar, grout, reinforcing. Toothing and pinning.
C18: 04 | D18: MAS-02 | E18: 04 22 00 | G18: CMU repair – tuck-pointing and spall repair | H18: SF | I18: 14.5 | J18: =ASSUMPTIONS!C12 -> 1 | K18: =1+ASSUMPTIONS!C16 -> 1.035 | L18: =I18*J18*K18 -> 15.0075 | M18: No | N18: Per SF affected surface. Includes mortar removal, repointing, color-matching mortar.
B19: DIV 05 — METALS
C20: 05 | D20: MET-01 | E20: 05 52 13 | G20: Stainless steel handrail – IDD residential corridor (1.5" dia.) | H20: LF | I20: 185 | J20: =ASSUMPTIONS!C12 -> 1 | K20: =1+ASSUMPTIONS!C16 -> 1.035 | L20: =I20*J20*K20 -> 191.475 | M20: No | N20: Continuous handrail both sides of corridor per DDDS licensing. Stainless for durability/hygiene.
C21: 05 | D21: MET-02 | E21: 05 52 13 | G21: Aluminum guardrail – stair and open-to-below conditions | H21: LF | I21: 365 | J21: =ASSUMPTIONS!C12 -> 1 | K21: =1+ASSUMPTIONS!C16 -> 1.035 | L21: =I21*J21*K21 -> 377.775 | M21: No | N21: IBC 42" height minimum. Includes anchor system. Powder coat standard.
C22: 05 | D22: MET-03 | E22: 05 40 00 | G22: Light gauge steel framing – new non-structural partitions | H22: SF | I22: 8.5 | J22: =ASSUMPTIONS!C12 -> 1 | K22: =1+ASSUMPTIONS!C16 -> 1.035 | L22: =I22*J22*K22 -> 8.7975 | M22: No | N22: Per SF of partition (one face). 3-5/8" 20ga stud at 16" OC. Includes track and bridging.
C23: 05 | D23: MET-04 | E23: 05 51 13 | G23: Steel stair – new elevator shaft framing and support | H23: LS | I23: 28000 | J23: =ASSUMPTIONS!C12 -> 1 | K23: =1+ASSUMPTIONS!C16 -> 1.035 | L23: =I23*J23*K23 -> 28980 | M23: No | N23: Allowance for elevator shaft structural framing, pit angle, and cab guide rail embeds.
B24: DIV 06 — WOOD & PLASTICS
C25: 06 | D25: CAR-01 | E25: 06 10 00 | G25: Rough carpentry – blocking and backing for grab bars / equipment | H25: SF | I25: 22 | J25: =ASSUMPTIONS!C12 -> 1 | K25: =1+ASSUMPTIONS!C16 -> 1.035 | L25: =I25*J25*K25 -> 22.77 | M25: No | N25: Per SF wall area requiring backing. IDD residential: extensive blocking for grab bars throughout.
C26: 06 | D26: CAR-02 | E26: 06 20 00 | G26: Finish carpentry – base cabinets (medication room, staff stations) | H26: LF | I26: 425 | J26: =ASSUMPTIONS!C12 -> 1 | K26: =1+ASSUMPTIONS!C16 -> 1.035 | L26: =I26*J26*K26 -> 439.875 | M26: Yes | N26: Allowance. Per LF of base cabinet. Includes box, door, hardware. Countertop separate.
C27: 06 | D27: CAR-03 | E27: 06 20 00 | G27: Finish carpentry – countertop (HPL, med-grade, per LF) | H27: LF | I27: 95 | J27: =ASSUMPTIONS!C12 -> 1 | K27: =1+ASSUMPTIONS!C16 -> 1.035 | L27: =I27*J27*K27 -> 98.325 | M27: Yes | N27: High-pressure laminate. Solid surface upcharge = $55/LF additional. ADA heights required.
B28: DIV 07 — THERMAL & MOISTURE PROTECTION
C29: 07 | D29: INS-01 | E29: 07 21 00 | G29: Batt insulation – exterior wall cavities (R-13 or R-19) | H29: SF | I29: 2.85 | J29: =ASSUMPTIONS!C12 -> 1 | K29: =1+ASSUMPTIONS!C16 -> 1.035 | L29: =I29*J29*K29 -> 2.94975 | M29: No | N29: Per SF of exterior wall. Faced batt, energy code compliant. Verify existing cavity depth.
C30: 07 | D30: INS-02 | E30: 07 21 19 | G30: Rigid insulation board – below-slab or roof deck | H30: SF | I30: 3.4 | J30: =ASSUMPTIONS!C12 -> 1 | K30: =1+ASSUMPTIONS!C16 -> 1.035 | L30: =I30*J30*K30 -> 3.519 | M30: No | N30: 2" polyiso or XPS. Per SF. For roof and slab-on-grade conditions.
C31: 07 | D31: ROO-01 | E31: 07 52 16 | G31: Roof membrane replacement – EPDM 60-mil fully adhered | H31: SF | I31: 14.5 | J31: =ASSUMPTIONS!C12 -> 1 | K31: =1+ASSUMPTIONS!C16 -> 1.035 | L31: =I31*J31*K31 -> 15.0075 | M31: No | N31: Per SF of roof area. Includes new insulation, edge metal, drain modification. No structural deck.
N32: Per SF of below-grade wall. Crystalline or sheet membrane. Includes drainage board.
C33: 07 | D33: CLK-01 | E33: 07 92 00 | G33: Sealants and caulking – windows, penetrations, control joints | H33: LF | I33: 8.5 | J33: =ASSUMPTIONS!C12 -> 1 | K33: =1+ASSUMPTIONS!C16 -> 1.035 | L33: =I33*J33*K33 -> 8.7975 | M33: No | N33: Per LF of joint. Silicone at exterior; paintable latex at interior. Safety-compliant VOC.
B34: DIV 08 — OPENINGS
C35: 08 | D35: DOO-01 | E35: 08 11 13 | G35: Hollow metal door + frame + hardware set – standard interior | H35: EA | I35: 3950 | J35: =ASSUMPTIONS!C12 -> 1 | K35: =1+ASSUMPTIONS!C16 -> 1.035 | L35: =I35*J35*K35 -> 4088.25 | M35: No | N35: Complete unit. ADA lever handle, LCN closer, Von Duprin panic if required. 3'x8' standard.
C36: 08 | D36: DOO-02 | E36: 08 11 13 | G36: Hollow metal door + frame + hardware – IDD resident bedroom (ligature-resistant) | H36: EA | I36: 5200 | J36: =ASSUMPTIONS!C12 -> 1 | K36: =1+ASSUMPTIONS!C16 -> 1.035 | L36: =I36*J36*K36 -> 5382 | M36: Yes | N36: Allowance. Anti-ligature hardware required per DDDS licensing: recessed hinges, tamper-resistant.
C37: 08 | D37: DOO-03 | E37: 08 11 13 | G37: Hollow metal door + frame – medication room (keyed security) | H37: EA | I37: 4800 | J37: =ASSUMPTIONS!C12 -> 1 | K37: =1+ASSUMPTIONS!C16 -> 1.035 | L37: =I37*J37*K37 -> 4968 | M37: Yes | N37: Allowance. Controlled access hardware, security hinges, vision panel with film. DDDS required.
C38: 08 | D38: DOO-04 | E38: 08 11 16 | G38: Aluminum storefront entrance – main accessible entry | H38: EA | I38: 18500 | J38: =ASSUMPTIONS!C12 -> 1 | K38: =1+ASSUMPTIONS!C16 -> 1.035 | L38: =I38*J38*K38 -> 19147.5 | M38: Yes | N38: Allowance. Full-lite aluminum with ADA-compliant power door operator. Includes threshold and sill.
C39: 08 | D39: WIN-01 | E39: 08 51 13 | G39: Aluminum window replacement – existing school openings | H39: SF | I39: 72 | J39: =ASSUMPTIONS!C12 -> 1 | K39: =1+ASSUMPTIONS!C16 -> 1.035 | L39: =I39*J39*K39 -> 74.52 | M39: Yes | N39: Allowance. Per SF of rough opening. Thermally broken aluminum, Low-E glazing, Safety film interior.
B40: DIV 09 — FINISHES
C41: 09 | D41: GWB-01 | E41: 09 29 00 | G41: Gypsum wallboard partition – 3-5/8" metal stud, taped + primed (per face) | H41: SF | I41: 17.5 | J41: =ASSUMPTIONS!C12 -> 1 | K41: =1+ASSUMPTIONS!C16 -> 1.035 | L41: =I41*J41*K41 -> 18.1125 | M41: No | N41: Per face SF. Double for both faces. Type-X at corridor walls per NFPA 101.
C42: 09 | D42: GWB-02 | E42: 09 29 00 | G42: Gypsum wallboard – moisture-resistant (bathrooms, hygiene rooms) | H42: SF | I42: 19.5 | J42: =ASSUMPTIONS!C12 -> 1 | K42: =1+ASSUMPTIONS!C16 -> 1.035 | L42: =I42*J42*K42 -> 20.1825 | M42: No | N42: Per face SF. Cement board at wet areas behind tile. Required at all IDD bathroom walls.
C43: 09 | D43: ACT-01 | E43: 09 51 00 | G43: ACT ceiling – 2x2 grid + tile (standard occupied spaces) | H43: SF | I43: 9.25 | J43: =ASSUMPTIONS!C12 -> 1 | K43: =1+ASSUMPTIONS!C16 -> 1.035 | L43: =I43*J43*K43 -> 9.57375 | M43: No | N43: Standard 2x2 ACT. Includes grid, tile, suspension. Does not include MEP above.
C44: 09 | D44: ACT-02 | E44: 09 51 23 | G44: ACT ceiling – moisture-resistant tile (bathrooms, laundry) | H44: SF | I44: 11.5 | J44: =ASSUMPTIONS!C12 -> 1 | K44: =1+ASSUMPTIONS!C16 -> 1.035 | L44: =I44*J44*K44 -> 11.9025 | M44: No | N44: Moisture-resistant tile required at all wet areas per DDDS licensing.
C45: 09 | D45: GWB-03 | E45: 09 29 00 | G45: Gypsum board ceiling (drywall) – corridors and sensory rooms | H45: SF | I45: 12.75 | J45: =ASSUMPTIONS!C12 -> 1 | K45: =1+ASSUMPTIONS!C16 -> 1.035 | L45: =I45*J45*K45 -> 13.19625 | M45: No | N45: Drywall ceiling at corridors (fire rated) and sensory/quiet rooms. Smooth finish.
C46: 09 | D46: PAI-01 | E46: 09 91 00 | G46: Interior paint – standard 2-coat system (walls + ceiling) | H46: SF | I46: 3.95 | J46: =ASSUMPTIONS!C12 -> 1 | K46: =1+ASSUMPTIONS!C16 -> 1.035 | L46: =I46*J46*K46 -> 4.08825 | M46: No | N46: Per SF of surface. Low-VOC latex. IDD residential: eggshell at walls, flat at ceilings.
C47: 09 | D47: PAI-02 | E47: 09 91 00 | G47: Interior paint – semi-gloss (bathrooms, kitchens, medication rooms) | H47: SF | I47: 4.5 | J47: =ASSUMPTIONS!C12 -> 1 | K47: =1+ASSUMPTIONS!C16 -> 1.035 | L47: =I47*J47*K47 -> 4.6575 | M47: No | N47: Per SF. Semi-gloss for washability. Required at all wet + clinical areas.
C48: 09 | D48: PAI-03 | E48: 09 96 00 | G48: High-performance epoxy coating – mechanical and utility rooms | H48: SF | I48: 10.5 | J48: =ASSUMPTIONS!C12 -> 1 | K48: =1+ASSUMPTIONS!C16 -> 1.035 | L48: =I48*J48*K48 -> 10.8675 | M48: No | N48: 2-coat epoxy floor and wall system. Tnemec or equal. Floors + lower 4' of walls.
C49: 09 | D49: FLR-01 | E49: 09 65 13 | G49: LVT (luxury vinyl tile) – resident bedrooms and corridors | H49: SF | I49: 11.5 | J49: =ASSUMPTIONS!C12 -> 1 | K49: =1+ASSUMPTIONS!C16 -> 1.035 | L49: =I49*J49*K49 -> 11.9025 | M49: No | N49: Per SF. 6mm commercial LVT, wear layer ≥0.55mm. Forbo Allura or equal. Ease of cleaning for IDD.
C50: 09 | D50: FLR-02 | E50: 09 66 13 | G50: Ceramic tile – bathroom floors (slip-resistant, DCOF ≥0.42) | H50: SF | I50: 18.5 | J50: =ASSUMPTIONS!C12 -> 1 | K50: =1+ASSUMPTIONS!C16 -> 1.035 | L50: =I50*J50*K50 -> 19.1475 | M50: No | N50: Per SF. 12x12 or 12x24 porcelain. Slip-resistant per ADA/DDDS. Includes mortar bed.
C51: 09 | D51: FLR-03 | E51: 09 66 13 | G51: Ceramic tile – bathroom walls (wainscot to 72") | H51: SF | I51: 16.5 | J51: =ASSUMPTIONS!C12 -> 1 | K51: =1+ASSUMPTIONS!C16 -> 1.035 | L51: =I51*J51*K51 -> 17.0775 | M51: No | N51: Per SF of tile. 4x12 or subway tile. Epoxy grout at wet areas. Full-height at shower surrounds.
C52: 09 | D52: FLR-04 | E52: 09 65 16 | G52: Sheet vinyl – sensory rooms, therapy rooms (seamless, cushioned) | H52: SF | I52: 13.75 | J52: =ASSUMPTIONS!C12 -> 1 | K52: =1+ASSUMPTIONS!C16 -> 1.035 | L52: =I52*J52*K52 -> 14.23125 | M52: Yes | N52: Allowance. Seamless sheet vinyl preferred for IDD sensory environments. Forbo Marmoleum or equal.
C53: 09 | D53: FLR-05 | E53: 09 68 13 | G53: Carpet tile – therapy/activity rooms (soft zone, low-pile) | H53: SF | I53: 7.5 | J53: =ASSUMPTIONS!C12 -> 1 | K53: =1+ASSUMPTIONS!C16 -> 1.035 | L53: =I53*J53*K53 -> 7.7625 | M53: Yes | N53: Allowance. 24x24 carpet tile, GlasTac adhesive. IDD: pattern/color per OT recommendation.
C54: 09 | D54: ACC-01 | E54: 09 22 36 | G54: Corner guards – stainless steel, IDD corridor (full height) | H54: LF | I54: 42 | J54: =ASSUMPTIONS!C12 -> 1 | K54: =1+ASSUMPTIONS!C16 -> 1.035 | L54: =I54*J54*K54 -> 43.47 | M54: No | N54: Per LF. Stainless, mechanically anchored. Required at all IDD corridor corners. DDDS standard.
C55: 09 | D55: ACC-02 | E55: 09 22 36 | G55: Wall protection – chair rail and crash rail system | H55: LF | I55: 28.5 | J55: =ASSUMPTIONS!C12 -> 1 | K55: =1+ASSUMPTIONS!C16 -> 1.035 | L55: =I55*J55*K55 -> 29.4975 | M55: No | N55: Per LF of rail. PVC or rubber. 32" and 42" heights at residential corridors.
B56: DIV 10 — SPECIALTIES & EQUIPMENT
C57: 10 | D57: ACC-03 | E57: 10 28 00 | G57: Toilet accessories – ADA-compliant set (grab bars, dispenser, mirror) | H57: EA | I57: 1250 | J57: =ASSUMPTIONS!C12 -> 1 | K57: =1+ASSUMPTIONS!C16 -> 1.035 | L57: =I57*J57*K57 -> 1293.75 | M57: No | N57: Per bathroom. Includes (2) grab bars, TP dispenser, soap dispenser, ADA mirror. Bradley or equal.
C58: 10 | D58: ACC-04 | E58: 10 28 13 | G58: Ligature-resistant toilet accessories – IDD resident bathrooms | H58: EA | I58: 2200 | J58: =ASSUMPTIONS!C12 -> 1 | K58: =1+ASSUMPTIONS!C16 -> 1.035 | L58: =I58*J58*K58 -> 2277 | M58: Yes | N58: Allowance per DDDS requirement. Tamper-resistant, recessed, anti-ligature hardware throughout.
C59: 10 | D59: ACC-05 | E59: 10 26 00 | G59: Fire extinguisher cabinet – recessed, painted steel | H59: EA | I59: 485 | J59: =ASSUMPTIONS!C12 -> 1 | K59: =1+ASSUMPTIONS!C16 -> 1.035 | L59: =I59*J59*K59 -> 501.975 | M59: No | N59: Per cabinet. Includes extinguisher. Fire marshal placement per NFPA 10.
C60: 10 | D60: SIG-01 | E60: 10 14 23 | G60: ADA room sign – tactile (Braille + raised characters per ICC A117.1) | H60: EA | I60: 195 | J60: =ASSUMPTIONS!C12 -> 1 | K60: =1+ASSUMPTIONS!C16 -> 1.035 | L60: =I60*J60*K60 -> 201.825 | M60: No | N60: Per sign. Includes mounting hardware. Room ID, restroom, stair. Sign text from SIGNAGE PROGRAM tab.
C61: 10 | D61: SIG-02 | E61: 10 14 53 | G61: Wayfinding directional sign – interior wall-mounted | H61: EA | I61: 325 | J61: =ASSUMPTIONS!C12 -> 1 | K61: =1+ASSUMPTIONS!C16 -> 1.035 | L61: =I61*J61*K61 -> 336.375 | M61: Yes | N61: Allowance. Per sign location. System pricing in SIGNAGE PROGRAM tab (ALW-SGN-02).
C62: 10 | D62: NUR-01 | E62: 10 51 16 | G62: Nurse/staff call panel – resident room header unit | H62: EA | I62: 850 | J62: =ASSUMPTIONS!C12 -> 1 | K62: =1+ASSUMPTIONS!C16 -> 1.035 | L62: =I62*J62*K62 -> 879.75 | M62: Yes | N62: Allowance. Per room. Wired staff call with dome light at corridor. Rauland or equal.
C63: 10 | D63: NUR-02 | E63: 10 51 16 | G63: Nurse/staff call panel – corridor annunciator | H63: EA | I63: 1200 | J63: =ASSUMPTIONS!C12 -> 1 | K63: =1+ASSUMPTIONS!C16 -> 1.035 | L63: =I63*J63*K63 -> 1242 | M63: Yes | N63: Allowance. Per corridor zone. Ties to room call units. Coordinate with electrical.
C64: 10 | D64: WIN-02 | E64: 10 91 19 | G64: Window treatment – IDD residential (blackout, safety-cord-free) | H64: EA | I64: 385 | J64: =ASSUMPTIONS!C12 -> 1 | K64: =1+ASSUMPTIONS!C16 -> 1.035 | L64: =I64*J64*K64 -> 398.475 | M64: Yes | N64: Allowance per window. Cordless blackout shade. Anti-ligature specification required.
C65: 10 | D65: MIR-01 | E65: 10 28 13 | G65: Mirrors – stainless steel frameless (IDD residential bathrooms) | H65: EA | I65: 325 | J65: =ASSUMPTIONS!C12 -> 1 | K65: =1+ASSUMPTIONS!C16 -> 1.035 | L65: =I65*J65*K65 -> 336.375 | M65: No | N65: Per mirror. Shatter-resistant or polished stainless. Recessed or flush mount. DDDS standard.
B66: DIV 11 — EQUIPMENT (IDD Residential + Clinical)
C67: 11 | D67: EQP-01 | E67: 11 31 00 | G67: Residential kitchen equipment – dining service area | H67: LS | I67: 95000 | J67: =ASSUMPTIONS!C12 -> 1 | K67: =1+ASSUMPTIONS!C16 -> 1.035 | L67: =I67*J67*K67 -> 98325 | M67: Yes | N67: Allowance. Commercial-grade for IDD residential service: range, hood, refrigerators, dishwasher, serving line.
C68: 11 | D68: EQP-02 | E68: 11 31 16 | G68: Residential laundry equipment – per unit (washer + dryer) | H68: EA | I68: 4500 | J68: =ASSUMPTIONS!C12 -> 1 | K68: =1+ASSUMPTIONS!C16 -> 1.035 | L68: =I68*J68*K68 -> 4657.5 | M68: Yes | N68: Allowance per pair. Commercial-grade front-load, ADA-accessible controls. Speed Queen or equal.
C69: 11 | D69: EQP-03 | E69: 11 71 00 | G69: Medical equipment – medication dispensing unit (automated) | H69: EA | I69: 28000 | J69: =ASSUMPTIONS!C12 -> 1 | K69: =1+ASSUMPTIONS!C16 -> 1.035 | L69: =I69*J69*K69 -> 28980 | M69: Yes | N69: Allowance per floor. Omnicell or Pyxis system. Requires dedicated power, network, ventilation.
C70: 11 | D70: EQP-04 | E70: 11 72 00 | G70: Therapy equipment – sensory room (sensory swing, panels, lighting) | H70: LS | I70: 22000 | J70: =ASSUMPTIONS!C12 -> 1 | K70: =1+ASSUMPTIONS!C16 -> 1.035 | L70: =I70*J70*K70 -> 22770 | M70: Yes | N70: Allowance per sensory room. OT-specified: weighted swing, bubble column, tactile wall panels. IDD-specific.
C71: 11 | D71: EQP-05 | E71: 11 72 00 | G71: Therapy equipment – activity room (OT/PT standard package) | H71: LS | I71: 18000 | J71: =ASSUMPTIONS!C12 -> 1 | K71: =1+ASSUMPTIONS!C16 -> 1.035 | L71: =I71*J71*K71 -> 18630 | M71: Yes | N71: Allowance per therapy room. Balance beams, mats, therapy balls, storage. OT program-specific.
C72: 11 | D72: EQP-06 | E72: 11 82 16 | G72: Residential furniture – IDD resident bedroom (bed, dresser, desk, chair) | H72: EA | I72: 3800 | J72: =ASSUMPTIONS!C12 -> 1 | K72: =1+ASSUMPTIONS!C16 -> 1.035 | L72: =I72*J72*K72 -> 3933 | M72: Yes | N72: Allowance per room. Residential-grade, ADA-compatible, anti-tip anchored. 112 rooms.
B73: DIV 12 — FURNISHINGS
C74: 12 | D74: FUR-01 | E74: 12 21 13 | G74: Window blinds – cordless, blackout (see also WIN-02 for IDD) | H74: EA | I74: 285 | J74: =ASSUMPTIONS!C12 -> 1 | K74: =1+ASSUMPTIONS!C16 -> 1.035 | L74: =I74*J74*K74 -> 294.975 | M74: Yes | N74: Allowance. Standard non-IDD areas: offices, therapy, dining. Cordless specification throughout.
C75: 12 | D75: FUR-02 | E75: 12 56 00 | G75: Common area furnishings – dining (tables, chairs, per seat) | H75: EA | I75: 385 | J75: =ASSUMPTIONS!C12 -> 1 | K75: =1+ASSUMPTIONS!C16 -> 1.035 | L75: =I75*J75*K75 -> 398.475 | M75: Yes | N75: Allowance per seat. Commercial-grade, stackable chairs. ADA-compliant table heights.
C76: 12 | D76: FUR-03 | E76: 12 56 00 | G76: Common area furnishings – therapy/activity room (lounge seating) | H76: LS | I76: 12000 | J76: =ASSUMPTIONS!C12 -> 1 | K76: =1+ASSUMPTIONS!C16 -> 1.035 | L76: =I76*J76*K76 -> 12420 | M76: Yes | N76: Allowance per room. Cleanable upholstery, residential scale, IDD-appropriate selection.
B77: DIV 21 — FIRE SUPPRESSION
C78: 21 | D78: FPS-01 | E78: 21 13 13 | G78: NFPA 13 wet-pipe sprinkler system – new throughout building | H78: SF | I78: 8.5 | J78: =ASSUMPTIONS!C12 -> 1 | K78: =1+ASSUMPTIONS!C16 -> 1.035 | L78: =I78*J78*K78 -> 8.7975 | M78: No | N78: Per SF GFA. Full building NFPA 13 required for IBC R-4 IDD residential. Includes riser, heads, piping.
C79: 21 | D79: FPS-02 | E79: 21 13 13 | G79: Sprinkler head replacement / reconfiguration (existing partial system) | H79: EA | I79: 185 | J79: =ASSUMPTIONS!C12 -> 1 | K79: =1+ASSUMPTIONS!C16 -> 1.035 | L79: =I79*J79*K79 -> 191.475 | M79: No | N79: Per head. If partial system exists and requires reconfiguration to meet NFPA 13.
B80: DIV 22 — PLUMBING
C81: 22 | D81: PLB-01 | E81: 22 11 16 | G81: Plumbing rough-in and trim – new bathroom (complete fixture group) | H81: EA | I81: 14500 | J81: =ASSUMPTIONS!C12 -> 1 | K81: =1+ASSUMPTIONS!C16 -> 1.035 | L81: =I81*J81*K81 -> 15007.5 | M81: No | N81: Per bathroom. Includes water closet, lavatory, shower (if applicable), piping, waste, vent.
C82: 22 | D82: PLB-02 | E82: 22 11 16 | G82: Plumbing fixture – ADA water closet (wall-hung, anti-ligature flush) | H82: EA | I82: 2200 | J82: =ASSUMPTIONS!C12 -> 1 | K82: =1+ASSUMPTIONS!C16 -> 1.035 | L82: =I82*J82*K82 -> 2277 | M82: Yes | N82: Allowance. Anti-ligature flush valve per DDDS. Wall-hung for cleaning access. Sloan or Zurn.
C83: 22 | D83: PLB-03 | E83: 22 11 16 | G83: Plumbing fixture – ADA lavatory (wall-hung, insulated P-trap) | H83: EA | I83: 1450 | J83: =ASSUMPTIONS!C12 -> 1 | K83: =1+ASSUMPTIONS!C16 -> 1.035 | L83: =I83*J83*K83 -> 1500.75 | M83: Yes | N83: Allowance. Insulated P-trap per ADA scald protection. Anti-ligature faucet for IDD bathrooms.
C84: 22 | D84: PLB-04 | E84: 22 35 00 | G84: Domestic hot water heater – commercial (per 20-resident zone) | H84: EA | I84: 8500 | J84: =ASSUMPTIONS!C12 -> 1 | K84: =1+ASSUMPTIONS!C16 -> 1.035 | L84: =I84*J84*K84 -> 8797.5 | M84: No | N84: Per water heater zone. High-recovery commercial unit. Tempering valve required at IDD bathrooms.
C85: 22 | D85: PLB-05 | E85: 22 11 16 | G85: Plumbing rough-in – kitchen equipment connections | H85: LS | I85: 18000 | J85: =ASSUMPTIONS!C12 -> 1 | K85: =1+ASSUMPTIONS!C16 -> 1.035 | L85: =I85*J85*K85 -> 18630 | M85: No | N85: Lump sum allowance for kitchen rough plumbing. Gas (if applicable) priced separately.
B86: DIV 23 — HVAC
C87: 23 | D87: HVA-01 | E87: 23 05 00 | G87: HVAC system replacement – residential unit ventilators (per room) | H87: EA | I87: 4800 | J87: =ASSUMPTIONS!C12 -> 1 | K87: =1+ASSUMPTIONS!C16 -> 1.035 | L87: =I87*J87*K87 -> 4968 | M87: No | N87: Per resident room. Unit ventilator with individual zone control. IDD residential: independent room control required.
C88: 23 | D88: HVA-02 | E88: 23 05 00 | G88: HVAC ductwork and distribution – common areas | H88: SF | I88: 18.5 | J88: =ASSUMPTIONS!C12 -> 1 | K88: =1+ASSUMPTIONS!C16 -> 1.035 | L88: =I88*J88*K88 -> 19.1475 | M88: No | N88: Per SF of common area (dining, therapy, corridors). Includes duct, diffusers, VAV if applicable.
C89: 23 | D89: HVA-03 | E89: 23 82 19 | G89: Bathroom exhaust fan – continuous, code minimum (50 CFM) | H89: EA | I89: 485 | J89: =ASSUMPTIONS!C12 -> 1 | K89: =1+ASSUMPTIONS!C16 -> 1.035 | L89: =I89*J89*K89 -> 501.975 | M89: No | N89: Per bathroom. DDDS: continuous exhaust required in all resident bathrooms. Include backdraft damper.
C90: 23 | D90: HVA-04 | E90: 23 05 93 | G90: HVAC controls and BAS (Building Automation System) integration | H90: LS | I90: 65000 | J90: =ASSUMPTIONS!C12 -> 1 | K90: =1+ASSUMPTIONS!C16 -> 1.035 | L90: =I90*J90*K90 -> 67275 | M90: Yes | N90: Allowance. Entire building controls package. Includes thermostats, sensors, BAS integration, commissioning.
C91: 23 | D91: HVA-05 | E91: 23 82 00 | G91: Kitchen exhaust hood and make-up air system | H91: LS | I91: 45000 | J91: =ASSUMPTIONS!C12 -> 1 | K91: =1+ASSUMPTIONS!C16 -> 1.035 | L91: =I91*J91*K91 -> 46575 | M91: Yes | N91: Allowance. Commercial UL-listed hood, fire suppression tie-in, make-up air unit. Health dept. compliance.
B92: DIV 26 — ELECTRICAL
C93: 26 | D93: ELC-01 | E93: 26 05 00 | G93: Electrical service upgrade – new main switchgear and distribution | H93: LS | I93: 185000 | J93: =ASSUMPTIONS!C12 -> 1 | K93: =1+ASSUMPTIONS!C16 -> 1.035 | L93: =I93*J93*K93 -> 191475 | M93: No | N93: Allowance. Full service upgrade for IDD residential + clinical loads. Coordinate with utility for transformer.
C94: 26 | D94: ELC-02 | E94: 26 05 19 | G94: Electrical wiring – resident room circuit package (lights, outlets, call) | H94: EA | I94: 3200 | J94: =ASSUMPTIONS!C12 -> 1 | K94: =1+ASSUMPTIONS!C16 -> 1.035 | L94: =I94*J94*K94 -> 3312 | M94: No | N94: Per resident room. Includes branch circuits, devices, nurse call rough-in. Tamper-resistant outlets required.
C95: 26 | D95: ELC-03 | E95: 26 05 19 | G95: Electrical wiring – bathroom (GFI circuits, exhaust, lighting) | H95: EA | I95: 1850 | J95: =ASSUMPTIONS!C12 -> 1 | K95: =1+ASSUMPTIONS!C16 -> 1.035 | L95: =I95*J95*K95 -> 1914.75 | M95: No | N95: Per bathroom. GFCI throughout, exhaust fan circuit, vanity lighting, night light circuit.
C96: 26 | D96: ELC-04 | E96: 26 51 00 | G96: Lighting fixture – LED corridor/common area (fixture + lamp) | H96: EA | I96: 385 | J96: =ASSUMPTIONS!C12 -> 1 | K96: =1+ASSUMPTIONS!C16 -> 1.035 | L96: =I96*J96*K96 -> 398.475 | M96: No | N96: Per fixture. Commercial LED, 0-10V dimming, correlated color 3000K. IDD: warm neutral tones preferred.
C97: 26 | D97: ELC-05 | E97: 26 51 00 | G97: Lighting fixture – LED resident bedroom (ceiling, dimmable) | H97: EA | I97: 285 | J97: =ASSUMPTIONS!C12 -> 1 | K97: =1+ASSUMPTIONS!C16 -> 1.035 | L97: =I97*J97*K97 -> 294.975 | M97: No | N97: Per fixture. Residential-scale LED, flush mount, dimmable. IDD: no strobing or harsh color temp.
C98: 26 | D98: ELC-06 | E98: 26 09 26 | G98: Occupancy sensor – resident room and common area | H98: EA | I98: 165 | J98: =ASSUMPTIONS!C12 -> 1 | K98: =1+ASSUMPTIONS!C16 -> 1.035 | L98: =I98*J98*K98 -> 170.775 | M98: No | N98: Per sensor. Required for energy code. PIR or dual-technology. Delay setting for IDD populations.
C99: 26 | D99: ELC-07 | E99: 26 32 13 | G99: Emergency generator – diesel standby (per required KVA) | H99: KVA | I99: 850 | J99: =ASSUMPTIONS!C12 -> 1 | K99: =1+ASSUMPTIONS!C16 -> 1.035 | L99: =I99*J99*K99 -> 879.75 | M99: Yes | N99: Allowance per KVA. NFPA 99/110 Type 10 for IDD residential. Includes ATS, enclosure, fuel tank.
C100: 26 | D100: ELC-08 | E100: 26 27 26 | G100: Tamper-resistant outlet covers / safety outlets throughout | H100: EA | I100: 38 | J100: =ASSUMPTIONS!C12 -> 1 | K100: =1+ASSUMPTIONS!C16 -> 1.035 | L100: =I100*J100*K100 -> 39.33 | M100: No | N100: Per outlet. TR outlets required per NEC 406.12 and DDDS licensing. All resident areas.
B101: DIV 27 — COMMUNICATIONS
...

Sheet TAKEOFF
B2: QUANTITY TAKEOFF — M-Well Community Health Campus · Phase 1: School Building Renovation (IDD Residential, 27,452 SF)
B3: Enter quantities in column L (Quantity). Column M (Adj. Unit Cost) pulls automatically from UNIT PRICE LIBRARY via VLOOKUP on Cost Code. Column N (Line Total) = L × M. Column O (Included?) controls BID SUMMARY: enter 'Yes', 'No', or 'Allowance'. Add rows above the SUBTOTAL row. Do not modify formulas in L or M.
B4: B | C4: Floor | D4: Area / Zone | E4: Div | F4: Spec Section | G4: Bid Package | H4: Cost Code | I4: Scope Item | J4: Unit | K4: Quantity Source | L4: Quantity | M4: Adj. Unit Cost (from Library) | N4: Line Total | O4: Included? | P4: Comments
B5: FLOOR 1 — PHASE 1A: Partial Fit-Out + Full Building Life-Safety Backbone
C6: 1F | D6: Entire Building | E6: 02 | F6: 02 41 19 | H6: DEM-01 | I6: Selective demolition – interior partitions and finishes | J6: SF | K6: 27,452 SF × 65% demo factor | L6: 17844 | M6: =IFERROR(VLOOKUP(H6,'UNIT PRICE LIBRARY'!D:L,9,FALSE()),0) -> 4.6575 | N6: =IF(O6="No",0,L6*M6) -> 83108.43 | O6: Yes | P6: 65% of GFA requires interior demolition. Excludes areas to remain.
C7: 1F | D7: Entire Building | E7: 02 | F7: 02 41 19 | H7: DEM-02 | I7: Selective demolition – existing ceilings (ACT + drywall) | J7: SF | K7: 27,452 SF GFA | L7: 27452 | M7: =IFERROR(VLOOKUP(H7,'UNIT PRICE LIBRARY'!D:L,9,FALSE()),0) -> 3.36375 | N7: =IF(O7="No",0,L7*M7) -> 92341.665 | O7: Yes | P7: Full ceiling demolition required to run new MEP backbone.
C8: 1F | D8: Entire Building | E8: 02 | F8: 02 41 19 | H8: DEM-03 | I8: Selective demolition – existing doors, frames (to be replaced) | J8: EA | K8: Count existing | L8: 65 | M8: =IFERROR(VLOOKUP(H8,'UNIT PRICE LIBRARY'!D:L,9,FALSE()),0) -> 294.975 | N8: =IF(O8="No",0,L8*M8) -> 19173.375 | O8: Yes | P8: Replace 65 of estimated 80 door openings. Retain serviceable openings.
C9: 1F | D9: Entire Building | E9: 02 | F9: 02 41 19 | H9: DEM-04 | I9: Selective demolition – existing flooring throughout | J9: SF | K9: 27,452 SF GFA | L9: 27452 | M9: =IFERROR(VLOOKUP(H9,'UNIT PRICE LIBRARY'!D:L,9,FALSE()),0) -> 2.84625 | N9: =IF(O9="No",0,L9*M9) -> 78135.255 | O9: Yes | P9: Full flooring removal for new finishes and substrate prep.
C10: 1F | D10: Entire Building | E10: 02 | F10: HAZ-01 | H10: HAZ-01 | I10: Asbestos abatement – floor tile and mastic (pre-1980 school) | J10: SF | K10: Estimated 40% of floor area | L10: 10981 | M10: =IFERROR(VLOOKUP(H10,'UNIT PRICE LIBRARY'!D:L,9,FALSE()),0) -> 18.63 | N10: =IF(O10="No",0,L10*M10) -> 204576.03 | O10: Yes | P10: Pre-1980 building: assume 40% of floor area affected. Phase I ESA to confirm.
C11: 1F | D11: Corridors + Stairs | E11: 03 | F11: 03 30 00 | H11: CON-01 | I11: Concrete slab patch / repair – corridors and damaged areas | J11: SF | K11: Estimated 15% of slab | L11: 4118 | M11: =IFERROR(VLOOKUP(H11,'UNIT PRICE LIBRARY'!D:L,9,FALSE()),0) -> 22.77 | N11: =IF(O11="No",0,L11*M11) -> 93766.86 | O11: Yes | P11: 15% of floor area patching assumed for pre-1980 slab.
C12: 1F | D12: Elevator Shaft | E12: 03 | F12: 03 30 00 | H12: CON-03 | I12: Elevator pit – concrete liner, waterproofing, sump | J12: LS | K12: 1 shaft | L12: 1 | M12: =IFERROR(VLOOKUP(H12,'UNIT PRICE LIBRARY'!D:L,9,FALSE()),0) -> 19147.5 | N12: =IF(O12="No",0,L12*M12) -> 19147.5 | O12: Yes | P12: Phase 1A: shaft shell + pit only. Cab installed in Phase 1B.
C13: 1F | D13: Entire Building | E13: 04 | F13: 04 22 00 | H13: MAS-01 | I13: CMU infill – new program openings to be closed | J13: SF | K13: Estimated 8 openings × 40 SF | L13: 320 | M13: =IFERROR(VLOOKUP(H13,'UNIT PRICE LIBRARY'!D:L,9,FALSE()),0) -> 33.12 | N13: =IF(O13="No",0,L13*M13) -> 10598.4 | O13: Yes | P13: New program partitions require closure of some existing openings.
C14: 1F | D14: Corridors + Stairs | E14: 05 | F14: 05 52 13 | H14: MET-01 | I14: Stainless steel handrail – IDD residential corridors (both sides) | J14: LF | K14: Corridor LF × 2 sides × 2 floors ÷ 2 | L14: 520 | M14: =IFERROR(VLOOKUP(H14,'UNIT PRICE LIBRARY'!D:L,9,FALSE()),0) -> 191.475 | N14: =IF(O14="No",0,L14*M14) -> 99567 | O14: Yes | P14: 520 LF of corridor on Floor 1. Both sides per DDDS. Stainless for hygiene.
C15: 1F | D15: Stairs A + B | E15: 05 | F15: 05 52 13 | H15: MET-02 | I15: Aluminum guardrail – stair A and B open-to-below | J15: LF | K15: 2 stairs × 28 LF each | L15: 56 | M15: =IFERROR(VLOOKUP(H15,'UNIT PRICE LIBRARY'!D:L,9,FALSE()),0) -> 377.775 | N15: =IF(O15="No",0,L15*M15) -> 21155.4 | O15: Yes | P15: IBC 42" guardrail at open stair conditions.
C16: 1F | D16: New Partitions | E16: 05 | F16: 05 40 00 | H16: MET-03 | I16: Light gauge steel framing – new IDD program partitions | J16: SF | K16: New partition area (both faces) 6,400 SF | L16: 6400 | M16: =IFERROR(VLOOKUP(H16,'UNIT PRICE LIBRARY'!D:L,9,FALSE()),0) -> 8.7975 | N16: =IF(O16="No",0,L16*M16) -> 56304 | O16: Yes | P16: New partitions for program rooms on Floor 1. Both faces included.
C17: 1F | D17: Elevator Shaft | E17: 05 | F17: 05 51 13 | H17: MET-04 | I17: Steel elevator shaft framing + structural support | J17: LS | K17: 1 shaft | L17: 1 | M17: =IFERROR(VLOOKUP(H17,'UNIT PRICE LIBRARY'!D:L,9,FALSE()),0) -> 28980 | N17: =IF(O17="No",0,L17*M17) -> 28980 | O17: Yes | P17: Shaft steel, pit angle, guide rail embeds. Cab by owner in Phase 1B.
... C28: 1F | D28: Corridors + Common | E28: 09 | F28: GWB-01 | H28: GWB-01 | I28: GWB partition – new IDD program partitions (per face) | J28: SF | K28: New partition area (both faces) | L28: 6400 | M28: =IFERROR(VLOOKUP(H28,'UNIT PRICE LIBRARY'!D:L,9,FALSE()),0) -> 18.1125 | N28: =IF(O28="No",0,L28*M28) -> 115920 | O28: Yes | P28: Type-X GWB at corridor walls per NFPA 101 § 18/19.
M29: =IFERROR(VLOOKUP(H29,'UNIT PRICE LIBRARY'!D:L,9,FALSE()),0) -> 0 | N29: =IF(O29="No",0,L29*M29) -> 0 | O29: Yes | P29: Cement board at tile areas; moisture-resistant GWB elsewhere in wet rooms.
P30: Excludes resident rooms (drywall) and bathrooms (MR tile).
C31: 1F | D31: Bathrooms | E31: 09 | F31: 09 51 23 | H31: ACT-02 | I31: ACT ceiling – moisture-resistant (all bathrooms + laundry) | J31: SF | K31: 42 bathrooms × 80 SF + laundry 100 SF | L31: 3460 | M31: =IFERROR(VLOOKUP(H31,'UNIT PRICE LIBRARY'!D:L,9,FALSE()),0) -> 11.9025 | N31: =IF(O31="No",0,L31*M31) -> 41182.65 | O31: Yes | P31: MR tile or MR ACT at all wet rooms per DDDS.
C32: 1F | D32: Resident Rooms + Stairs | E32: 09 | F32: 09 29 00 | H32: GWB-03 | I32: Drywall ceiling – resident bedrooms and sensory rooms | J32: SF | K32: 35 rooms × 180 SF avg ceiling | L32: 6300 | M32: =IFERROR(VLOOKUP(H32,'UNIT PRICE LIBRARY'!D:L,9,FALSE()),0) -> 13.19625 | N32: =IF(O32="No",0,L32*M32) -> 83136.375 | O32: Yes | P32: Smooth drywall ceiling at resident rooms. Sensory rooms: full smooth interior.
C33: 1F | D33: Common Areas | E33: 09 | F33: 09 91 00 | H33: PAI-01 | I33: Interior paint – standard 2-coat (walls + ceilings, all spaces) | J33: SF | K33: 27,452 SF × 2.8 surface factor | L33: 76866 | M33: =IFERROR(VLOOKUP(H33,'UNIT PRICE LIBRARY'!D:L,9,FALSE()),0) -> 4.08825 | N33: =IF(O33="No",0,L33*M33) -> 314247.42 | O33: Yes | P33: 2.8× surface factor for walls + ceiling. Low-VOC required throughout.
C34: 1F | D34: Bathrooms + Kitchens | E34: 09 | F34: 09 91 00 | H34: PAI-02 | I34: Interior paint – semi-gloss (all wet and clinical areas) | J34: SF | K34: Bathroom + kitchen wall SF | L34: 12400 | M34: =IFERROR(VLOOKUP(H34,'UNIT PRICE LIBRARY'!D:L,9,FALSE()),0) -> 4.6575 | N34: =IF(O34="No",0,L34*M34) -> 57753 | O34: Yes | P34: Semi-gloss for washability at all wet areas and medication rooms.
C35: 1F | D35: Mechanical + Utility | E35: 09 | F35: 09 96 00 | H35: PAI-03 | I35: High-performance epoxy coating – mechanical and utility rooms | J35: SF | K35: Mech 320 SF + utility 200 SF | L35: 520 | M35: =IFERROR(VLOOKUP(H35,'UNIT PRICE LIBRARY'!D:L,9,FALSE()),0) -> 10.8675 | N35: =IF(O35="No",0,L35*M35) -> 5651.1 | O35: Yes | P35: Epoxy floor and wall at all mechanical/electrical rooms.
C36: 1F | D36: Resident Rooms + Corridors | E36: 09 | F36: 09 65 13 | H36: FLR-01 | I36: LVT flooring – resident bedrooms and corridors (6mm commercial) | J36: SF | K36: Rooms 9,000 SF + corridors 4,200 SF | L36: 13200 | M36: =IFERROR(VLOOKUP(H36,'UNIT PRICE LIBRARY'!D:L,9,FALSE()),0) -> 11.9025 | N36: =IF(O36="No",0,L36*M36) -> 157113 | O36: Yes | P36: Commercial LVT throughout residential areas. Ease of cleaning key for IDD program.
C37: 1F | D37: Bathrooms | E37: 09 | F37: 09 66 13 | H37: FLR-02 | I37: Ceramic tile – bathroom floors (slip-resistant, DCOF ≥0.42) | J37: SF | K37: 42 bathrooms × 80 SF | L37: 3360 | M37: =IFERROR(VLOOKUP(H37,'UNIT PRICE LIBRARY'!D:L,9,FALSE()),0) -> 19.1475 | N37: =IF(O37="No",0,L37*M37) -> 64335.6 | O37: Yes | P37: Slip-resistant porcelain. ADA-compliant DCOF. Required at all IDD bathrooms.
C38: 1F | D38: Bathrooms | E38: 09 | F38: 09 66 13 | H38: FLR-03 | I38: Ceramic tile – bathroom walls (wainscot to 72") | J38: SF | K38: 42 bathrooms × 240 SF walls to 72" | L38: 10080 | M38: =IFERROR(VLOOKUP(H38,'UNIT PRICE LIBRARY'!D:L,9,FALSE()),0) -> 17.0775 | N38: =IF(O38="No",0,L38*M38) -> 172141.2 | O38: Yes | P38: Full tile wainscot at all resident bathrooms per DDDS hygiene standards.
C39: 1F | D39: Sensory Rooms | E39: 09 | F39: 09 65 16 | H39: FLR-04 | I39: Sheet vinyl – sensory rooms (seamless, cushioned, impact-absorbing) | J39: SF | K39: 2 sensory rooms × 280 SF | L39: 560 | M39: =IFERROR(VLOOKUP(H39,'UNIT PRICE LIBRARY'!D:L,9,FALSE()),0) -> 14.23125 | N39: =IF(O39="No",0,L39*M39) -> 7969.5 | O39: Allowance | P39: Forbo Marmoleum or equal. OT-specified. Color/pattern TBD by OT program.
C40: 1F | D40: Therapy Rooms | E40: 09 | F40: 09 68 13 | H40: FLR-05 | I40: Carpet tile – therapy and activity rooms (soft zone) | J40: SF | K40: 3 therapy rooms × 420 SF avg | L40: 1260 | M40: =IFERROR(VLOOKUP(H40,'UNIT PRICE LIBRARY'!D:L,9,FALSE()),0) -> 7.7625 | N40: =IF(O40="No",0,L40*M40) -> 9780.75 | O40: Allowance | P40: 24x24 carpet tile. IDD: pattern and color per OT recommendation. Avoid strong patterns.
C41: 1F | D41: IDD Corridors | E41: 09 | F41: 09 22 36 | H41: ACC-01 | I41: Corner guards – stainless steel IDD corridors (full height) | J41: LF | K41: Corridor LF × 4 corners per bay × est. factor | L41: 280 | M41: =IFERROR(VLOOKUP(H41,'UNIT PRICE LIBRARY'!D:L,9,FALSE()),0) -> 43.47 | N41: =IF(O41="No",0,L41*M41) -> 12171.6 | O41: Yes | P41: All IDD corridor corners. Full height stainless. DDDS standard requirement.
C42: 1F | D42: IDD Corridors | E42: 09 | F42: 09 22 36 | H42: ACC-02 | I42: Wall protection – chair rail and crash rail system | J42: LF | K42: Corridor LF × 2 sides | L42: 1040 | M42: =IFERROR(VLOOKUP(H42,'UNIT PRICE LIBRARY'!D:L,9,FALSE()),0) -> 29.4975 | N42: =IF(O42="No",0,L42*M42) -> 30677.4 | O42: Yes | P42: 32" and 42" rails at residential corridors. Protects walls and residents.
... C55: 1F | D55: Therapy Rooms | E55: 11 | F55: 11 72 00 | H55: EQP-05 | I55: Therapy room equipment package (OT/PT standard) | J55: LS | K55: 3 therapy rooms | L55: 3 | M55: =IFERROR(VLOOKUP(H55,'UNIT PRICE LIBRARY'!D:L,9,FALSE()),0) -> 18630 | N55: =IF(O55="No",0,L55*M55) -> 55890 | O55: Allowance | P55: Balance beams, therapy mats, balls, storage. Scope from OT program guide.
B56: FULL BUILDING — Life-Safety + MEP Backbone (Phase 1A — Non-Negotiable Scope)
C57: BLDG | D57: Entire Building | E57: 21 | F57: 21 13 13 | H57: FPS-01 | I57: NFPA 13 wet-pipe sprinkler system – full building (27,452 SF) | J57: SF | K57: Full building GFA | L57: 27452 | M57: =IFERROR(VLOOKUP(H57,'UNIT PRICE LIBRARY'!D:L,9,FALSE()),0) -> 8.7975 | N57: =IF(O57="No",0,L57*M57) -> 241508.97 | O57: Yes | P57: Full building NFPA 13 required for IBC R-4 IDD residential. Cannot phase. Install entire building in Phase 1A.
C58: BLDG | D58: Entire Building | E58: 22 | F58: 22 11 16 | H58: PLB-01 | I58: Plumbing rough-in + trim – new bathrooms (complete fixture group) | J58: EA | K58: 42 bathrooms | L58: 42 | M58: =IFERROR(VLOOKUP(H58,'UNIT PRICE LIBRARY'!D:L,9,FALSE()),0) -> 15007.5 | N58: =IF(O58="No",0,L58*M58) -> 630315 | O58: Yes | P58: Full plumbing at all bathrooms. WC, lavatory, shower where applicable. Full waste/vent runs.
C59: BLDG | D59: Resident Bathrooms | E59: 22 | F59: 22 11 16 | H59: PLB-02 | I59: ADA anti-ligature water closet (wall-hung, DDDS) | J59: EA | K59: 35 resident bathrooms | L59: 35 | M59: =IFERROR(VLOOKUP(H59,'UNIT PRICE LIBRARY'!D:L,9,FALSE()),0) -> 2277 | N59: =IF(O59="No",0,L59*M59) -> 79695 | O59: Yes | P59: Anti-ligature flush valve required per DDDS at all resident bathrooms.
C60: BLDG | D60: Resident Bathrooms | E60: 22 | F60: 22 11 16 | H60: PLB-03 | I60: ADA lavatory (wall-hung, insulated P-trap) | J60: EA | K60: 35 resident bathrooms | L60: 35 | M60: =IFERROR(VLOOKUP(H60,'UNIT PRICE LIBRARY'!D:L,9,FALSE()),0) -> 1500.75 | N60: =IF(O60="No",0,L60*M60) -> 52526.25 | O60: Yes | P60: Anti-scald protection, insulated P-trap, anti-ligature faucet.
C61: BLDG | D61: Mechanical Rooms | E61: 22 | F61: 22 35 00 | H61: PLB-04 | I61: Domestic hot water heaters – commercial (1 per 20-resident zone) | J61: EA | K61: 6 zones for 112 residents | L61: 6 | M61: =IFERROR(VLOOKUP(H61,'UNIT PRICE LIBRARY'!D:L,9,FALSE()),0) -> 8797.5 | N61: =IF(O61="No",0,L61*M61) -> 52785 | O61: Yes | P61: High-recovery commercial units with tempering valves for safety.
C62: BLDG | D62: Kitchen | E62: 22 | F62: 22 11 16 | H62: PLB-05 | I62: Kitchen plumbing rough-in – dining service equipment connections | J62: LS | K62: 1 kitchen | L62: 1 | M62: =IFERROR(VLOOKUP(H62,'UNIT PRICE LIBRARY'!D:L,9,FALSE()),0) -> 18630 | N62: =IF(O62="No",0,L62*M62) -> 18630 | O62: Yes | P62: All kitchen equipment rough plumbing. Gas (if applicable) priced separately.
C63: BLDG | D63: Resident Rooms | E63: 23 | F63: 23 05 00 | H63: HVA-01 | I63: HVAC – unit ventilators with individual zone control (per room) | J63: EA | K63: 35 resident rooms | L63: 35 | M63: =IFERROR(VLOOKUP(H63,'UNIT PRICE LIBRARY'!D:L,9,FALSE()),0) -> 4968 | N63: =IF(O63="No",0,L63*M63) -> 173880 | O63: Yes | P63: Individual zone control required per DDDS for resident comfort and infection control.
C64: BLDG | D64: Common Areas | E64: 23 | F64: 23 05 00 | H64: HVA-02 | I64: HVAC ductwork + distribution – common areas (dining, therapy, corridors) | J64: SF | K64: Common area SF approx 8,000 | L64: 8000 | M64: =IFERROR(VLOOKUP(H64,'UNIT PRICE LIBRARY'!D:L,9,FALSE()),0) -> 19.1475 | N64: =IF(O64="No",0,L64*M64) -> 153180 | O64: Yes | P64: Includes ductwork, diffusers, VAV boxes as required. Full HVAC for common program areas.
C65: BLDG | D65: All Bathrooms | E65: 23 | F65: 23 82 19 | H65: HVA-03 | I65: Bathroom exhaust fans – continuous code-minimum (42 bathrooms) | J65: EA | K65: 42 bathrooms + 4 utility rooms | L65: 46 | M65: =IFERROR(VLOOKUP(H65,'UNIT PRICE LIBRARY'!D:L,9,FALSE()),0) -> 501.975 | N65: =IF(O65="No",0,L65*M65) -> 23090.85 | O65: Yes | P65: DDDS requires continuous exhaust at all resident bathrooms. Includes backdraft dampers.
C66: BLDG | D66: Entire Building | E66: 23 | F66: 23 05 93 | H66: HVA-04 | I66: HVAC controls + BAS integration – entire building | J66: LS | K66: 1 building | L66: 1 | M66: =IFERROR(VLOOKUP(H66,'UNIT PRICE LIBRARY'!D:L,9,FALSE()),0) -> 67275 | N66: =IF(O66="No",0,L66*M66) -> 67275 | O66: Yes | P66: Full controls package. BAS integration for monitoring and energy code compliance.
C67: BLDG | D67: Kitchen | E67: 23 | F67: 23 82 00 | H67: HVA-05 | I67: Kitchen exhaust hood + make-up air system | J67: LS | K67: 1 kitchen | L67: 1 | M67: =IFERROR(VLOOKUP(H67,'UNIT PRICE LIBRARY'!D:L,9,FALSE()),0) -> 46575 | N67: =IF(O67="No",0,L67*M67) -> 46575 | O67: Yes | P67: UL-listed commercial hood, fire suppression tie-in, make-up air unit. Health dept. required.
C68: BLDG | D68: Entire Building | E68: 26 | F68: 26 05 00 | H68: ELC-01 | I68: Electrical service upgrade – new main switchgear + distribution | J68: LS | K68: 1 building | L68: 1 | M68: =IFERROR(VLOOKUP(H68,'UNIT PRICE LIBRARY'!D:L,9,FALSE()),0) -> 191475 | N68: =IF(O68="No",0,L68*M68) -> 191475 | O68: Yes | P68: Full service upgrade for IDD residential + clinical loads. Coordinate with utility for transformer.
... C82: BLDG | D82: Key Locations | E82: 27 | F82: 27 41 21 | H82: COM-05 | I82: CCTV security cameras – entries, corridors, common areas | J82: EA | K82: Estimated 18 cameras | L82: 18 | M82: =IFERROR(VLOOKUP(H82,'UNIT PRICE LIBRARY'!D:L,9,FALSE()),0) -> 1707.75 | N82: =IF(O82="No",0,L82*M82) -> 30739.5 | O82: Allowance | P82: IP cameras with NVR. Required at entries, corridors, common areas per DDDS.
B83: SITE — Phase 1 School Building (Immediate Accessible Site Improvements)
C84: SITE | D84: Parking Area | E84: 32 | F84: 32 12 16 | H84: SIT-01 | I84: Accessible parking surface – ADA-compliant spaces and markings | J84: SY | K84: 12 accessible spaces × 35 SY each | L84: 420 | M84: =IFERROR(VLOOKUP(H84,'UNIT PRICE LIBRARY'!D:L,9,FALSE()),0) -> 67.275 | N84: =IF(O84="No",0,L84*M84) -> 28255.5 | O84: Yes | P84: ADA van-accessible + standard accessible spaces. 12 minimum for 112-bed IDD residential.
C85: SITE | D85: Accessible Route | E85: 32 | F85: 32 17 23 | H85: SIT-02 | I85: Accessible pedestrian path – concrete (entry to building, parking) | J85: SF | K85: Entry route LF × 6' width est. | L85: 1800 | M85: =IFERROR(VLOOKUP(H85,'UNIT PRICE LIBRARY'!D:L,9,FALSE()),0) -> 15.0075 | N85: =IF(O85="No",0,L85*M85) -> 27013.5 | O85: Yes | P85: ADA accessible route. Includes curb ramps, detectable warnings at crossings.
C86: SITE | D86: Perimeter | E86: 32 | F86: 32 31 13 | H86: SIT-03 | I86: Perimeter security fence – chain link with privacy slats | J86: LF | K86: School building perimeter est. | L86: 480 | M86: =IFERROR(VLOOKUP(H86,'UNIT PRICE LIBRARY'!D:L,9,FALSE()),0) -> 56.925 | N86: =IF(O86="No",0,L86*M86) -> 27324 | O86: Allowance | P86: DDDS: secure perimeter recommended for IDD residential. Height and spec TBD by DDDS pre-app meeting.
C87: SITE | D87: Campus | E87: 32 | F87: 32 90 00 | H87: SIT-04 | I87: Landscaping – Phase 1 campus restoration and accessible entry planting | J87: LS | K87: 1 scope | L87: 1 | M87: =IFERROR(VLOOKUP(H87,'UNIT PRICE LIBRARY'!D:L,9,FALSE()),0) -> 67275 | N87: =IF(O87="No",0,L87*M87) -> 67275 | O87: Allowance | P87: Seed/sod disturbed areas, foundation planting at entry, accessible route planting strips.
C88: TAKEOFF SUBTOTAL (before markups) — includes only rows where Included? = 'Yes' or 'Allowance' | N88: =SUMIF(O5:O87,"Yes",N5:N87)+SUMIF(O5:O87,"Allowance",N5:N87) -> 5885676.2
B89: → ADD NEW TAKEOFF ROWS ABOVE THE SUBTOTAL. Enter Floor, Zone, and Cost Code. Adj. Unit Cost auto-populates from UNIT PRICE LIBRARY via VLOOKUP on Cost Code.

Sheet EQUIPMENT ALLOWANCES
B1: OWNER SELECTION / ATHLETIC EQUIPMENT ALLOWANCES
B2: Category | C2: Allowance Item | D2: Basis of Design | E2: Qty | F2: Allowance Each | G2: Allowance Total | H2: Owner Selection Status | I2: Comments / Open Items
B3: Gym | C3: Main/side basketball backstop systems | D3: Jaypro / Porter / Draper | E3: 4 | F3: 14500 | G3: =E3*F3 -> 58000 | H3: Pending | I3: Select model/series, extension length, mounting type. 1 main + 3 side courts.
B4: Gym | C4: Telescoping bleacher system | D4: Jaypro / Irwin / Hussey | E4: 1 | F4: 95000 | G4: =E4*F4 -> 95000 | H4: Pending | I4: Confirm row count, rail configuration, ADA seating layout, finish.
B5: Gym | C5: Scoreboard / control system | D5: Daktronics / Watchfire / Electro-Mech | E5: 1 | F5: 18000 | G5: =E5*F5 -> 18000 | H5: Pending | I5: Confirm display type, clock size, controller, optional shot clock.
B6: Gym | C6: Wall padding / graphics | D6: Jaypro / Safety Padding / Bison | E6: 1 | F6: 32000 | G6: =E6*F6 -> 32000 | H6: Pending | I6: Confirm padding extents, color, logos / graphics, stage pad scope.
B7: Gym | C7: Volleyball post/sleeve system | D7: Jaypro / Porter / Draper | E7: 1 | F7: 3500 | G7: =E7*F7 -> 3500 | H7: Pending | I7: Confirm 7000-series configuration or equivalent.
B8: Boxing | C8: Boxing ring and accessories | D8: Title / Ringside / Everlast | E8: 1 | F8: 18000 | G8: =E8*F8 -> 18000 | H8: Pending | I8: Confirm ring size, ropes, corner pads, canvas, accessory package.
B9: Boxing | C9: Bag systems / speed bag stations | D9: Various | E9: 1 | F9: 14000 | G9: =E9*F9 -> 14000 | H9: Pending | I9: Confirm bag count, support frame type, bag style/weight, speed bag platform.
B10: Boxing | C10: Rubber athletic flooring | D10: Mondo / Ecore / Gerflor | E10: 2500 | F10: 14.5 | G10: =E10*F10 -> 36250 | H10: Pending | I10: Confirm thickness (6/8/10mm), color, transition details, wall base color.
B12: TOTAL EQUIPMENT ALLOWANCES | G12: =SUM(G3:G10) -> 274750
B13: Items Pending Owner Decision | G13: =COUNTIF(H3:H10,"Pending") -> 8

Sheet FLOOR SUMMARY
B1: FLOOR-BY-FLOOR COST SUMMARY
B2: Floor | C2: Base Building Subtotal | D2: Equipment Allowances | E2: Subtotal | F2: General Conditions | G2: OH&P | H2: Contingencies | I2: Bid/Permit/Bonds | J2: Est. Floor Total
B3: BLDG | C3: =SUMPRODUCT((TAKEOFF!$C$5:$C$200=B3)*(TAKEOFF!$O$5:$O$200="Yes")*TAKEOFF!$N$5:$N$200) -> 2451138.8 | D3: =SUMPRODUCT((TAKEOFF!$C$5:$C$200=B3)*(TAKEOFF!$O$5:$O$200="Allowance")*TAKEOFF!$N$5:$N$200) -> 51801.75 | E3: =C3+D3 -> 2502940.5 | F3: =E3*ASSUMPTIONS!$C$19 -> 200235.24 | G3: =(E3+F3)*ASSUMPTIONS!$C$20 -> 270317.57 | H3: =(E3+F3+G3)*(ASSUMPTIONS!$C$21+ASSUMPTIONS!$C$22+ASSUMPTIONS!$C$23) -> 892047.99 | I3: =(E3+F3+G3+H3)*ASSUMPTIONS!$C$24 -> 77310.826 | J3: =SUM(E3:I3) -> 3942852.1
B4: 1F | C4: =SUMPRODUCT((TAKEOFF!$C$5:$C$200=B4)*(TAKEOFF!$O$5:$O$200="Yes")*TAKEOFF!$N$5:$N$200) -> 2905549 | D4: =SUMPRODUCT((TAKEOFF!$C$5:$C$200=B4)*(TAKEOFF!$O$5:$O$200="Allowance")*TAKEOFF!$N$5:$N$200) -> 327318.75 | E4: =C4+D4 -> 3232867.7 | F4: =E4*ASSUMPTIONS!$C$19 -> 258629.42 | G4: =(E4+F4)*ASSUMPTIONS!$C$20 -> 349149.71 | H4: =(E4+F4+G4)*(ASSUMPTIONS!$C$21+ASSUMPTIONS!$C$22+ASSUMPTIONS!$C$23) -> 1152194.1 | I4: =(E4+F4+G4+H4)*ASSUMPTIONS!$C$24 -> 99856.818 | J4: =SUM(E4:I4) -> 5092697.7
B5: 2F | C5: =SUMPRODUCT((TAKEOFF!$C$5:$C$200=B5)*(TAKEOFF!$O$5:$O$200="Yes")*TAKEOFF!$N$5:$N$200) -> 0 | D5: =SUMPRODUCT((TAKEOFF!$C$5:$C$200=B5)*(TAKEOFF!$O$5:$O$200="Allowance")*TAKEOFF!$N$5:$N$200) -> 0 | E5: =C5+D5 -> 0 | F5: =E5*ASSUMPTIONS!$C$19 -> 0 | G5: =(E5+F5)*ASSUMPTIONS!$C$20 -> 0 | H5: =(E5+F5+G5)*(ASSUMPTIONS!$C$21+ASSUMPTIONS!$C$22+ASSUMPTIONS!$C$23) -> 0 | I5: =(E5+F5+G5+H5)*ASSUMPTIONS!$C$24 -> 0 | J5: =SUM(E5:I5) -> 0
B6: SITE | C6: =SUMPRODUCT((TAKEOFF!$C$5:$C$200=B6)*(TAKEOFF!$O$5:$O$200="Yes")*TAKEOFF!$N$5:$N$200) -> 55269 | D6: =SUMPRODUCT((TAKEOFF!$C$5:$C$200=B6)*(TAKEOFF!$O$5:$O$200="Allowance")*TAKEOFF!$N$5:$N$200) -> 94599 | E6: =C6+D6 -> 149868 | F6: =E6*ASSUMPTIONS!$C$19 -> 11989.44 | G6: =(E6+F6)*ASSUMPTIONS!$C$20 -> 16185.744 | H6: =(E6+F6+G6)*(ASSUMPTIONS!$C$21+ASSUMPTIONS!$C$22+ASSUMPTIONS!$C$23) -> 53412.955 | I6: =(E6+F6+G6+H6)*ASSUMPTIONS!$C$24 -> 4629.1228 | J6: =SUM(E6:I6) -> 236085.26
B7: TOTAL
B8: TOTAL | C8: =SUM(C3:C6) -> 5411956.7 | D8: =SUM(D3:D6) -> 473719.5 | E8: =SUM(E3:E6) -> 5885676.2 | F8: =SUM(F3:F6) -> 470854.1 | G8: =SUM(G3:G6) -> 635653.03 | H8: =SUM(H3:H6) -> 2097655 | I8: =SUM(I3:I6) -> 181796.77 | J8: =SUM(J3:J6) -> 9271635.1
B10: ↑ Total Project ROM feeds BID SUMMARY and SF BENCHMARK sheets.

Sheet BID SUMMARY
B1: ROM COST ESTIMATE — EXECUTIVE SUMMARY
B2: ="Project: " & ASSUMPTIONS!C3 -> Project: M-Well Community Health Campus
B3: ="Estimate Date: " & TEXT(ASSUMPTIONS!C4,"mm/dd/yyyy") & " | Type: " & ASSUMPTIONS!C5 -> Estimate Date: 01/00/1900 | Type: ROM / Conceptual
B4: Summary Item | C4: Amount | E4: Pricing Basis / Notes
B5: Base Building Subtotal | C5: =IFERROR(SUMIF('FLOOR SUMMARY'!B3:B8,"<>TOTAL",'FLOOR SUMMARY'!C3:C8),0) -> 5411956.7 | E5: Architectural / interior renovation ROM with quantity-based takeoff. Excludes allowances.
B6: Equipment Allowances | C6: =IFERROR(SUM('FLOOR SUMMARY'!D3:D6),0) -> 473719.5 | E6: Owner-selection-dependent athletic and specialty equipment. Pending confirmation.
B7: Subtotal Before Markups | C7: =C5+C6 -> 5885676.2
B8: General Conditions | C8: =C7*ASSUMPTIONS!$C$19 -> 470854.1 | E8: Rate: per ASSUMPTIONS!C19
B9: Overhead & Profit (OH&P) | C9: =(C7+C8)*ASSUMPTIONS!$C$20 -> 635653.03 | E9: Rate: per ASSUMPTIONS!C20
B10: Total Contingencies | C10: =(C7+C8+C9)*(ASSUMPTIONS!C21+ASSUMPTIONS!C22+ASSUMPTIONS!C23) -> 2097655 | E10: Design + existing conditions + equipment/owner selection contingencies.
B11: Bid / Permit / Bonds | C11: =(C7+C8+C9+C10)*ASSUMPTIONS!$C$24 -> 181796.77 | E11: Rate: per ASSUMPTIONS!C24
B12: TOTAL PROJECT ROM | C12: =C5+C8+C9+C10+C11 -> 8797915.6
B14: Project Cost per SF | C14: =IFERROR(C12/ASSUMPTIONS!$C$9,0) -> 320.48359 | E14: Reference only. Compare to SF BENCHMARK sheet for sanity check.
B16: CONTINGENCY BREAKDOWN (for reference)
B17: Design Contingency | C17: =(C7+C8+C9)*ASSUMPTIONS!C21 -> 839062
B18: Existing Conditions Contingency | C18: =(C7+C8+C9)*ASSUMPTIONS!C22 -> 699218.34
B19: Equipment/Owner Selection Contingency | C19: =(C7+C8+C9)*ASSUMPTIONS!C23 -> 559374.67
B21: SOFT COSTS & TOTAL PROJECT INVESTMENT (see SOFT COSTS and TOTAL PROJECT BUDGET sheets)
B22: Architecture Fee (from SOFT COSTS) | C22: ='SOFT COSTS'!F54 -> 690636.38 | E22: Base fee + renovation premium per M4Di fee schedule.
B23: Total Engineering Fees | C23: ='SOFT COSTS'!F84 -> 818206.15 | E23: Structural, MEP, FP, Civil, Geotech.
B24: Other Consultant & Owner Costs | C24: ='SOFT COSTS'!F85 -> 439895.78 | E24: Technology, legal, permits, insurance, testing, environmental.
B25: TOTAL SOFT COSTS | C25: ='SOFT COSTS'!F86 -> 1948738.3 | E25: See SOFT COSTS sheet for detail and overrides.
B26: Owner Contingency | C26: ='TOTAL PROJECT BUDGET'!C34 -> 439895.78 | E26: Post-GMP owner contingency and program reserves.
B27: TOTAL PROJECT INVESTMENT | C27: ='TOTAL PROJECT BUDGET'!C36 -> 11186550 | E27: Full project cost: hard + soft + owner costs.

Sheet SF BENCHMARK
B1: COST PER SF — BENCHMARK DASHBOARD
B2: Compares current ROM estimate to M4Di historical database and facility type benchmarks.
B3: Metric | C3: Value | E3: Historical Comparison | F3: Value
B4: Project Area (SF) | C4: =ASSUMPTIONS!C9 -> 27452 | E4: Project $/SF vs. Hist. Avg | F4: =IFERROR(C6/C7,"N/A - no data") -> 0.00016056292
B5: ROM Construction Cost | C5: ='BID SUMMARY'!C12 -> 8797915.6 | E5: Project $/SF vs. Hist. Median | F5: =IFERROR(C6/C8,"N/A - no data") -> 0.00015261124
B6: Calculated Project Cost/SF | C6: ='BID SUMMARY'!C14 -> 320.48359 | E6: Sanity Check | F6: =IF(C6>C10,"Above historical max",IF(C6>C7,"Above historical average",IF(C6<C9,"Below historical min","Within historical range"))) -> Within historical range
B7: Historical Average $/SF | C7: =IFERROR(AVERAGE('HISTORICAL DB'!G4:G103),0) -> 1996000
B8: Historical Median $/SF | C8: =IFERROR(MEDIAN('HISTORICAL DB'!G4:G103),0) -> 2100000
B9: Historical Min $/SF | C9: =IFERROR(MIN(IF('HISTORICAL DB'!G4:G103>0,'HISTORICAL DB'!G4:G103)),0) -> 0
B10: Historical Max $/SF | C10: =IFERROR(MAX('HISTORICAL DB'!G4:G103),0) -> 3200000
B11: Historical Data Count | C11: =COUNTA('HISTORICAL DB'!A4:A103) -> 0
B13: FACILITY TYPE BENCHMARK RANGES ($/SF)
B14: Facility Type | C14: Low $/SF | D14: High $/SF | F14: Check vs. Project
B15: Community Facility Renovation | C15: 120 | D15: 250 | F15: =IF('BID SUMMARY'!C14=0,"Enter data",IF('BID SUMMARY'!C14<C15,"Below range",IF('BID SUMMARY'!C14>D15,"Above range","Within range"))) -> Above range
B16: Church / Faith-Based Renovation | C16: 110 | D16: 230 | F16: =IF('BID SUMMARY'!C14=0,"Enter data",IF('BID SUMMARY'!C14<C16,"Below range",IF('BID SUMMARY'!C14>D16,"Above range","Within range"))) -> Above range
B17: Athletic Facility Upgrade | C17: 150 | D17: 320 | F17: =IF('BID SUMMARY'!C14=0,"Enter data",IF('BID SUMMARY'!C14<C17,"Below range",IF('BID SUMMARY'!C14>D17,"Above range","Within range"))) -> Above range
B18: Athletic Flooring Replacement | C18: 80 | D18: 165 | F18: =IF('BID SUMMARY'!C14=0,"Enter data",IF('BID SUMMARY'!C14<C18,"Below range",IF('BID SUMMARY'!C14>D18,"Above range","Within range"))) -> Above range
B19: Adaptive Reuse — Community Use | C19: 140 | D19: 290 | F19: =IF('BID SUMMARY'!C14=0,"Enter data",IF('BID SUMMARY'!C14<C19,"Below range",IF('BID SUMMARY'!C14>D19,"Above range","Within range"))) -> Above range
B20: New Construction — Community Fac. | C20: 220 | D20: 420 | F20: =IF('BID SUMMARY'!C14=0,"Enter data",IF('BID SUMMARY'!C14<C20,"Below range",IF('BID SUMMARY'!C14>D20,"Above range","Within range"))) -> Within range
B21: Mixed-Use (residential + community) | C21: 260 | D21: 480 | F21: =IF('BID SUMMARY'!C14=0,"Enter data",IF('BID SUMMARY'!C14<C21,"Below range",IF('BID SUMMARY'!C14>D21,"Above range","Within range"))) -> Within range
B24: HOW TO READ THIS DASHBOARD
B25: If project $/SF is BELOW all ranges: | C25: Scope may be missing items, quantities may be understated, or allowances are not yet included.
B26: If project $/SF is ABOVE all ranges: | C26: Owner selections, specialty equipment, corrosion remediation, or code upgrades may be driving cost.
B27: If project aligns with historical average: | C27: ROM is behaving like a plausible early estimate. Continue to P3 for detailed scope confirmation.
B28: Historical database: | C28: Replace example rows in HISTORICAL DB with M4Di's own completed projects over time. This is the proprietary asset.

Sheet HISTORICAL DB
B1: M4Di HISTORICAL PROJECT COST DATABASE — PROPRIETARY ASSET
B2: CRITICAL: Enter every completed M4Di engagement in this database. This is M4Di's proprietary competitive advantage. Do not distribute externally. Source for SF BENCHMARK dashboard and annual cost reports.
B3: Project Name / Code | C3: Project Type | D3: Location / Region | E3: Year Completed | F3: Building Area (SF) | G3: Final Const. Cost | H3: Cost / SF | I3: Scope Description | J3: Data Source / Notes
B4: YMCA Gymnasium Renovation | C4: Athletic Facility Upgrade | D4: Pennsylvania | E4: 2023 | F4: 18000 | G4: 3200000 | H4: =IFERROR(G4/F4,0) -> 177.77778 | I4: Gym upgrades, flooring, bleachers, scoring equipment, wall padding. | J4: Example benchmark — replace with M4Di project data
B5: High School Gymnasium Upgrade | C5: Athletic Facility Upgrade | D5: Delaware | E5: 2022 | F5: 12000 | G5: 2100000 | H5: =IFERROR(G5/F5,0) -> 175 | I5: Bleacher replacement, floor refinish, scoreboard, accessible path of travel. | J5: Example benchmark — replace with M4Di project data
B6: Community Rec Center Interior | C6: Community Facility Renovation | D6: Maryland | E6: 2021 | F6: 8000 | G6: 950000 | H6: =IFERROR(G6/F6,0) -> 118.75 | I6: Interior renovation, athletic flooring, community room upgrades. | J6: Example benchmark — replace with M4Di project data
B7: Church Fellowship Hall Adaptive Reuse | C7: Adaptive Reuse — Community Use | D7: Delaware | E7: 2023 | F7: 6500 | G7: 1450000 | H7: =IFERROR(G7/F7,0) -> 223.07692 | I7: Fellowship hall converted to community clinic and gathering space. ADA upgrades. | J7: Example benchmark — replace with M4Di project data
B8: Faith-Based Youth Center Renovation | C8: Community Facility Renovation | D8: New Jersey | E8: 2024 | F8: 9200 | G8: 2280000 | H8: =IFERROR(G8/F8,0) -> 247.82609 | I8: Full interior renovation, new MEP, gymnasium floor, community kitchen. | J8: Example benchmark — replace with M4Di project data
B10: → ADD NEW COMPLETED PROJECTS ABOVE THIS LINE. Copy Cost/SF formula from column H. Fill all fields at project closeout.
B12: DATABASE STATISTICS (auto-calculated — used by SF BENCHMARK)
B13: Total Projects in Database | C13: =COUNTA(B4:B9) -> 5
B14: Average Cost / SF | C14: =IFERROR(AVERAGE(H4:H9),0) -> 188.48616
B15: Median Cost / SF | C15: =IFERROR(MEDIAN(H4:H9),0) -> 177.77778
B16: Minimum Cost / SF | C16: =IFERROR(MIN(IF(H4:H9>0,H4:H9)),0) -> 0
B17: Maximum Cost / SF | C17: =IFERROR(MAX(H4:H9),0) -> 247.82609

Sheet OWNER SELECTIONS
B1: OWNER ATHLETIC EQUIPMENT SELECTION MATRIX
B2: Use this sheet to document owner selections affecting allowances and final bid comparability. Each "Pending" item represents an open decision that must be resolved before the estimate can be finalized.
B3: Allowance Ref | C3: Category | D3: Equipment / System | E3: Spec Section | F3: Basis of Design | G3: Owner Confirm? | H3: Selected Mfr. | I3: Selected Model/Series | J3: Color/ Finish | K3: Allowance Each | L3: Qty | M3: Allowance Total | N3: Critical Owner Decision
B4: ATH-01 | C4: Gym | D4: Wall padding / graphics | E4: 11 66 23 | F4: Jaypro / Safety Padding / Bison | G4: Pending | K4: 32000 | L4: 1 | M4: =K4*L4 -> 32000 | N4: Confirm padding extents, color, logos/graphics, stage pad scope.
B5: ATH-02 | C5: Gym | D5: Scoreboard / controls | E5: 11 66 23 | F5: Daktronics / Watchfire / Electro-Mech | G5: Pending | K5: 18000 | L5: 1 | M5: =K5*L5 -> 18000 | N5: Confirm display type, clock size, controller, optional shot clock package.
B6: ATH-03 | C6: Gym | D6: Telescoping bleachers | E6: 11 66 23 | F6: Jaypro / Irwin / Hussey | G6: Pending | K6: 95000 | L6: 1 | M6: =K6*L6 -> 95000 | N6: Confirm row count, rail configuration, ADA seating layout, finish.
B7: ATH-04 | C7: Gym | D7: Basketball backstop systems | E7: 11 66 23 | F7: Jaypro / Porter / Draper | G7: Pending | K7: 14500 | L7: 4 | M7: =K7*L7 -> 58000 | N7: Select exact model/series, extension length, mounting type.
B8: ATH-05 | C8: Gym | D8: Volleyball system | E8: 11 66 23 | F8: Jaypro / Porter / Draper | G8: Pending | K8: 3500 | L8: 1 | M8: =K8*L8 -> 3500 | N8: Select post/sleeve system and exact 7000-series configuration.
B9: ATH-06 | C9: Boxing | D9: Boxing ring and accessories | E9: 11 66 43 | F9: Title / Ringside / Everlast | G9: Pending | K9: 18000 | L9: 1 | M9: =K9*L9 -> 18000 | N9: Confirm ring size, ropes, corner pads, canvas, accessory package.
B10: BOX-ALW | C10: Boxing | D10: Bag systems / speed bag stations | E10: 11 66 43 | F10: Various | G10: Pending | K10: 14000 | L10: 1 | M10: =K10*L10 -> 14000 | N10: Confirm bag count, support frame type, bag style/weight, speed bag platform.
B11: FIN-04 | C11: Boxing | D11: Rubber athletic flooring | E11: 09 65 66 | F11: Mondo / Ecore / Gerflor | G11: Pending | K11: 14.5 | L11: 2500 | M11: =K11*L11 -> 36250 | N11: Confirm thickness (6/8/10mm), color, transition details, wall base color.
B13: TOTAL OWNER SELECTION ALLOWANCES | M13: =SUM(M4:M11) -> 274750
B14: Items Still Pending Owner Decision | M14: =COUNTIF(G4:G11,"Pending") -> 8

Sheet ALLOWANCE LOG
B1: ALLOWANCE LOG — Living Tracker for ALDi Gate Reporting
B2: Export this log monthly as part of ALDi gate reporting. Each row represents an open allowance that must be resolved before GMP. Status should be updated as owner decisions are confirmed.
B3: Allowance ID | C3: Spec Section | D3: Category | E3: Description | F3: Allowance Amount | G3: Basis / Reason | H3: Owner Decision Required? | I3: Status | J3: Notes / Next Action
B4: ALW-01 | C4: 11 66 23 | D4: Gym Equipment | E4: Basketball backstop systems | F4: 65000 | G4: Model TBD — Jaypro J800 family or equal | H4: Yes | I4: Pending | J4: Owner to confirm: model/series, extension length, mounting type. Due before DD.
B5: ALW-02 | C5: 11 66 23 | D5: Gym Equipment | E5: Telescoping bleacher system | F5: 95000 | G5: Layout and ADA seating TBD | H5: Yes | I5: Pending | J5: Owner to confirm: row count, ADA configuration, finish. Structural coordination required.
B6: ALW-03 | C6: 11 66 23 | D6: Gym Equipment | E6: Scoreboard / control system | F6: 18000 | G6: Manufacturer TBD | H6: Yes | I6: Pending | J6: Owner to confirm: display type, clock size, controller. Power/data coordination required.
B7: ALW-04 | C7: 11 66 23 | D7: Gym Equipment | E7: Wall padding and graphics | F7: 32000 | G7: Owner graphics and color scope TBD | H7: Yes | I7: Pending | J7: Owner to confirm: extents, color, logos, stage pad scope.
B8: ALW-05 | C8: 11 66 43 | D8: Boxing Equipment | E8: Boxing ring and accessories | F8: 18000 | G8: Model TBD — Title/Ringside/Everlast | H8: Yes | I8: Pending | J8: Owner to confirm: ring size (14x14 assumed), ropes, corner pads, canvas.
B9: ALW-06 | C9: 09 65 00 | D9: Athletic Flooring | E9: Rubber flooring — boxing gym | F9: 28000 | G9: Thickness and color TBD by owner | H9: Yes | I9: Pending | J9: Owner to confirm: thickness (6/8/10mm), color, wall base. Coordinate transitions.
B10: ALW-07 | C10: 22 11 00 | D10: MEP | E10: Plumbing modifications — pump room | F10: 15000 | G10: Scope pending MEP engineer review | H10: No | I10: Pending | J10: Pending MEP engineer opinion. Allowance covers minor modifications only.
B11: ALW-08 | C11: 26 05 00 | D11: MEP | E11: Electrical — scoreboard/equipment feeds | F11: 9000 | G11: Pending scoreboard/equipment selection | H11: Yes | I11: Pending | J11: Allowance pending owner equipment selections. Coordinate with ELC.
B13: TOTAL OPEN ALLOWANCES | F13: =SUM(F4:F11) -> 280000
B14: Items Pending Owner Decision | F14: =COUNTIF(I4:I11,"Pending") -> 8
B16: ALW-SGN-01 | C16: 10 14 00 | D16: Signage | E16: Room ID + Numbering System | F16: 10000 | G16: M4Di room schedule generated from SIGNAGE PROGRAM tab. 57 interior sign locations + hardware. | H16: Yes | I16: Pending | J16: See SIGNAGE PROGRAM tab for full room schedule and brand framework.
B17: ALW-SGN-02 | C17: 10 14 53 | D17: Signage | E17: Wayfinding + Directional System | F17: 38000 | G17: Campus orientation map, floor directories, corridor directionals. Exterior entry identification. | H17: Yes | I17: Pending | J17: See SIGNAGE PROGRAM tab for full room schedule and brand framework.
B18: ALW-SGN-03 | C18: 10 14 00 | D18: Signage | E18: Exterior + Campus Identity | F18: 18000 | G18: Building name sign, address numerals, accessible parking. NCC sign permit required. | H18: Yes | I18: Pending | J18: See SIGNAGE PROGRAM tab for full room schedule and brand framework.
B19: ALW-SGN-04 | C19: 10 14 00 | D19: Signage | E19: Donor / Community Identity (optional) | F19: 0 | G19: Budget TBD by owner. Recommend IDD-appropriate sensory-calm displays. $0 if not pursued. | H19: Yes | I19: Pending | J19: See SIGNAGE PROGRAM tab for full room schedule and brand framework.

Sheet CLARIFICATIONS
B1: CLARIFICATIONS / EXCLUSIONS / RISK LOG
B2: Include this sheet in all client deliverables. It defines the boundaries of the estimate and protects M4Di from scope disputes. Update at every estimate revision.
B3: Category | C3: Item | D3: Included / Excluded / Allowance | E3: Risk Level | F3: Comment / Mitigation
B4: General | C4: All quantities are conceptual and require field verification before GMP | D4: Included | E4: High | F4: Use as ROM only. Not a GMP or guaranteed maximum price.
B5: General | C5: Estimate based on scope narrative and program only — no drawings | D5: Included | E5: High | F5: Unit quantities are estimator's judgment. Field verify before DD.
B6: Equipment | C6: Athletic equipment model numbers and manufacturers | D6: Allowance | E6: High | F6: Owner selections pending. Allowances will be updated as selections are confirmed.
B7: Equipment | C7: Boxing equipment package | D7: Allowance | E7: High | F7: Basis of design still open. Owner to confirm model and accessory scope.
B8: MEP | C8: Power and data modifications for scoreboards and specialty equipment | D8: Allowance | E8: Medium | F8: Allowance included. Requires MEP engineer coordination and load calculations.
B9: MEP | C9: HVAC modifications or upgrades | D9: Excluded | E9: Medium | F9: Not in scope unless noted. Carry separate MEP budget if HVAC work is anticipated.
B10: MEP | C10: Plumbing — new fixtures or drainage | D10: Excluded | E10: Medium | F10: Minor modifications covered by allowance. Major new plumbing excluded.
B11: Existing Conditions | C11: Concealed corrosion or substrate damage beyond scope assumptions | D11: Excluded | E11: High | F11: Carry contingency or unit rates for concealed conditions. Field verification recommended.
B12: Existing Conditions | C12: Hazardous material abatement (asbestos, lead paint) | D12: Excluded | E12: High | F12: Requires testing and licensed abatement contractor. Separate budget required.
B13: Existing Conditions | C13: Structural deficiencies identified during construction | D13: Excluded | E13: High | F13: Not in scope. Structural engineer review recommended before estimate finalization.
B14: Schedule | C14: Cost escalation beyond current estimate date | D14: Excluded | E14: Medium | F14: Adjust ENR escalation factor in ASSUMPTIONS for revised bid dates.
... B21: Accessibility | C21: ADA path of travel upgrades beyond specified scope | D21: Excluded | E21: Medium | F21: ADA items within designated scope are included. Full-building accessibility audit not in scope.
B23: → ADD PROJECT-SPECIFIC CLARIFICATIONS ABOVE. Always include this sheet in client deliverable packages.

Sheet SOFT COSTS
B1: SOFT COSTS — Professional Fees & Pre-Construction Budget
B2: Soft costs are calculated as a percentage of the Total Hard Cost ROM (from BID SUMMARY). Architecture fee uses the M4Di Base Fee Schedule (AIA-aligned). Engineering and specialty fees use benchmark percentages adjustable per project. All rates are user-overridable.
B4: A — PROJECT BASIS (from ASSUMPTIONS & BID SUMMARY)
B5: Total Hard Cost ROM | C5: ='BID SUMMARY'!C12 -> 8797915.6 | D5: Pulled from BID SUMMARY. This is the construction cost base for all fee calculations.
B6: Project Type (for fee schedule) | C6: =ASSUMPTIONS!C6 -> Adaptive Reuse | D6: Auto-pulled from ASSUMPTIONS. Drives fee type classification below.
B7: Estimate Phase | C7: =ASSUMPTIONS!C5 -> ROM / Conceptual | D7: ROM / Conceptual | Schematic | Design Development | GMP
B8: Gross Area (SF) | C8: =ASSUMPTIONS!C9 -> 27452 | D8: From ASSUMPTIONS. Used for cost/SF benchmarking.
B10: B — ARCHITECTURE FEE (M4Di Base Fee Schedule)
B11: Fee lookup uses the M4Di Base Fee Schedule. Select the Project Type Code (A–E) based on complexity. For renovation/adaptive reuse, apply the renovation premium. New Construction = base rate only. Renovation = base + premium.
B13: FEE SCHEDULE REFERENCE TABLE — Base % of Construction Cost
B14: Construction Budget Range | D14: Type A | E14: Type B | F14: Type C | G14: Type D | H14: Type E
B15: Up to – $49,999 | D15: 0.089 | E15: 0.099 | F15: 0.109 | G15: 0.117 | H15: 0.12
B16: $50,000 – $99,999 | D16: 0.084 | E16: 0.094 | F16: 0.107 | G16: 0.111 | H16: 0.119
B17: $100,000 – $149,999 | D17: 0.081 | E17: 0.091 | F17: 0.104 | G17: 0.109 | H17: 0.115
B18: $150,000 – $199,999 | D18: 0.079 | E18: 0.089 | F18: 0.101 | G18: 0.105 | H18: 0.112
B19: $200,000 – $299,999 | D19: 0.074 | E19: 0.084 | F19: 0.099 | G19: 0.103 | H19: 0.11
B20: $300,000 – $499,999 | D20: 0.072 | E20: 0.082 | F20: 0.094 | G20: 0.1 | H20: 0.107
B21: $500,000 – $749,999 | D21: 0.069 | E21: 0.079 | F21: 0.091 | G21: 0.097 | H21: 0.104
B22: $750,000 – $999,999 | D22: 0.067 | E22: 0.077 | F22: 0.089 | G22: 0.094 | H22: 0.101
B23: $1,000,000 – $1,499,999 | D23: 0.064 | E23: 0.074 | F23: 0.084 | G23: 0.091 | H23: 0.098
B24: $1,500,000 – $1,999,999 | D24: 0.062 | E24: 0.072 | F24: 0.082 | G24: 0.088 | H24: 0.095
B25: $2,000,000 – $2,999,999 | D25: 0.059 | E25: 0.069 | F25: 0.079 | G25: 0.085 | H25: 0.092
B26: $3,000,000 – $3,999,999 | D26: 0.057 | E26: 0.067 | F26: 0.077 | G26: 0.083 | H26: 0.09
... B33: Renovation premium (add to above) | D33: 0.005 | E33: 0.0065 | F33: 0.0075 | G33: 0.0085 | H33: 0.01
B35: PROJECT TYPE CLASSIFICATION — Select the code that matches your facility
B36: Type A | C36: Warehouse, Public Garage, Residential (standard)
B37: Type B | C37: Office, Parking Facility, Retail, Visitor Center, Maintenance Garage, Tenant Fit-out
B38: Type C | C38: School, Training Facility, Day Care, Fitness Center, Mixed-Use, Adult Care, Laundry
B39: Type D | C39: Library, Restaurant, Theater (no stage), Outpatient Clinic, Detention, Courthouse, Data Center
B40: Type E | C40: Hospital, Research, Museum, Stadium, Prison, Emergency Ops, Theater/Auditorium with stage
B41: M4Di Default — Community Facility Renovation | C41: Use Type C (Fitness Center / Mixed-Use) for church/community renovation. Use Type D for clinic or complex adaptive reuse.
B44: C — FEE INPUTS & CALCULATIONS (enter yellow cells; formulas auto-populate)
B45: Discipline / Fee Item | C45: % of Hard Cost (enter or auto) | D45: Calculated Fee ($) | E45: User Override ($ if fixed) | F45: Fee Used (calc or override) | G45: Included in Budget? | H45: Notes / Assumptions
B46: PROJECT TYPE CODE & RENOVATION SELECTION (user inputs)
B47: AIA Project Type Code (A / B / C / D / E) | C47: C | D47: Type A=warehouse/parking, B=office/retail, C=school/fitness/mixed-use (M4Di default), D=clinic/library/theater, E=hospital/research. See guide above.
B48: Renovation / Adaptive Reuse? (Yes / No) | C48: Yes | D48: Yes: adds renovation premium to base Arch fee per fee schedule. WHACC = Yes (interior improvement + adaptive reuse elements).
B50: ARCHITECTURE & ENGINEERING FEES
B51: Discipline / Fee Item | C51: % of Hard Cost | D51: Calculated Fee ($) | E51: User Override ($) leave blank = use calc | F51: Fee Used | G51: Include? | H51: Notes / Source
B52: Architecture — Base Fee (fee schedule) | C52: =IFERROR(IF(C47="A",IF(C5<50000,D15,IF(C5<100000,D16,IF(C5<150000,D17,IF(C5<200000,D18,IF(C5<300000,D19,IF(C5<500000,D20,IF(C5<750000,D21,IF(C5<1000000,D22,IF(C5<1500000,D23,IF(C5<2000000,D24,IF(C5<3000000,D25,IF(C5<4000000,D26,IF(C5<5000000,D27,IF(C5<8000000,D28,IF(C5<12000000,D29,IF(C5<15000000,D30,IF(C5<20000000,D31,D32))))))))))))))))),IF(C47="B",IF(C5<50000,E15,IF(C5<100000,E16,IF(C5<150000,E17,IF(C5<200000,E18,IF(C5<300000,E19,IF(C5<500000,E20,IF(C5<750000,E21,IF(C5<1000000,E22,IF(C5<1500000,E23,IF(C5<2000000,E24,IF(C5<3000000,E25,IF(C5<4000000,E26,IF(C5<5000000,E27,IF(C5<8000000,E28,IF(C5<12000000,E29,IF(C5<15000000,E30,IF(C5<20000000,E31,E32))))))))))))))))),IF(C47="C",IF(C5<50000,F15,IF(C5<100000,F16,IF(C5<150000,F17,IF(C5<200000,F18,IF(C5<300000,F19,IF(C5<500000,F20,IF(C5<750000,F21,IF(C5<1000000,F22,IF(C5<1500000,F23,IF(C5<2000000,F24,IF(C5<3000000,F25,IF(C5<4000000,F26,IF(C5<5000000,F27,IF(C5<8000000,F28,IF(C5<12000000,F29,IF(C5<15000000,F30,IF(C5<20000000,F31,F32))))))))))))))))),IF(C47="D",IF(C5<50000,G15,IF(C5<100000,G16,IF(C5<150000,G17,IF(C5<200000,G18,IF(C5<300000,G19,IF(C5<500000,G20,IF(C5<750000,G21,IF(C5<1000000,G22,IF(C5<1500000,G23,IF(C5<2000000,G24,IF(C5<3000000,G25,IF(C5<4000000,G26,IF(C5<5000000,G27,IF(C5<8000000,G28,IF(C5<12000000,G29,IF(C5<15000000,G30,IF(C5<20000000,G31,G32))))))))))))))))),IF(C47="E",IF(C5<50000,H15,IF(C5<100000,H16,IF(C5<150000,H17,IF(C5<200000,H18,IF(C5<300000,H19,IF(C5<500000,H20,IF(C5<750000,H21,IF(C5<1000000,H22,IF(C5<1500000,H23,IF(C5<2000000,H24,IF(C5<3000000,H25,IF(C5<4000000,H26,IF(C5<5000000,H27,IF(C5<8000000,H28,IF(C5<12000000,H29,IF(C5<15000000,H30,IF(C5<20000000,H31,H32))))))))))))))))),0))))),0) -> 0.071 | D52: =C5*C52 -> 624652.01 | F52: =IF(AND(E52<>"",E52<>0),E52,D52) -> 624652.01 | G52: Yes | H52: Auto-calculated from M4Di Base Fee Schedule. Based on construction cost tier and Type Code.
B53: + Renovation Premium (if applicable) | C53: =IF(C48="Yes",IF(C47="A",D33,IF(C47="B",E33,IF(C47="C",F33,IF(C47="D",G33,IF(C47="E",H33,0))))),0) -> 0.0075 | D53: =C5*C53 -> 65984.367 | F53: =IF(AND(E53<>"",E53<>0),E53,D53) -> 65984.367 | G53: Yes | H53: Add-on for renovation/adaptive reuse per fee schedule. Set to 0 if new construction.
B54: Architecture — TOTAL FEE | C54: =C52+C53 -> 0.0785 | F54: =F52+F53 -> 690636.38
B56: ENGINEERING DISCIPLINES
B57: Structural Engineering | C57: 0.015 | D57: =C5*C57 -> 131968.73 | F57: =IF(AND(E57<>"",E57<>0),E57,D57) -> 131968.73 | G57: Yes | H57: Typical: 1.0%–2.0% of construction cost. Higher for complex structural systems, seismic, or adaptive reuse.
B58: Mechanical Engineering (HVAC) | C58: 0.018 | D58: =C5*C58 -> 158362.48 | F58: =IF(AND(E58<>"",E58<>0),E58,D58) -> 158362.48 | G58: Yes | H58: Typical: 1.2%–2.5%. Higher for healthcare/lab. Use lower end for straightforward community facilities.
B59: Electrical Engineering | C59: 0.015 | D59: =C5*C59 -> 131968.73 | F59: =IF(AND(E59<>"",E59<>0),E59,D59) -> 131968.73 | G59: Yes | H59: Typical: 1.0%–2.0%. Adjust for high-voltage, generator, or specialty lighting systems.
B60: Plumbing Engineering | C60: 0.01 | D60: =C5*C60 -> 87979.156 | F60: =IF(AND(E60<>"",E60<>0),E60,D60) -> 87979.156 | G60: Yes | H60: Typical: 0.8%–1.5%. Minimal for interior renovation with no new fixtures. Higher for kitchen/clinic.
B61: Fire Protection Engineering | C61: 0.008 | D61: =C5*C61 -> 70383.325 | F61: =IF(AND(E61<>"",E61<>0),E61,D61) -> 70383.325 | G61: Yes | H61: Typical: 0.5%–1.0%. Includes sprinkler design and fire alarm engineering if in scope.
B62: Civil Engineering | C62: 0.012 | D62: =C5*C62 -> 105574.99 | F62: =IF(AND(E62<>"",E62<>0),E62,D62) -> 105574.99 | G62: Yes | H62: Typical: 0.8%–2.0%. Covers grading, stormwater, utilities, ADA site access. Minimal for interior-only.
B63: Geotechnical / Soils Report | C63: 0.005 | D63: =C5*C63 -> 43989.578 | F63: =IF(AND(E63<>"",E63<>0),E63,D63) -> 43989.578 | G63: Yes | H63: Typical: 0.3%–0.8% or fixed fee $5K–$25K. Required for new foundations or unknown soil conditions.
B64: Landscape Architecture | C64: 0.005 | D64: =C5*C64 -> 43989.578 | F64: =IF(AND(E64<>"",E64<>0),E64,D64) -> 43989.578 | G64: Yes | H64: Typical: 0.3%–0.8%. Site improvements, accessible path, outdoor amenity. May be $0 for interior scope.
B65: Accessibility / ADA Consultant | C65: 0.005 | D65: =C5*C65 -> 43989.578 | F65: =IF(AND(E65<>"",E65<>0),E65,D65) -> 43989.578 | G65: Yes | H65: Typical: 0.3%–0.5% or fixed fee. Recommended for public-access facilities; CDFIs and HUD often require.
B67: SPECIALTY CONSULTANTS & OWNER COSTS
B68: Interior Design / Furniture | C68: 0.005 | D68: =C5*C68 -> 43989.578 | F68: =IF(AND(E68<>"",E68<>0),E68,D68) -> 43989.578 | G68: Yes | H68: If separate from Arch. Includes FF&E design and procurement management.
B69: Technology / AV / IT Consultant | C69: 0.004 | D69: =C5*C69 -> 35191.663 | F69: =IF(AND(E69<>"",E69<>0),E69,D69) -> 35191.663 | G69: Yes | H69: Low-voltage, AV, security systems design. Required for scoreboard, PA, access control.
B70: Cost Estimating (M4Di OI) | C70: 0 | D70: =C5*C70 -> 0 | F70: =IF(AND(E70<>"",E70<>0),E70,D70) -> 0 | G70: Yes | H70: M4Di P1/P2/P3 fees are separate contracts. Shown here for total project budget reference.
B71: Owner Project Management | C71: 0 | D71: =C5*C71 -> 0 | F71: =IF(AND(E71<>"",E71<>0),E71,D71) -> 0 | G71: Yes | H71: M4Di ALDi retainer. Enter actual contracted amount in override column.
B72: Legal / Title / Closing | C72: 0.003 | D72: =C5*C72 -> 26393.747 | F72: =IF(AND(E72<>"",E72<>0),E72,D72) -> 26393.747 | G72: Yes | H72: Covers property matters, contract review. Variable; use $5K–$15K allowance for small projects.
B73: Permitting / Plan Review Fees | C73: 0.015 | D73: =C5*C73 -> 131968.73 | F73: =IF(AND(E73<>"",E73<>0),E73,D73) -> 131968.73 | G73: Yes | H73: Variable by jurisdiction. Delaware municipalities: typically 1.0%–2.0% of construction cost.
B74: Builder's Risk Insurance | C74: 0.008 | D74: =C5*C74 -> 70383.325 | F74: =IF(AND(E74<>"",E74<>0),E74,D74) -> 70383.325 | G74: Yes | H74: Typically 0.5%–1.5% of total project cost. Confirm with owner's insurance agent.
B75: Testing / Special Inspections | C75: 0.005 | D75: =C5*C75 -> 43989.578 | F75: =IF(AND(E75<>"",E75<>0),E75,D75) -> 43989.578 | G75: Yes | H75: IBC-required inspections (concrete, steel, masonry) and materials testing. AHJ-dependent.
B76: Survey / As-Builts / Scanning | C76: 0 | D76: =C5*C76 -> 0 | F76: =IF(AND(E76<>"",E76<>0),E76,D76) -> 0 | G76: Yes | H76: Fixed fee item — enter actual quote in override. Typical range: $3,000–$15,000.
B77: Environmental Assessment (Phase I) | C77: 0 | D77: =C5*C77 -> 0 | F77: =IF(AND(E77<>"",E77<>0),E77,D77) -> 0 | G77: Yes | H77: Fixed fee — enter in override. Required for most CDFI/HUD-funded projects. ~$2,500–$5,000.
B78: Relocation / Move-Out Costs | C78: 0 | D78: =C5*C78 -> 0 | F78: =IF(AND(E78<>"",E78<>0),E78,D78) -> 0 | G78: Yes | H78: Owner cost. Enter estimate in override if applicable. Not part of construction budget.
B79: Financing / Loan Origination | C79: 0.01 | D79: =C5*C79 -> 87979.156 | F79: =IF(AND(E79<>"",E79<>0),E79,D79) -> 87979.156 | G79: Yes | H79: Typical: 0.5%–1.5% of loan amount. Applies to construction loans and CDFI financing.
B80: Fundraising / Development Costs | C80: 0 | D80: =C5*C80 -> 0 | F80: =IF(AND(E80<>"",E80<>0),E80,D80) -> 0 | G80: Yes | H80: Owner/nonprofit cost. Enter fixed estimate in override if applicable.
B82: SOFT COST SUBTOTALS & TOTAL PROJECT BUDGET
B83: Architecture Subtotal | F83: =IF(OR(G52="Yes",G52="Allowance"),F52,0)+IF(OR(G53="Yes",G53="Allowance"),F53,0) -> 690636.38
B84: Engineering Subtotal (all disciplines) | F84: =IF(OR(G57="Yes",G57="Allowance"),F57,0)+IF(OR(G58="Yes",G58="Allowance"),F58,0)+IF(OR(G59="Yes",G59="Allowance"),F59,0)+IF(OR(G60="Yes",G60="Allowance"),F60,0)+IF(OR(G61="Yes",G61="Allowance"),F61,0)+IF(OR(G62="Yes",G62="Allowance"),F62,0)+IF(OR(G63="Yes",G63="Allowance"),F63,0)+IF(OR(G64="Yes",G64="Allowance"),F64,0)+IF(OR(G65="Yes",G65="Allowance"),F65,0) -> 818206.15
B85: Other Consultants & Owner Costs Subtotal | F85: =IF(OR(G68="Yes",G68="Allowance"),F68,0)+IF(OR(G69="Yes",G69="Allowance"),F69,0)+IF(OR(G70="Yes",G70="Allowance"),F70,0)+IF(OR(G71="Yes",G71="Allowance"),F71,0)+IF(OR(G72="Yes",G72="Allowance"),F72,0)+IF(OR(G73="Yes",G73="Allowance"),F73,0)+IF(OR(G74="Yes",G74="Allowance"),F74,0)+IF(OR(G75="Yes",G75="Allowance"),F75,0)+IF(OR(G76="Yes",G76="Allowance"),F76,0)+IF(OR(G77="Yes",G77="Allowance"),F77,0)+IF(OR(G78="Yes",G78="Allowance"),F78,0)+IF(OR(G79="Yes",G79="Allowance"),F79,0)+IF(OR(G80="Yes",G80="Allowance"),F80,0) -> 439895.78
B86: TOTAL SOFT COSTS | C86: =IFERROR(F86/C5,0) -> 0.2215 | F86: =F83+F84+F85 -> 1948738.3
B88: SOFT COST $/SF BENCHMARKS (informational)
B89: Typical total soft costs range from 18%–35% of hard costs for community/institutional projects. Simpler interior renovations: 18%–22%. Complex adaptive reuse or new construction with full engineering: 25%–35%. Healthcare/research: 30%–40%. Current project soft cost %: see TOTAL SOFT COSTS row above.
B91: ▶ Total Soft Costs feeds TOTAL PROJECT BUDGET sheet.

Sheet TOTAL PROJECT BUDGET
B1: TOTAL PROJECT BUDGET — Hard Costs + Soft Costs + Owner Costs
B2: This sheet aggregates the full project investment: construction hard costs (from BID SUMMARY), professional fees and soft costs (from SOFT COSTS), and owner contingency. Use this for board presentations, CDFI loan packages, and grant applications.
B3: ="Project: " & ASSUMPTIONS!C3 & " | " & TEXT(ASSUMPTIONS!C4,"mm/dd/yyyy") & " | Phase: " & ASSUMPTIONS!C5 -> Project: M-Well Community Health Campus | 01/00/1900 | Phase: ROM / Conceptual
B5: Budget Item | C5: Amount ($) | D5: % of Hard Cost | E5: % of Total | F5: Notes
B6: SECTION 1 — HARD COSTS (Construction)
B7: Base Building Subtotal (labor + materials) | C7: ='BID SUMMARY'!C5 -> 5411956.7 | D7: =IFERROR(C7/C13,0) -> 0.61514078 | E7: =IFERROR(C7/C36,0) -> 0.48379142 | F7: Quantity-based takeoff from TAKEOFF sheet, adjusted for region and escalation.
B8: Equipment Allowances (owner selections) | C8: ='BID SUMMARY'!C6 -> 473719.5 | D8: =IFERROR(C8/C13,0) -> 0.053844515 | E8: =IFERROR(C8/C36,0) -> 0.042347239 | F8: Athletic and specialty equipment. Pending owner selections. See EQUIPMENT ALLOWANCES.
B9: General Conditions | C9: ='BID SUMMARY'!C8 -> 470854.1 | D9: =IFERROR(C9/C13,0) -> 0.053518824 | E9: =IFERROR(C9/C36,0) -> 0.042091092 | F9: On-site supervision, temp facilities, insurance. Rate per ASSUMPTIONS.
B10: Overhead & Profit (OH&P) | C10: ='BID SUMMARY'!C9 -> 635653.03 | D10: =IFERROR(C10/C13,0) -> 0.072250412 | E10: =IFERROR(C10/C36,0) -> 0.056822975 | F10: Contractor OH&P. Rate per ASSUMPTIONS.
B11: Total Contingencies | C11: ='BID SUMMARY'!C10 -> 2097655 | D11: =IFERROR(C11/C13,0) -> 0.23842636 | E11: =IFERROR(C11/C36,0) -> 0.18751582 | F11: Design + existing conditions + owner selection contingency. Will reduce at each gate.
B12: Bid / Permit / Bonds | C12: ='BID SUMMARY'!C11 -> 181796.77 | D12: =IFERROR(C12/C13,0) -> 0.020663618 | E12: =IFERROR(C12/C36,0) -> 0.016251371 | F12: Permitting fees, bid bonds, performance bonds.
B13: TOTAL HARD COST (Construction ROM) | C13: ='BID SUMMARY'!C12 -> 8797915.6 | D13: 1 | E13: =IFERROR(C13/C36,0) -> 0.78647267
B15: SECTION 2 — SOFT COSTS (Professional Fees & Owner Costs)
B16: Architecture — Total Fee (base + renovation premium) | C16: ='SOFT COSTS'!F54 -> 690636.38 | D16: =IFERROR(C16/C13,0) -> 0.0785 | E16: =IFERROR(C16/C36,0) -> 0.061738105 | F16: Base fee per M4Di fee schedule + renovation premium. See SOFT COSTS sheet.
B17: Structural Engineering | C17: ='SOFT COSTS'!F57 -> 131968.73 | D17: =IFERROR(C17/C13,0) -> 0.015 | E17: =IFERROR(C17/C36,0) -> 0.01179709 | F17: See SOFT COSTS sheet for rate and override.
B18: Mechanical Engineering (HVAC) | C18: ='SOFT COSTS'!F58 -> 158362.48 | D18: =IFERROR(C18/C13,0) -> 0.018 | E18: =IFERROR(C18/C36,0) -> 0.014156508 | F18: See SOFT COSTS sheet for rate and override.
B19: Electrical Engineering | C19: ='SOFT COSTS'!F59 -> 131968.73 | D19: =IFERROR(C19/C13,0) -> 0.015 | E19: =IFERROR(C19/C36,0) -> 0.01179709 | F19: See SOFT COSTS sheet for rate and override.
B20: Plumbing Engineering | C20: ='SOFT COSTS'!F60 -> 87979.156 | D20: =IFERROR(C20/C13,0) -> 0.01 | E20: =IFERROR(C20/C36,0) -> 0.0078647267 | F20: See SOFT COSTS sheet for rate and override.
B21: Fire Protection Engineering | C21: ='SOFT COSTS'!F61 -> 70383.325 | D21: =IFERROR(C21/C13,0) -> 0.008 | E21: =IFERROR(C21/C36,0) -> 0.0062917814 | F21: See SOFT COSTS sheet for rate and override.
B22: Civil Engineering | C22: ='SOFT COSTS'!F62 -> 105574.99 | D22: =IFERROR(C22/C13,0) -> 0.012 | E22: =IFERROR(C22/C36,0) -> 0.009437672 | F22: See SOFT COSTS sheet. Minimal for interior-only scope.
B23: Geotechnical / Soils Report | C23: ='SOFT COSTS'!F63 -> 43989.578 | D23: =IFERROR(C23/C13,0) -> 0.005 | E23: =IFERROR(C23/C36,0) -> 0.0039323634 | F23: Fixed fee item for new foundations or unknown conditions.
B24: Other Consultants & Owner Costs | C24: ='SOFT COSTS'!F85 -> 439895.78 | D24: =IFERROR(C24/C13,0) -> 0.05 | E24: =IFERROR(C24/C36,0) -> 0.039323634 | F24: Technology, legal, permits, insurance, testing, environmental. See SOFT COSTS.
B25: TOTAL SOFT COSTS | C25: ='SOFT COSTS'!F86 -> 1948738.3 | D25: =IFERROR(C25/C13,0) -> 0.2215 | E25: =IFERROR(C25/C36,0) -> 0.1742037
B27: SECTION 3 — OWNER CONTINGENCY & PREDEVELOPMENT
B28: Owner Project Contingency (post-GMP) | C28: =IFERROR(D28*C13,0) -> 439895.78 | D28: 0.05 | E28: =IFERROR(C28/C36,0) -> 0.039323634 | F28: Owner-held contingency for scope changes, unforeseen conditions, and owner decisions after GMP. Recommend 5%–10%.
B29: Predevelopment Costs (M4Di P1–P3 fees) | C29: =IFERROR(D29*C13,0) -> 0 | D29: 0 | E29: =IFERROR(C29/C36,0) -> 0 | F29: M4Di feasibility ops fees already incurred or contracted. Enter fixed dollar amount in override on SOFT COSTS.
B30: FF&E — Furniture, Fixtures & Equipment | C30: =IFERROR(D30*C13,0) -> 0 | D30: 0 | E30: =IFERROR(C30/C36,0) -> 0 | F30: Non-construction FF&E not in the construction contract. Enter lump sum estimate.
B31: Technology / AV / Security Systems | C31: =IFERROR(D31*C13,0) -> 0 | D31: 0 | E31: =IFERROR(C31/C36,0) -> 0 | F31: Owner-procured tech systems outside of construction contract. Enter estimate.
B32: Moving / Relocation / Swing Space | C32: =IFERROR(D32*C13,0) -> 0 | D32: 0 | E32: =IFERROR(C32/C36,0) -> 0 | F32: If applicable. Enter fixed estimate.
B33: Program Reserve (funding gap buffer) | C33: =IFERROR(D33*C13,0) -> 0 | D33: 0 | E33: =IFERROR(C33/C36,0) -> 0 | F33: Discretionary reserve for funding shortfalls. Typically 3%–8% of total project cost for nonprofit owners.
B34: TOTAL OWNER CONTINGENCY & OTHER | C34: =C28+C29+C30+C31+C32+C33 -> 439895.78 | D34: =IFERROR(C34/C13,0) -> 0.05 | E34: =IFERROR(C34/C36,0) -> 0.039323634
B36: TOTAL PROJECT INVESTMENT | C36: =C13+C25+C34 -> 11186550 | D36: 1
B38: SUMMARY METRICS
B39: Total Project Investment | C39: =C36 -> 11186550
B40: Hard Cost ROM | C40: ='BID SUMMARY'!C12 -> 8797915.6
B41: Soft Costs (professional fees + other) | C41: ='SOFT COSTS'!F86 -> 1948738.3
B42: Soft Costs as % of Hard Costs | C42: =IFERROR('SOFT COSTS'!F86/'BID SUMMARY'!C12,0) -> 0.2215 | D42: Benchmark: 18%–25% typical community facility; 25%–35% complex renovation/new construction.
B43: Total Project Cost / SF | C43: =IFERROR(C36/ASSUMPTIONS!C9,0) -> 407.49489 | D43: Total investment including all soft costs. Compare to $/SF benchmarks in SF BENCHMARK sheet.
B44: Hard Cost / SF | C44: ='BID SUMMARY'!C14 -> 320.48359 | D44: Construction cost only. Use for benchmarking against comparable projects.

Sheet SIGNAGE PROGRAM
B2: M4Di™ SIGNAGE PROGRAM BRIEF
B3: Wayfinding · Room Identification · Life Safety · Brand Framework
B4: =ASSUMPTIONS!C3&" | "&ASSUMPTIONS!C2&" | Phase: "&ASSUMPTIONS!C5 -> M-Well Community Health Campus | Value | Phase: ROM / Conceptual
B6: SECTION A — SIGNAGE PHILOSOPHY & M4Di APPROACH
B7: Signage is a life-safety, regulatory compliance, and program quality issue — not a finishing detail. M4Di introduces the signage program at P1 as a named allowance, refines it at P3, and locks it in the ALDi Gate 0 Owner Cost budget. This brief is the P3 deliverable that protects the owner from an unbudgeted post-construction cost.
B9: SECTION B — SIGNAGE CATEGORY FRAMEWORK
B10: B | C10: Category | D10: Description | E10: Code Basis | F10: Who Owns It | G10: Phase 1 Budget Low | H10: Phase 1 Budget High | I10: Status | J10: Notes
B11: CAT-1 | C11: Life Safety Signage | D11: Exit signs (NFPA 101), exit path markings, stairwell ID, occupant load placards, fire door labels | E11: NFPA 101 · IBC · IFC | F11: Contractor (in hard cost) | G11: 18000 | H11: 28000 | I11: In ROM
B12: CAT-2 | C12: ADA Regulatory Compliance Signage | D12: Tactile room signs (Braille + raised characters), restroom ID, accessible route, elevator tactile indicators | E12: ADA · ICC A117.1 · 28 CFR Part 36 | F12: Contractor (in hard cost) | G12: 12000 | H12: 22000 | I12: In ROM
B13: CAT-3 | C13: Room Identification & Numbering System | D13: Consistent room number schedule keyed to life safety floor plans. Required for DDDS licensing inspection and emergency response. | E13: NFPA 101 § 7.10 · DDDS inspection | F13: AE / Owner | G13: 8000 | H13: 15000 | I13: Allowance
B14: CAT-4 | C14: Wayfinding & Directional Signage | D14: Entrance identification, floor directories, corridor directionals, campus orientation map at entry. Supports resident orientation and staff efficiency. | E14: Best practice · DDDS quality standard | F14: Owner Furnished | G14: 25000 | H14: 55000 | I14: Allowance
B15: CAT-5 | C15: Campus & Building Exterior Identification | D15: Building name sign, address numerals, site entrance marker, accessible parking signage | E15: IBC · ADA · County signage ordinance | F15: Owner Furnished | G15: 12000 | H15: 28000 | I15: Allowance
B16: CAT-6 | C16: Donor Recognition & Community Identity | D16: Major donor wall, program sponsor recognition, mission statement display, community artwork integration | E16: Owner discretion | F16: Owner Furnished | G16: 0 | H16: 35000 | I16: Optional
C17: TOTAL OWNER-FURNISHED SIGNAGE ALLOWANCE (CAT 3+4+5+6) | G17: =G13+G14+G15+G16 -> 45000 | H17: =H13+H14+H15+H16 -> 133000
B19: SECTION C — ROOM IDENTIFICATION SCHEDULE (Phase 1 — School Renovation)
B20: Room numbers follow M4Di standard: Floor prefix (1 or 2) + sequential 3-digit number. Example: 1-101 = Floor 1, Room 101. Life safety floor plans, DDDS licensing application, and emergency response documentation all reference this schedule. AE incorporates into CD door and room finish schedule.
B21: B | C21: Room No. | D21: Floor | E21: Room Name / Function | F21: IDD Program Use | G21: SF (approx) | H21: Sign Type (CAT) | I21: ADA Tactile Required? | J21: Sign Text (proposed)
B22: 1-101 | C22: 1 | D22: Resident Room — Private (with bath) | E22: High-acuity / medical fragility | F22: 260 | G22: CAT-2/3 | H22: Yes | I22: Room 1-101
B23: 1-102 | C23: 1 | D23: Resident Room — Private (with bath) | E23: High-acuity / medical fragility | F23: 260 | G23: CAT-2/3 | H23: Yes | I23: Room 1-102
B24: 1-103 | C24: 1 | D24: Resident Room — Private (with bath) | E24: High-acuity / medical fragility | F24: 260 | G24: CAT-2/3 | H24: Yes | I24: Room 1-103
B25: 1-104 | C25: 1 | D25: Resident Room — Private (with bath) | E25: High-acuity / medical fragility | F25: 260 | G25: CAT-2/3 | H25: Yes | I25: Room 1-104
B26: 1-105 | C26: 1 | D26: Resident Room — Shared (2-bed) | E26: Standard residential | F26: 220 | G26: CAT-2/3 | H26: Yes | I26: Room 1-105
B27: 1-106 | C27: 1 | D27: Resident Room — Shared (2-bed) | E27: Standard residential | F27: 220 | G27: CAT-2/3 | H27: Yes | I27: Room 1-106
B28: 1-107 | C28: 1 | D28: Resident Room — Shared (2-bed) | E28: Standard residential | F28: 220 | G28: CAT-2/3 | H28: Yes | I28: Room 1-107
B29: 1-108 | C29: 1 | D29: Resident Room — Shared (2-bed) | E29: Standard residential | F29: 220 | G29: CAT-2/3 | H29: Yes | I29: Room 1-108
B30: 1-109 | C30: 1 | D30: Resident Room — Flex Double | E30: Convertible single/double | F30: 200 | G30: CAT-2/3 | H30: Yes | I30: Room 1-109
B31: 1-110 | C31: 1 | D31: Resident Room — Flex Double | E31: Convertible single/double | F31: 200 | G31: CAT-2/3 | H31: Yes | I31: Room 1-110
B32: 1-111 | C32: 1 | D32: Resident Room — Private (shared bath) | E32: Standard residential | F32: 180 | G32: CAT-2/3 | H32: Yes | I32: Room 1-111
B33: 1-112 | C33: 1 | D33: Resident Room — Private (shared bath) | E33: Standard residential | F33: 180 | G33: CAT-2/3 | H33: Yes | I33: Room 1-112
... B81: 2-404 | C81: 2 | D81: Mechanical / Electrical | E81: Building systems | F81: 200 | G81: CAT-2/3 | H81: No | I81: Mechanical
B82: EXT-01 | C82: EXT | D82: Building Entrance — Primary | E82: Main accessible entry | G82: CAT-4/5 | H82: Yes | I82: M-Well Community Health Campus
B83: EXT-02 | C83: EXT | D83: Building Entrance — Secondary | E83: Staff / service entry | G83: CAT-4/5 | H83: No | I83: Staff Entrance
B84: EXT-03 | C84: EXT | D84: Campus Address Numerals | E84: Street-facing ID | G84: CAT-5 | H84: No | I84: 3110
B85: EXT-04 | C85: EXT | D85: Accessible Parking — Reserved | E85: ADA van accessible spaces | G85: CAT-5 | H85: Yes | I85: Accessible Parking
B86: EXT-05 | C86: EXT | D86: Campus Orientation Map | E86: Entry lobby wayfinding | G86: CAT-4 | H86: Yes | I86: M-Well Campus · You Are Here
B87: EXT-06 | C87: EXT | D87: Floor Directory — Level 1 | E87: Lobby / elevator lobby | G87: CAT-4 | H87: Yes | I87: Floor 1 Directory
B88: EXT-07 | C88: EXT | D88: Floor Directory — Level 2 | E88: Elevator lobby Level 2 | G88: CAT-4 | H88: Yes | I88: Floor 2 Directory
C89: TOTAL SIGN LOCATIONS: 67 (interior rooms + exterior campus)
B91: SECTION D — SIGNAGE BUDGET SUMMARY & OI TOOL PLACEMENT
B92: B | C92: Category | D92: OI Tool Location | E92: Line Reference | F92: Low | G92: High | H92: Notes
B93: CAT-1: Life Safety Signage | C93: HARD COST — Fire Protection / Electrical | D93: In TAKEOFF | E93: $18,000 | F93: $28,000 | G93: Already in ROM. Do not double-count.
B94: CAT-2: ADA Regulatory Signage | C94: HARD COST — Interior Buildout | D94: In TAKEOFF | E94: $12,000 | F94: $22,000 | G94: ~$110/door × 70 rooms + shared. Verify in TAKEOFF line FIN-series.
B95: CAT-3: Room ID + Numbering System | C95: OWNER COST — Signage Allowance | D95: ALLOWANCE LOG · ALW-SGN-01 | E95: $8,000 | F95: $15,000 | G95: M4Di room schedule generated from this tab. Fabricator prices from schedule.
B96: CAT-4: Wayfinding + Directional | C96: OWNER COST — Signage Allowance | D96: ALLOWANCE LOG · ALW-SGN-02 | E96: $25,000 | F96: $55,000 | G96: Highest orphan risk. Must be named line in Gate 0 Owner Cost budget.
B97: CAT-5: Exterior / Campus ID | C97: OWNER COST — Signage Allowance | D97: ALLOWANCE LOG · ALW-SGN-03 | E97: $12,000 | F97: $28,000 | G97: NCC sign permit required. 8–12 week fabrication lead time.
B98: CAT-6: Donor / Community Identity | C98: OWNER COST — Optional Allowance | D98: ALLOWANCE LOG · ALW-SGN-04 | E98: $0 | F98: $35,000 | G98: Optional. IDD residential: sensory-calm displays recommended.
C99: TOTAL OWNER-FURNISHED SIGNAGE (CAT 3+4+5+6 combined range) | E99: $45,000 | F99: $133,000
B101: SECTION E — BRAND FRAMEWORK OPTIONS (for owners without existing brand)
B102: M4Di provides three lightweight brand framework options for nonprofits and physician groups that do not have an established visual identity. These are not full brand identities — they are functional signage systems that prevent mismatched signs and ensure visual coherence across the facility. Select one option; the AE and sign fabricator work from it.
B103: B | C103: Option | D103: System Name | E103: Color System | F103: Typeface | G103: Material Spec | H103: Best For | I103: Status
B104: Option A | C104: Calm Clarity | D104: Soft white substrate · warm grey text · teal accent bar | E104: DM Sans (Google Fonts — free) | F104: Brushed aluminum extrusion · acrylic face · vinyl applied text | G104: IDD residential / behavioral health / community health. Neutral, non-institutional, sensory-calm. | H104: RECOMMENDED for M-Well
B105: Option B | C105: Civic Anchor | D105: Navy substrate · white text · warm gold accent bar | E105: Source Sans Pro (Google Fonts — free) | F105: Painted steel extrusion · dimensional letters on exterior | G105: Faith-based facilities / community centers / civic buildings. Authoritative, familiar. | H105: Alternative
B106: Option C | C106: Modern Community | D106: Dark charcoal substrate · white text · green accent (M4Di #196b23) | E106: Inter (Google Fonts — free) | F106: PVC substrate · UV-printed face · flush-mount wall panel | G106: Mixed-use / community development / CDFI-funded projects. Contemporary, mission-aligned. | H106: Alternative
B108: SELECTED BRAND OPTION (enter choice): | E108: Option A — Calm Clarity | F108: Update this cell when client confirms brand direction. This selection governs the sign fabricator RFP.
B110: SECTION F — ALLOWANCE LOG ENTRIES (copy to ALLOWANCE LOG tab at Gate 0)
B111: These four entries should be copied into the ALLOWANCE LOG tab when the ALDi Budget Tracker is initiated at Gate 0. They become the live tracking records for signage decisions through design and construction.
B112: B | C112: ID | D112: Spec Section | E112: Category | F112: Description | G112: Allowance Amount | H112: Basis | I112: Owner Decision Required? | J112: Status
B113: ALW-SGN-01 | C113: 10 14 00 | D113: Signage | E113: Room ID + Numbering System | F113: 10000 | G113: M4Di room schedule generated from SIGNAGE PROGRAM tab. 57 interior sign locations + hardware. | H113: Yes | I113: Pending
B114: ALW-SGN-02 | C114: 10 14 53 | D114: Signage | E114: Wayfinding + Directional System | F114: 38000 | G114: Campus orientation map, floor directories, corridor directionals. Exterior entry identification. | H114: Yes | I114: Pending
B115: ALW-SGN-03 | C115: 10 14 00 | D115: Signage | E115: Exterior + Campus Identity | F115: 18000 | G115: Building name sign, address numerals, accessible parking. NCC sign permit required. | H115: Yes | I115: Pending
B116: ALW-SGN-04 | C116: 10 14 00 | D116: Signage | E116: Donor / Community Identity (optional) | F116: 0 | G116: Budget TBD by owner. Recommend IDD-appropriate sensory-calm displays. $0 if not pursued. | H116: Yes | I116: Pending
C117: TOTAL SIGNAGE ALLOWANCE (enter in TOTAL PROJECT BUDGET → Owner Costs) | F117: =SUM(F113:F116) -> 66000
B119: SECTION G — WHEN TO INTRODUCE SIGNAGE IN THE M4Di WORKFLOW
B120: B | C120: Stage | D120: Action Required
B121: P1 · FeasOps™ | C121: Introduce signage as a named allowance in the ROM. Add CAT-3+4+5 to the Owner Cost section of TOTAL PROJECT BUDGET. Size by project type: IDD residential = $8–15/SF of occupied program SF. Flag as a deferred decision risk in the P1 Risk Memo. NOTE: for DDDS licensing facilities, wayfinding quality directly affects licensing reviewer impressions.
B122: P2 · FeasOps™ | C122: Refine the signage allowance using the confirmed room count from the test fit. Generate a preliminary room schedule (this tab Section C). Update the allowance range from parametric to quantity-based. Confirm which brand framework option is appropriate for the owner type.
B123: P3 · FeasOps™ | C123: Deliver the completed SIGNAGE PROGRAM BRIEF (this tab) as a standalone P3 deliverable or add-on ($3,500–$6,000 depending on scale). Provide the room schedule, category framework, budget summary, brand framework recommendation, and ALLOWANCE LOG entries ready to copy to Gate 0.
B124: Gate 0 · ALDi™ | C124: Copy the four ALW-SGN-01 through 04 entries into the ALLOWANCE LOG. Add the signage total as a named line in Section 3 (Owner Contingency & Other) of TOTAL PROJECT BUDGET. Column D locks with signage as a visible, protected line — not buried in FF&E.
B125: Gate 1–2 | C125: AE incorporates room schedule into CD door and room finish schedule. Sign fabricator RFP issued by owner (M4Di provides scope document from this tab). Selection memo required per M4Di procurement standards. Allowance resolves to fixed price when fabricator is selected.
B126: Gate 3–4 | C126: Fabricator selected. Signage contract executed. Allowance closes and actual price enters Column F. Installation typically occurs at construction closeout — coordinate with punch list. Final room signs = prerequisite for DDDS final licensing inspection.
B128: M4Di™ Signage Program Brief · © 2026 Merge 4 Design LLC d/b/a M4Di · Confidential — For project use only · All marks draft pending legal confirmation

Sheet TAB QA
B1: TAB QA — CRITICAL FORMULA CHECKS & WORKBOOK VALIDATION
B2: Use this sheet after any revision to confirm critical formulas are working correctly. Open in Excel, press Ctrl+Alt+F9 to force full recalculation, then review each check.
B3: Check ID | C3: Sheet | D3: Cell | E3: Description | F3: Expected Behavior | G3: Live Value | H3: Manual QA Result | I3: Reviewer Notes
B4: QA-01 | C4: ASSUMPTIONS | D4: C12 | E4: Weighted trade labor factor | F4: Returns 1.000x for Delaware and ~1.145x for Philadelphia Metro | G4: =ASSUMPTIONS!C12 -> 1 | H4: Not Checked
B5: QA-02 | C5: REGIONAL FACTORS | D5: I3 | E5: Delaware weighted labor basket | F5: Returns a numeric weighted basket (should be ~26.17) | G5: ='REGIONAL FACTORS'!I3 -> 26.172 | H5: Not Checked
B6: QA-03 | C6: REGIONAL FACTORS | D6: I4 | E6: Philadelphia region factor | F6: Returns factor >1.000x (should be ~1.145) | G6: ='REGIONAL FACTORS'!I4 -> 26.03 | H6: Not Checked
B7: QA-04 | C7: UNIT PRICE LIBRARY | D7: K3 | E7: Adjusted unit price row 3 | F7: Returns numeric adjusted unit price (Base Price × Region Factor × Escalation) | G7: ='UNIT PRICE LIBRARY'!K3 -> 0 | H7: Not Checked
B8: QA-05 | C8: TAKEOFF | D8: L3 | E8: Adj. unit cost VLOOKUP row 3 | F8: Returns matching adjusted unit cost from UNIT PRICE LIBRARY via Cost Code VLOOKUP | G8: =TAKEOFF!L3 -> 0 | H8: Not Checked
B9: QA-06 | C9: TAKEOFF | D9: M3 | E9: Takeoff line total row 3 | F9: Returns quantity × adjusted unit cost (or 0 if Included = No) | G9: =TAKEOFF!M3 -> 0 | H9: Not Checked
B10: QA-07 | C10: FLOOR SUMMARY | D10: C3 | E10: LL base building total | F10: Sums all LL rows from TAKEOFF where Included = Yes or Allowance | G10: ='FLOOR SUMMARY'!C3 -> 2451138.8 | H10: Not Checked
B11: QA-08 | C11: FLOOR SUMMARY | D11: I8 | E11: Total Project ROM | F11: Should equal sum of all floor totals in column J | G11: ='FLOOR SUMMARY'!I8 -> 181796.77 | H11: Not Checked
B12: QA-09 | C12: BID SUMMARY | D12: C10 | E12: TOTAL PROJECT ROM | F12: Should match FLOOR SUMMARY total project ROM within rounding | G12: ='BID SUMMARY'!C12 -> 8797915.6 | H12: Not Checked
B13: QA-10 | C13: BID SUMMARY | D13: C14 | E13: Project cost per SF | F13: Total ROM / Project SF from ASSUMPTIONS. Returns numeric $/SF. | G13: ='BID SUMMARY'!C14 -> 320.48359 | H13: Not Checked
B14: QA-11 | C14: OWNER SELECTIONS | D14: M12 | E14: Owner selection allowance total | F14: Returns sum of all Allowance Each × Qty. Should match EQUIPMENT ALLOWANCES total. | G14: ='OWNER SELECTIONS'!M12 -> 0 | H14: Not Checked
B15: QA-12 | C15: SF BENCHMARK | D15: C6 | E15: Calculated project cost / SF | F15: Returns numeric $/SF from BID SUMMARY | G15: ='SF BENCHMARK'!C6 -> 320.48359 | H15: Not Checked
B16: QA-13 | C16: SF BENCHMARK | D16: F6 | E16: Sanity check text | F16: Returns readable text: Within historical range / Above / Below | G16: ='SF BENCHMARK'!F6 -> Within historical range | H16: Not Checked
B17: QA-14 | C17: HISTORICAL DB | D17: H4 | E17: Historical cost per SF row 4 | F17: Returns numeric cost/SF for the first historical project | G17: ='HISTORICAL DB'!H4 -> 177.77778 | H17: Not Checked
B18: QA-15 | C18: ALLOWANCE LOG | D18: F12 | E18: Total open allowances | F18: Sum of all allowance amounts. Should be > $0 while items are pending. | G18: ='ALLOWANCE LOG'!F12 -> 0 | H18: Not Checked
B21: QUICK QA STEPS
B22: 1. Open workbook in desktop Excel (not browser).
B23: 2. Press Ctrl+Alt+F9 to force full recalculation of all formulas.
B24: 3. Review Live Value column — confirm no REF errors, VALUE errors, NAME errors, or blank totals.
B25: 4. Check BID SUMMARY Total ROM vs. FLOOR SUMMARY Total ROM — should match.
B26: 5. Confirm ALLOWANCE LOG pending count matches OWNER SELECTIONS pending count.
B27: 6. Mark each check as Pass / Fail / Review.
B28: 7. Save a dated revision copy before issuing to any external party.
