Workbook

Sheet Overview
B1: MERGE 4 DESIGN LLC × L.E.E.P., INC.
B2: FORWARD HOME PROGRAM
B3: City of Wilmington Vacant Lot Initiative — Four-Tier Building Package Proforma
B4: $220K–$250K (T1) to $267K–$317K (T4 off-grid) · L.E.E.P. trained workforce · May 2026
B5: Merge 4 Design LLC · 215 N. Market St. Suite 317 · Wilmington DE 19801 · merge4design.com
B6: L.E.E.P., Inc. · Gwenevere Motley, Executive Director · Trained installation workforce
B8: PROGRAM SUMMARY — TYPE D 10-UNIT CLUSTER
B9: Total units (Type D pilot) | C9: ='Type D — 10 Units'!D6 -> 1350
B10: T1 sale price per unit | C10: ='Type D — 10 Units'!D8 -> 0
B11: T1 gross revenue | C11: ='Type D — 10 Units'!D35 -> 31
B12: T1 total project cost | C12: ='Type D — 10 Units'!D26 -> 44775
B13: T1 developer net margin | C13: ='Type D — 10 Units'!D38 -> 0
B14: T1 developer margin % | C14: ='Type D — 10 Units'!D39 -> #DIV/0!
B15: Build schedule | C15: 31 weeks
B16: Land cost (City program) | C16: $1 per lot
B17: Investor equity trigger | C17: ='Type D — 10 Units'!D11 -> 261127800000000
B18: Construction loan | C18: ='Type D — 10 Units'!D12 -> 0
B21: FOUR-TIER PRICE AND PERFORMANCE OVERVIEW
B22: Tier | C22: HERS | D22: Sale price (net §45L) | E22: Build premium | F22: Grid status | G22: Food production
B23: T1 — Forward Code+ | C23: 55–70 | D23: $220K–$250K | E23: Base | F23: Grid | G23: —
B24: T2 — Forward Zero | C24: 0–30 | D24: $227K–$263K | E24: ~+$12K–$18K | F24: Grid | G24: —
B25: T3 — Forward Positive | C25: Neg–+10 | D25: $243K–$287K | E25: ~+$28K–$42K | F25: Grid (PV export) | G25: 200–400 lbs/yr
B26: T4 — Forward Harvest | C26: Net positive | D26: $267K–$317K | E26: ~+$52K–$72K | F26: Off-grid capable | G26: 200–600 lbs/yr
B28: NOTE: All proformas at G0 ROM ±25%. Land=$1/lot (City program). Site work+utilities City-funded. Blue cells=inputs. Navigate tabs for full proformas. §45L credit=$5,000/unit (T2–T4 DOE Zero Energy Ready Home). | Soft costs disaggregated per CBai MEP Workflow SOP v1 (June 2026): A&E + MEP PE (CBai-assisted) + permits + M4Di OI Tool. Toggle Assumptions!C10 (1=First typology / 2=Repeat Claymont template) to model fee compression on repeat engagements.
B30: WORKBOOK NAVIGATION
B31: Overview | C31: This sheet — program summary, tier comparison, navigation
B32: Assumptions | C32: Shared inputs — change here to update all proformas
B33: Type A — 4 Units | C33: Single-lot 4-unit for-sale + rental proforma
B34: Type D — 10 Units | C34: 10-unit lot cluster pilot — T1 for-sale + rental
B35: Tier Premium Summary | C35: T1–T4 incremental premium cost analysis
B36: Schedule | C36: 31-week delivery schedule with phase milestones
B37: Cost Comparison | C37: Forward Panel vs. SIP vs. stick frame material cost

Sheet Assumptions
B1: SHARED ASSUMPTIONS — FORWARD HOME PROGRAM
B2: Blue/yellow cells = inputs. Change here — all four proforma tabs update automatically.
B4: CONSTRUCTION COST (per unit — per SF of wall or fixed)
B5: 4Ward-SIB panel system (per SF wall) | C5: 10.5 | D5: M4Di ALDDB; Barricade SIB ROM May 2026
B6: Foundation / structural (per SF) | C6: 5 | D6: M4Di ROM; Claymont AE24-002 reference
B7: MEP systems (per SF) | C7: 4 | D7: Includes heat pump; downsized 1 ton vs. stick
B8: Finishes / millwork / appliances (per SF) | C8: 5 | D8: Mid-range Forward Home spec
B9: SOFT COSTS — DISAGGREGATED (CBai MEP SOP v1)
B10: Typology (1 = First use / 2 = Repeat/Claymont template) | C10: 1 | D10: 1 = First engagement · 2 = Repeat (Claymont template) — toggles MEP PE fee
B11: A&E architectural fee (per unit) | C11: 5500 | D11: AOR subconsultant + schematic/permit drawings. Fixed regardless of typology.
B12: MEP PE fee — first typology (per unit, G0–G3) | C12: 3200
B13: MEP PE fee — repeat typology (Claymont template, per unit) | C13: 1800 | D13: 40–50% of full-service per SOP §3 repeat typology target. Available once Claymont G4 template archived (target Q4 2026).
B14: Permits / filing / AHJ fees (per unit) | C14: 1800 | D14: City of Wilmington residential permit. Fixed. Not affected by typology toggle.
B15: M4Di OI Tool / ALDi Tracker (per unit) | C15: 1200 | D15: Predevelopment ROM + ALDi gate tracking through G4. OED cost-verification standard.
B16: TOTAL SOFT COSTS / UNIT (active typology) | C16: =C11+IF(C10=1,C12,C13)+C14+C15 -> 11700 | D16: Active total — updates when typology toggle changes. First use: ~$11,700 · Repeat: ~$10,300
B17: Tier 4 MEP premium (per unit — cistern/agrivoltaic/island electrical) | C17: 3200 | D17: Additional PE scope: cistern plumbing, agrivoltaic trellis structural, island-mode electrical. Range $2,500-$4,000/unit. SOP v1.
B18: Contingency | C18: 0.08 | D18: 8% of hard + soft costs
B20: FINANCING
B21: Construction loan interest rate (annual)
B22: Build schedule — weeks (4Ward-SIB system) | C22: 31 | D22: vs. 35 wks std SIP; 39 wks stick (Offsite Builder 2025)
B23: Loan-to-cost ratio | C23: 0.8 | D23: Typical residential construction LTC
B25: REVENUE
B26: Type A avg. sale price / unit
B27: Type D avg. sale price / unit | C27: 235000 | D27: Cluster achieves higher end
B29: RENTAL SCENARIO
B30: Monthly rent / unit
B31: Stabilized expense ratio | C31: 0.45 | D31: NOI = 55%
B32: Cap rate (valuation) | C32: 0.062 | D32: Delaware multifamily Q1 2026 estimate
B34: CITY PROGRAM
B35: Land cost per lot (City program) | C35: 1 | D35: City of Wilmington vacant lot initiative
B36: Site work / utilities | C36: 0 | D36: Covered by City — developer cost $0
B38: TIER INCREMENTAL PREMIUMS (per unit, G0 ROM ±25%)
B39: Tier 2 — Forward Zero premium (mid) | C39: 15000 | D39: $12K–$18K range
B40: Tier 3 — Forward Positive premium (mid) | C40: 35000 | D40: $28K–$42K range
B41: Tier 4 — Forward Harvest premium (mid) | C41: 62000 | D41: $52K–$72K range
B42: IRA §45L developer credit (T2–T4) | C42: 5000 | D42: DOE Zero Energy Ready Home; T1 not eligible
B45: COLOR CODE: Blue = hardcoded input · Yellow background = key assumption · Green text = linked from this sheet · SOFT COSTS: Toggle C10 between 1 (first typology) and 2 (Claymont repeat template) to see CBai MEP SOP v1 fee compression effect on total.

Sheet Type A — 4 Units
B1: TYPE A — SINGLE LOT | 2–4 UNIT FORWARD HOME
B2: G0 ROM ±25% · For-sale + Rental · Land $1 (City) · Site/Utilities City-funded · L.E.E.P. workforce
B3: Line item | C3: Input / Formula | D3: Per unit | E3: Total (4 units)
B4: PROJECT INPUTS
B5: Number of units | C5: 4 | D5: 4
B6: Avg. unit size (SF) | C6: 1050 | D6: =C6 -> 1050 | E6: =D6*C5 -> 4200
B7: T1 sale price (from Assumptions) | C7: =Assumptions!C18 -> 0.08 | D7: =Assumptions!C18 -> 0.08 | E7: =D7*C5 -> 0.32
B9: SOURCES
B10: Investor equity (site control triggered) | C10: 180000 | D10: =C10/C5 -> 45000 | E10: =C10 -> 180000
B11: Construction loan (LTC × total cost) | D11: =D25*Assumptions!C14 -> 218262600000000 | E11: =D11*C5 -> 873050400000000
B12: City land + site/utilities | C12: City-funded
D13: City-funded
E14: City-funded
B16: USES (CONSTRUCTION COSTS)
B17: Panel system — 4Ward-SIB (SF × rate) | C17: =Assumptions!C5 -> 10.5 | D17: =C6*Assumptions!C5 -> 11025 | E17: =D17*C5 -> 44100
B18: Foundation / structural | C18: =Assumptions!C6 -> 5 | D18: =C6*Assumptions!C6 -> 5250 | E18: =D18*C5 -> 21000
B19: MEP systems (HVAC heat pump, plumbing, elec.) | C19: =Assumptions!C7 -> 4 | D19: =C6*Assumptions!C7 -> 4200 | E19: =D19*C5 -> 16800
B20: Finishes / millwork / appliances | C20: =Assumptions!C8 -> 5 | D20: =C6*Assumptions!C8 -> 5250 | E20: =D20*C5 -> 21000
B21: Soft costs — A&E + MEP PE + permits + M4Di (per unit) | C21: =Assumptions!C16 -> 11700 | D21: =Assumptions!C16 -> 11700 | E21: =Assumptions!C16*C6 -> 12285000
B22: ↳ Typology toggle: see Assumptions!C10 (1=First ~$11.7K · 2=Repeat ~$10.3K)
B23: Subtotal pre-contingency | D23: =SUM(D17:D21) -> 37425 | E23: =SUM(E17:E21) -> 12387900
B24: Contingency (8%) | C24: =Assumptions!C18 -> 0.08 | D24: =D22*Assumptions!C18 -> 0 | E24: =E22*Assumptions!C18 -> 0
B25: Loan carry (31 wks @ 10.25%) | D25: =(D22+D23)*(Assumptions!C13/Assumptions!C15)*Assumptions!C14*Assumptions!C15 -> 121257000000 | E25: =D24*C5 -> 0
B26: TOTAL PROJECT COST | D26: =D22+D23+D24 -> 37425 | E26: =E22+E23+E24 -> 12387900
B28: FOR-SALE RETURN
B29: Gross sale revenue | D29: =Assumptions!C18 -> 0.08 | E29: =D28*C5 -> 0
B30: Less: total project cost | D30: =D25 -> 121257000000 | E30: =E25 -> 0
B31: DEVELOPER NET MARGIN | D31: =D28-D25 -> -121257000000 | E31: =E28-E25 -> 0
B32: Developer margin % | D32: =D30/D28 -> #DIV/0! | E32: =E30/E28 -> #DIV/0!
B34: RENTAL ALTERNATIVE
B35: Monthly rent / unit | D35: =Assumptions!C22 -> 31 | E35: =D34*C5 -> 0
B36: Gross annual income | D36: =D34*12 -> 0 | E36: =E34*12 -> 0
B37: NOI (55% ratio) | D37: =D35*(1-Assumptions!C23) -> 6.2 | E37: =E35*(1-Assumptions!C23) -> 0
B38: Stabilized cap rate | D38: =Assumptions!C24 -> 0
B39: Stabilized asset value (NOI ÷ cap rate) | D39: =D36/Assumptions!C24 -> #DIV/0! | E39: =E36/Assumptions!C24 -> #DIV/0!

Sheet Type D — 10 Units
B1: TYPE D — 10-UNIT LOT CLUSTER | PILOT PROPOSAL
B2: G0 ROM ±25% · For-sale + Rental · Land $1/lot · Site/Utilities City-funded · Investor equity at site control · L.E.E.P. workforce
B3: Line item | C3: Input / Formula | D3: Per unit | E3: Total (10 units)
B4: PROJECT INPUTS
B5: Number of units | C5: 10 | D5: 10
B6: Avg. unit size (SF) | C6: 1350 | D6: =C6 -> 1350 | E6: =D6*C5 -> 13500
B7: T1 sale price (from Assumptions) | C7: =Assumptions!C19 -> 0 | D7: =Assumptions!C19 -> 0 | E7: =D7*C5 -> 0
B9: SOURCES
B10: Investor equity (site control triggered) | C10: 500000 | D10: =C10/C5 -> 50000 | E10: =C10 -> 500000
B11: Construction loan (LTC × total cost) | D11: =D25*Assumptions!C14 -> 261127800000000 | E11: =D11*C5 -> 2.611278e+15
B12: City land ($1 × 10 lots) + site/utilities | C12: City-funded
D13: City-funded
E14: City-funded
B16: USES
B17: 4Ward-SIB Forward Panel (SF × rate) | C17: =Assumptions!C5 -> 10.5 | D17: =C6*Assumptions!C5 -> 14175 | E17: =D17*C5 -> 141750
B18: Foundation / structural | C18: =Assumptions!C6 -> 5 | D18: =C6*Assumptions!C6 -> 6750 | E18: =D18*C5 -> 67500
B19: MEP (HVAC + plumbing + elec.) | C19: =Assumptions!C7 -> 4 | D19: =C6*Assumptions!C7 -> 5400 | E19: =D19*C5 -> 54000
B20: Finishes / millwork / appliances | C20: =Assumptions!C8 -> 5 | D20: =C6*Assumptions!C8 -> 6750 | E20: =D20*C5 -> 67500
B21: Soft costs — A&E + MEP PE + permits + M4Di (per unit) | C21: =Assumptions!C16 -> 11700 | D21: =Assumptions!C16 -> 11700 | E21: =Assumptions!C16*C6 -> 15795000
B22: ↳ Typology toggle: see Assumptions!C10 (1=First ~$11.7K · 2=Repeat ~$10.3K)
B23: Subtotal pre-contingency | D23: =SUM(D17:D21) -> 44775 | E23: =SUM(E17:E21) -> 16125750
B24: Contingency (8%) | C24: =Assumptions!C18 -> 0.08 | D24: =D22*Assumptions!C18 -> 0 | E24: =E22*Assumptions!C18 -> 0
B25: Loan carry (31 wks @ 10.25%) | D25: =(D22+D23)*(Assumptions!C13/Assumptions!C15)*Assumptions!C14*Assumptions!C15 -> 145071000000 | E25: =D24*C5 -> 0
B26: TOTAL PROJECT COST | D26: =D22+D23+D24 -> 44775 | E26: =E22+E23+E24 -> 16125750
B28: FOR-SALE RETURN
B29: Gross sale revenue | D29: =Assumptions!C19 -> 0 | E29: =D28*C5 -> 0
B30: Less: total project cost | D30: =D25 -> 145071000000 | E30: =E25 -> 0
B31: DEVELOPER NET MARGIN | D31: =D28-D25 -> -145071000000 | E31: =E28-E25 -> 0
B32: Developer margin % | D32: =D30/D28 -> #DIV/0! | E32: =E30/E28 -> #DIV/0!
B34: RENTAL ALTERNATIVE
B35: Monthly rent / unit | D35: =Assumptions!C22 -> 31 | E35: =D34*C5 -> 0
B36: Gross annual income | D36: =D34*12 -> 0 | E36: =E34*12 -> 0
B37: NOI (55%) | D37: =D35*(1-Assumptions!C23) -> 6.2 | E37: =E35*(1-Assumptions!C23) -> 0
B38: Stabilized cap rate | D38: =Assumptions!C24 -> 0
B39: Stabilized asset value | D39: =D36/Assumptions!C24 -> #DIV/0! | E39: =E36/Assumptions!C24 -> #DIV/0!

Sheet Tier Premium Summary
B1: FORWARD HOME — FOUR-TIER PREMIUM COST SUMMARY
B2: Incremental premiums above Tier 1 base · Per unit · G0 ROM ±25% · 1,300 SF Type D 10-unit cluster
B3: Cost element | C3: T1 Code+ | D3: T2 Zero | E3: T3 Positive | F3: T4 Harvest
B4: 4Ward-SIB Forward Panel system | C4: $13,650 | D4: $13,650 | E4: $13,650 | F4: $13,650
B5: Foundation — Superior Walls Xi Plus (T2–4) | C5: Base CMU | D5: + $4,200–$6,500 | E5: + $4,200–$6,500 | F5: + $4,200–$6,500
B6: Cavity insulation — mineral wool upgrade | C6: Std batt | D6: + $800–$1,200 | E6: + $800–$1,200 | F6: + $800–$1,200
B7: Interior air barrier membrane (T3–4) | C7: — | D7: — | E7: + $1,400–$2,200 | F7: + $1,400–$2,200
B8: Allura cladding — base Lap (all tiers) | C8: $8,450 | D8: $8,450 | E8: $8,450 | F8: $8,450
B9: Allura Panel + Shakes upgrade | C9: Base | D9: + $1,200–$1,800 | E9: + $2,400–$3,600 | F9: + $2,400–$3,600
B10: Crystal Magnus 4500 windows — double-pane | C10: $7,800–$9,200 | D10: Base included | E10: → upgrade to 4700 | F10: → upgrade to 4700
B11: Window upgrade — triple-pane/4700 | C11: — | D11: + $2,400–$3,600 | E11: + $4,800–$6,400 | F11: + $4,800–$6,400
B12: HVAC — Quilt 3-zone (T2 + T4) | C12: Std mini-split | D12: + $2,800–$4,200 | E12: — | F12: Quilt battery-opt.
B13: HVAC — Mitsubishi FX H2i sumo (T3) | C13: — | D13: — | E13: + $4,200–$6,000 | F13: —
B14: HVAC — GSHP alternate (T3 site-dependent) | C14: — | D14: — | E14: + $8,000–$14,000 | F14: —
... B31: IRA §45L developer credit | C31: — | D31: –$5,000/unit | E31: –$5,000/unit | F31: –$5,000/unit
B32: Net to buyer after §45L
B34: L.E.E.P., Inc. trained workforce is included across all four tiers. §45L = $5,000/unit developer credit for DOE Zero Energy Ready Home certification (Tiers 2–4). Buyers may also claim §25C credits for heat pump/water heater. 30% ITC on PV for developer/owner.

Sheet Schedule
B1: FORWARD HOME — 31-WEEK DELIVERY SCHEDULE
B2: 4Ward-SIB Forward Panel system · L.E.E.P. installation crew · All four tiers use same schedule framework
B3: Phase | C3: Timing | D3: Key deliverables | E3: Milestone
B4: Phase 1 — Predevelopment (M4Di) | C4: Wks 1–6 | D4: LOI executed · Investor equity activated · G0 ROM verification · Site + zoning analysis (Ch. 48) · Tier selection · DOE/PHIUS enrollment (T2–4) | E4: Equity committed
B5: Phase 2 — Design + Permitting | C5: Wks 7–18 | D5: Schematic design · Permit drawings (AOR stamp) · AHJ submission · M4Di ALDi cost control | E5: Permit approved
B6: Phase 3 — Fabrication + Site Prep | C6: Wks 12–22 | D6: 4Ward-SIB panel order (concurrent with Phase 2 tail) · Foundation · MEP coordination · Panel delivery logistics | E6: Panels on site
B7: Phase 4 — Erection + Enclosure | C7: Wks 22–26 | D7: L.E.E.P. crew panel install · Dry-in · MEP rough · Windows/doors · Blower door mid-test (T2+) | E7: Dry-in complete
B8: Phase 5 — Finishes + Rooftop | C8: Wks 26–29 | D8: Interior finishes · MEP trim-out · Rooftop system install (T2–T4) · Agrivoltaic trellis (T4) · Cistern (T3–T4) | E8: Rooftop complete
B9: Phase 6 — CO + Closing | C9: Wks 29–31 | D9: Final inspections · Certificate of occupancy · Sale closings (for-sale) or lease-up (rental) · M4Di cost report to OED | E9: CO issued
B11: SCHEDULE COMPARISON
B12: 4Ward-SIB Forward Panel (M4D system) | C12: 31 weeks | D12: Source: Offsite Builder Magazine 2025; SIPA RS Means study
B13: Standard SIP panelized | C13: 35 weeks | D13: Source: Offsite Builder Magazine 2025; SIPA RS Means study
B14: Site-built stick frame | C14: 39 weeks | D14: Source: Offsite Builder Magazine 2025; SIPA RS Means study

Sheet Cost Comparison
B1: COST COMPARISON — 4WARD-SIB vs. STANDARD SIP vs. STICK FRAME
B2: Per SF of wall · Blue cells = inputs · Sources: SIPA RS Means; M4Di ALDDB; Offsite Builder 2025
B3: Cost element | C3: 4Ward-SIB (Forward Panel) | D3: Standard SIP (OSB face) | E3: Stick frame (all-in layers) | F3: Panel saving vs. stick
B4: Unit size (SF) — adjust here | C4: 1200
B5: Panel / framing materials | C5: =C4*10.5 -> 12600 | D5: =C4*13 -> 15600 | E5: =C4*14 -> 16800
B6: WRB / house wrap | C6: Included | D6: =C4*1.8 -> 2160 | E6: =C4*1.8 -> 2160
B7: Continuous insulation (CI) | C7: Included | D7: =C4*2.5 -> 3000 | E7: =C4*3.5 -> 4200
B8: Cavity insulation sub | C8: Not required | D8: Not required | E8: =C4*1.5 -> 1800
B9: Wrap/CI install labor | C9: Eliminated | D9: =C4*1 -> 1200 | E9: =C4*2.5 -> 3000
B10: Panel engineering | C10: =C4*1.05 -> 1260 | D10: =C4*1.6 -> 1920 | E10: —
B11: TOTAL ALL-IN (per unit) | C11: =C4*10.5+C4*1.05-4500 -> 9360 | D11: =C4*13+C4*1.8+C4*2.5+C4*1.6-2000 -> 20680 | E11: =C4*14+C4*1.8+C4*3.5+C4*2.5+4500 -> 30660 | F11: =E11-C11 -> 21300
B12: Savings vs. stick frame (4Ward-SIB) | C12: =E11-C11 -> 21300 | F12: =(E11-C11)/E11 -> 0.69471624
B14: SCHEDULE SAVINGS (LOAN CARRY)
B15: Weeks saved vs. stick frame | C15: 8 weeks | D15: 4 weeks | E15: —
B16: Est. loan carry saving / unit (8 wks @ 10.25%) | C16: =Assumptions!C19*Assumptions!C14*(Assumptions!C13/52)*8 -> 0
B18: NOTE: 4Ward-SIB pricing fixed at order date. Standard SIP and stick frame subject to lumber index volatility. Energy savings ($1,800–$8,000/yr per unit depending on tier) not included in this cost comparison.
