Workbook

Sheet COVER
B3: Construction Cost Estimate
B4: 607 Concord Avenue · Wilmington, Delaware 19802
B5: ROUGH ORDER OF MAGNITUDE · FULL GUT REHABILITATION WITH COMPLETE MEP REPLACEMENT
B7: TOTAL PROJECT COST — ORDER OF MAGNITUDE
B8: =SUMMARY!P10 -> 292744.82 | O8: =SUMMARY!P10/1300 -> 225.18832
B9: ="CONSTRUCTION "&TEXT(SUMMARY!P8,"$#,##0")&" A/E FEES "&TEXT(SUMMARY!P9,"$#,##0")&" GROSS AREA "&TEXT(1300,"#,##0")&" SF" -> CONSTRUCTION $276,174 A/E FEES $16,570 GROSS AREA 1,300 SF
B11: Project information | L11: Prepared by
B12: PROJECT | F12: 607 Concord Avenue | L12: FIRM | P12: Merge 4 Design LLC
B13: LOCATION | F13: Wilmington, DE 19802 | L13: ADDRESS | P13: 500 Delaware Ave, Suite 1 #1551
B14: PARCEL | F14: 2601530162 | P14: Wilmington, DE 19899
B15: JURISDICTION | F15: New Castle County | L15: PROJECT NO. | P15: M2-2026-016
B16: BUILDING | F16: Rowhouse — end unit, corner | L16: ESTIMATE DATE | P16: 23 July 2026
B17: CONFIGURATION | F17: 2 story + basement + attic | L17: DRAWING BASIS | P17: AD-01 / A-101 / AD-03
B18: GROSS AREA | F18: 1,300 SF above grade | L18: DRAWING DATE | P18: 28 June 2026
B19: SCOPE | F19: Full gut rehabilitation | L19: ACCURACY | P19: ± 20% · AACE Class 4
B21: Project cost control stage
B22: ROM estimate | F22: Feasibility | J22: Design development | N22: GMP / contract | R22: Closeout
B23: COMPLETE | F23: PENDING | J23: PENDING | N23: PENDING | R23: PENDING
B25: Basis of estimate
B26: This estimate is a rough order of magnitude prepared from the architectural drawing set referenced above. Quantities are derived from plan takeoff and field-verifiable dimensions. Unit rates reflect current Wilmington-area subcontractor pricing for residential rehabilitation of comparable scale and complexity.
B27: All mechanical, electrical and plumbing systems are carried as complete replacement, including a 200-amp electrical service upgrade, new gas-fired forced-air heating with cooling, new supply and drain-waste-vent piping, and a new gas water heater.
B28: Exterior scope reflects observed existing conditions including roof replacement to the rafters, porch reconstruction, selective masonry repointing, and re-cladding of the rear wing.
B29: The estimate carries an 8% design and construction contingency and a 10% general contractor overhead and profit allowance. Architecture and engineering fees are shown separately at 6% of construction cost.
B30: Prepared for budgeting, financing and feasibility purposes. This is not a bid, a guaranteed maximum price, or an offer to perform work. Competitive contractor pricing should be obtained prior to any funding commitment or construction contract.
B32: Merge 4 Design LLC · M4Di Construction ROM · Project M2-2026-016 · Issued 23 July 2026 · Page 1 of 4

Sheet SUMMARY
B3: Cost summary
B5: Direct construction cost | K5: 52 line items · 10 divisions | P5: =DETAIL!G79 -> 232470
B6: Design & construction contingency | K6: 8% of direct cost | P6: =DETAIL!G79*0.08 -> 18597.6
B7: General contractor overhead & profit | K7: 10% | P7: =(DETAIL!G79+P6)*0.1 -> 25106.76
B8: Total construction cost | K8: Hard cost | P8: =DETAIL!G79+P6+P7 -> 276174.36
B9: Architecture & engineering fees | K9: 6% of construction | P9: =P8*0.06 -> 16570.462
B10: TOTAL PROJECT COST | K10: Order of magnitude | P10: =P8+P9 -> 292744.82
B12: Cost metrics
B13: GROSS FLOOR AREA | G13: DIRECT COST / SF | L13: CONSTRUCTION / SF | Q13: TOTAL PROJECT / SF
B14: =1300 -> 1300 | G14: =DETAIL!G79/1300 -> 178.82308 | L14: =P8/1300 -> 212.44182 | Q14: =P10/1300 -> 225.18832
B16: Cost distribution by division
B17: Division | L17: Subtotal | Q17: Share of direct
B18: 01 GENERAL CONDITIONS | L18: =DETAIL!G9 -> 9200 | Q18: =DETAIL!G9/DETAIL!G79 -> 0.039574999
B19: 02 DEMOLITION | L19: =DETAIL!G17 -> 20050 | Q19: =DETAIL!G17/DETAIL!G79 -> 0.086247688
B20: 03 FOUNDATIONS & STRUCTURE | L20: =DETAIL!G23 -> 14300 | Q20: =DETAIL!G23/DETAIL!G79 -> 0.061513314
B21: 04 EXTERIOR ENVELOPE | L21: =DETAIL!G34 -> 42450 | Q21: =DETAIL!G34/DETAIL!G79 -> 0.18260421
B22: 05 INTERIOR CONSTRUCTION | L22: =DETAIL!G40 -> 19520 | Q22: =DETAIL!G40/DETAIL!G79 -> 0.083967824
B23: 06 FINISHES | L23: =DETAIL!G47 -> 21300 | Q23: =DETAIL!G47/DETAIL!G79 -> 0.091624726
B24: 07 KITCHEN & BATHS | L24: =DETAIL!G56 -> 35600 | Q24: =DETAIL!G56/DETAIL!G79 -> 0.15313804
B25: 08 PLUMBING | L25: =DETAIL!G63 -> 21200 | Q25: =DETAIL!G63/DETAIL!G79 -> 0.091194563
B26: 09 HVAC | L26: =DETAIL!G70 -> 22650 | Q26: =DETAIL!G70/DETAIL!G79 -> 0.097431927
B27: 10 ELECTRICAL | L27: =DETAIL!G78 -> 26200 | Q27: =DETAIL!G78/DETAIL!G79 -> 0.11270271
B28: Direct construction cost | L28: =DETAIL!G79 -> 232470 | Q28: 1
B30: Existing condition observations
B31: FRONT ELEVATION | F31: Two-story brick rowhouse with attic dormer. Arched masonry window surrounds intact. Full-width covered porch. Entry door boarded in current imagery — structure vacant and secured.
B32: CORNER / SIDE | F32: End-unit condition exposes the full side elevation. Stone foundation shows moisture staining and efflorescence at grade. Basement openings boarded.
B33: REAR WING | F33: Addition clad in vinyl siding, weathered and deteriorated. Re-clad carried in Division 04.
B34: ROOF | F34: Existing roof aged beyond serviceable life. Full strip to rafters carried in Division 02.
B35: HAZARDOUS MATERIALS | F35: Structure predates 1978. Lead paint and asbestos presumed present. Survey and abatement excluded — see Exclusions, page 4.
B37: Merge 4 Design LLC · M4Di Construction ROM · Project M2-2026-016 · Issued 23 July 2026 · Page 2 of 4

Sheet DETAIL
B3: Construction cost detail — full quantity and rate buildup
B4: Scope item | C4: CSI ref | D4: Qty | E4: Unit | F4: Unit cost | G4: Line total | H4: % of dir.
B5: 01 GENERAL CONDITIONS
B6: Temporary protection, site safety, dumpsters, cleanup | C6: DIV 01-TF | D6: 1 | E6: LS | F6: 4500 | G6: =D6*F6 -> 4500 | H6: =G6/$G$79 -> 0.019357336
B7: Permits & inspections — New Castle County | C7: DIV 01-PM | D7: 1 | E7: LS | F7: 3500 | G7: =D7*F7 -> 3500 | H7: =G7/$G$79 -> 0.015055706
B8: Final clean | C8: DIV 01-FC | D8: 1 | E8: LS | F8: 1200 | G8: =D8*F8 -> 1200 | H8: =G8/$G$79 -> 0.0051619564
B9: Division subtotal | G9: =SUM(G6:G8) -> 9200
B10: 02 DEMOLITION
B11: Selective demo — windows, exterior doors, sidelights | C11: DIV 02-DI | D11: 1 | E11: LS | F11: 3500 | G11: =D11*F11 -> 3500 | H11: =G11/$G$79 -> 0.015055706
B12: Remove exterior brick wall to roof level | C12: DIV 02-DE | D12: 1 | E12: LS | F12: 4200 | G12: =D12*F12 -> 4200 | H12: =G12/$G$79 -> 0.018066847
B13: Remove load-bearing structural wall (interior) | C13: DIV 02-DS | D13: 1 | E13: LS | F13: 2800 | G13: =D13*F13 -> 2800 | H13: =G13/$G$79 -> 0.012044565
B14: Roof demolition — strip to rafters | C14: DIV 02-DR | D14: 1300 | E14: SF | F14: 2.5 | G14: =D14*F14 -> 3250 | H14: =G14/$G$79 -> 0.013980299
B15: Floor sheathing removal / porch decking demo | C15: DIV 02-DF | D15: 1 | E15: LS | F15: 1800 | G15: =D15*F15 -> 1800 | H15: =G15/$G$79 -> 0.0077429346
B16: MEP demolition — remove systems back to mains | C16: DIV 02-DM | D16: 1 | E16: LS | F16: 4500 | G16: =D16*F16 -> 4500 | H16: =G16/$G$79 -> 0.019357336
B17: Division subtotal | G17: =SUM(G11:G16) -> 20050
B18: 03 FOUNDATIONS & STRUCTURE
B19: Repair & parge foundation — front and side elevations | C19: DIV 03-CR | D19: 1 | E19: LS | F19: 2800 | G19: =D19*F19 -> 2800 | H19: =G19/$G$79 -> 0.012044565
B20: Repair basement slab — patch / limited pour | C20: DIV 03-CS | D20: 1 | E20: LS | F20: 1800 | G20: =D20*F20 -> 1800 | H20: =G20/$G$79 -> 0.0077429346
B21: New LVL beam & posts at each end | C21: DIV 06-SF | D21: 1 | E21: LS | F21: 6500 | G21: =D21*F21 -> 6500 | H21: =G21/$G$79 -> 0.027960597
B22: New 2x10 floor joists | C22: DIV 06-FJ | D22: 5 | E22: EA | F22: 640 | G22: =D22*F22 -> 3200 | H22: =G22/$G$79 -> 0.013765217
B23: Division subtotal | G23: =SUM(G19:G22) -> 14300
B24: 04 EXTERIOR ENVELOPE
B25: Asphalt shingle roof — main pitched areas | C25: DIV 07-RS | D25: 1300 | E25: SF | F25: 7.5 | G25: =D25*F25 -> 9750 | H25: =G25/$G$79 -> 0.041940896
B26: Low-slope rubber membrane roof — porch / flat area | C26: DIV 07-RM | D26: 1 | E26: LS | F26: 4800 | G26: =D26*F26 -> 4800 | H26: =G26/$G$79 -> 0.020647826
B27: Porch rebuild — decking, vinyl railings, steps | C27: DIV 06-PR | D27: 1 | E27: LS | F27: 5600 | G27: =D27*F27 -> 5600 | H27: =G27/$G$79 -> 0.02408913
B28: Exterior entry door with sidelights — front | C28: DIV 08-DE | D28: 1 | E28: EA | F28: 2800 | G28: =D28*F28 -> 2800 | H28: =G28/$G$79 -> 0.012044565
B29: Exterior rear door | C29: DIV 08-DR | D29: 1 | E29: EA | F29: 1800 | G29: =D29*F29 -> 1800 | H29: =G29/$G$79 -> 0.0077429346
B30: Replacement windows — match existing profile | C30: DIV 08-WD | D30: 8 | E30: EA | F30: 950 | G30: =D30*F30 -> 7600 | H30: =G30/$G$79 -> 0.03269239
B31: Masonry infill at basement window openings | C31: DIV 04-MI | D31: 3 | E31: EA | F31: 800 | G31: =D31*F31 -> 2400 | H31: =G31/$G$79 -> 0.010323913
B32: Rear wing re-clad — fiber cement siding | C32: DIV 07-SD | D32: 1 | E32: LS | F32: 4500 | G32: =D32*F32 -> 4500 | H32: =G32/$G$79 -> 0.019357336
B33: Brick repointing — spot tuckpointing | C33: DIV 04-RP | D33: 1 | E33: LS | F33: 3200 | G33: =D33*F33 -> 3200 | H33: =G33/$G$79 -> 0.013765217
B34: Division subtotal | G34: =SUM(G25:G33) -> 42450
B35: 05 INTERIOR CONSTRUCTION
B36: Gypsum board — walls and ceilings, all levels | C36: DIV 09-GB | D36: 2600 | E36: SF | F36: 4.2 | G36: =D36*F36 -> 10920 | H36: =G36/$G$79 -> 0.046973803
B37: Interior doors per schedule | C37: DIV 08-DI | D37: 8 | E37: EA | F37: 550 | G37: =D37*F37 -> 4400 | H37: =G37/$G$79 -> 0.018927173
B38: Closet shelving / linen storage | C38: DIV 06-MW | D38: 1 | E38: LS | F38: 1800 | G38: =D38*F38 -> 1800 | H38: =G38/$G$79 -> 0.0077429346
B39: Stair repair and refinish | C39: DIV 06-ST | D39: 1 | E39: LS | F39: 2400 | G39: =D39*F39 -> 2400 | H39: =G39/$G$79 -> 0.010323913
B40: Division subtotal | G40: =SUM(G36:G39) -> 19520
B41: 06 FINISHES
B42: Vinyl plank flooring on T&G plywood underlayment | C42: DIV 09-FV | D42: 800 | E42: SF | F42: 6.5 | G42: =D42*F42 -> 5200 | H42: =G42/$G$79 -> 0.022368478
B43: Carpet — bedrooms | C43: DIV 09-FC | D43: 400 | E43: SF | F43: 4 | G43: =D43*F43 -> 1600 | H43: =G43/$G$79 -> 0.0068826085
B44: Ceramic tile — bathrooms and kitchen | C44: DIV 09-FT | D44: 220 | E44: SF | F44: 9 | G44: =D44*F44 -> 1980 | H44: =G44/$G$79 -> 0.008517228
B45: Paint — walls, ceilings, trim | C45: DIV 09-PT | D45: 2600 | E45: SF | F45: 3.2 | G45: =D45*F45 -> 8320 | H45: =G45/$G$79 -> 0.035789564
B46: Trim and millwork — base, casing | C46: DIV 06-TM | D46: 1 | E46: LS | F46: 4200 | G46: =D46*F46 -> 4200 | H46: =G46/$G$79 -> 0.018066847
B47: Division subtotal | G47: =SUM(G42:G46) -> 21300
B49: Merge 4 Design LLC · M4Di Construction ROM · Project M2-2026-016 · Issued 23 July 2026 · Page 3 of 4
B50: 07 KITCHEN & BATHS
B51: Kitchen — cabinets, countertops, sink | C51: DIV 12-KC | D51: 1 | E51: LS | F51: 12000 | G51: =D51*F51 -> 12000 | H51: =G51/$G$79 -> 0.051619564
B52: Range and hood | C52: DIV 11-AP | D52: 1 | E52: EA | F52: 1800 | G52: =D52*F52 -> 1800 | H52: =G52/$G$79 -> 0.0077429346
B53: Full bath — vanity, toilet, tub, tile | C53: DIV 12-BF | D53: 1 | E53: EA | F53: 8500 | G53: =D53*F53 -> 8500 | H53: =G53/$G$79 -> 0.036563858
B54: Powder room — vanity and toilet | C54: DIV 12-BP | D54: 1 | E54: EA | F54: 3800 | G54: =D54*F54 -> 3800 | H54: =G54/$G$79 -> 0.016346195
B55: Master bath — vanity, toilet, tub/shower, tile | C55: DIV 12-BM | D55: 1 | E55: EA | F55: 9500 | G55: =D55*F55 -> 9500 | H55: =G55/$G$79 -> 0.040865488
B56: Division subtotal | G56: =SUM(G51:G55) -> 35600
B57: 08 PLUMBING
B58: Gas hot water heater | C58: DIV 22-WH | D58: 1 | E58: EA | F58: 2200 | G58: =D58*F58 -> 2200 | H58: =G58/$G$79 -> 0.0094635867
B59: PEX supply piping — full distribution | C59: DIV 22-SP | D59: 1 | E59: LS | F59: 6500 | G59: =D59*F59 -> 6500 | H59: =G59/$G$79 -> 0.027960597
B60: PVC drain, waste and vent system | C60: DIV 22-DV | D60: 1 | E60: LS | F60: 8500 | G60: =D60*F60 -> 8500 | H60: =G60/$G$79 -> 0.036563858
B61: Fixture rough-in | C61: DIV 22-RI | D61: 1 | E61: LS | F61: 2800 | G61: =D61*F61 -> 2800 | H61: =G61/$G$79 -> 0.012044565
B62: Sump pump — replace and reconnect | C62: DIV 22-SU | D62: 1 | E62: EA | F62: 1200 | G62: =D62*F62 -> 1200 | H62: =G62/$G$79 -> 0.0051619564
B63: Division subtotal | G63: =SUM(G58:G62) -> 21200
B64: 09 HVAC
B65: Gas furnace — forced air | C65: DIV 23-FA | D65: 1 | E65: EA | F65: 5500 | G65: =D65*F65 -> 5500 | H65: =G65/$G$79 -> 0.023658967
B66: Condenser and evaporator coil | C66: DIV 23-AC | D66: 1 | E66: EA | F66: 4800 | G66: =D66*F66 -> 4800 | H66: =G66/$G$79 -> 0.020647826
B67: Ductwork — supply and return, all floors | C67: DIV 23-DW | D67: 1 | E67: LS | F67: 9500 | G67: =D67*F67 -> 9500 | H67: =G67/$G$79 -> 0.040865488
B68: Registers, grilles, programmable thermostat | C68: DIV 23-TR | D68: 1 | E68: LS | F68: 1800 | G68: =D68*F68 -> 1800 | H68: =G68/$G$79 -> 0.0077429346
B69: Bathroom exhaust fans | C69: DIV 23-EF | D69: 3 | E69: EA | F69: 350 | G69: =D69*F69 -> 1050 | H69: =G69/$G$79 -> 0.0045167118
B70: Division subtotal | G70: =SUM(G65:G69) -> 22650
B71: 10 ELECTRICAL
B72: 200A panel — service upgrade | C72: DIV 26-SV | D72: 1 | E72: EA | F72: 4500 | G72: =D72*F72 -> 4500 | H72: =G72/$G$79 -> 0.019357336
B73: Branch wiring — circuits throughout | C73: DIV 26-BW | D73: 1 | E73: LS | F73: 12000 | G73: =D73*F73 -> 12000 | H73: =G73/$G$79 -> 0.051619564
B74: Outlets, switches, devices | C74: DIV 26-DV | D74: 1 | E74: LS | F74: 3200 | G74: =D74*F74 -> 3200 | H74: =G74/$G$79 -> 0.013765217
B75: Lighting fixtures — allowance | C75: DIV 26-LT | D75: 1 | E75: LS | F75: 4500 | G75: =D75*F75 -> 4500 | H75: =G75/$G$79 -> 0.019357336
B76: Smoke and CO detectors per code | C76: DIV 26-SD | D76: 1 | E76: LS | F76: 800 | G76: =D76*F76 -> 800 | H76: =G76/$G$79 -> 0.0034413043
B77: Kitchen appliance circuits | C77: DIV 26-AC | D77: 1 | E77: LS | F77: 1200 | G77: =D77*F77 -> 1200 | H77: =G77/$G$79 -> 0.0051619564
B78: Division subtotal | G78: =SUM(G72:G77) -> 26200
B79: TOTAL DIRECT CONSTRUCTION COST | G79: =G9+G17+G23+G34+G40+G47+G56+G63+G70+G78 -> 232470
B81: Exclusions
B82: — Hazardous materials survey, abatement or disposal (lead, asbestos) — structure predates 1978
B83: — Structural engineering design and stamped calculations
B84: — Site work, landscaping, driveway, fencing and utility service laterals
B85: — Appliances beyond range and hood; window treatments; furnishings
B86: — Owner-directed upgrades above stated allowances
B87: — Escalation beyond estimate date; permit expediting; financing and carrying costs
B89: Merge 4 Design LLC · M4Di Construction ROM · Project M2-2026-016 · Issued 23 July 2026 · Page 4 of 4
