Workbook

Sheet COVER
B1: M4Di | ALDi Design & Construction Budget Tracker
B2: Project Cost Control from ROM Estimate Through Construction Closeout
B4: Project Name: | F4: Enter the official M4Di project code
B5: Project Address: | F5: Full site address
B6: Owner / Client: | F6: Legal entity name
B7: Architect of Record: | F7: e.g., M4D / Aubyn Architecture
B8: M4Di Project Lead:
B9: Gross Area (SF): | F9: Total building SF in scope
B10: ALDi Start Date: | F10: Date M4Di ALDi engagement begins
B11: ROM Estimate Date: | F11: Date of M4Di P3 ROM (v1)
B13: COLUMN GUIDE — Four Estimate Stages
B14: Column | C14: Stage | D14: When Populated | E14: Purpose / Notes
B15: Column D M4Di ROM | C15: Rough Order of Magnitude | D15: At ALDi engagement start (P3 deliverable) | E15: The locked baseline. Never changes after ALDi Gate 0. All variances measured against this column.
B16: Column E 75% DD Estimate | C16: Design Development (75%) | D16: At ALDi Gate 2 (DD milestone) | E16: First major design-informed reality check. Should be within ±15% of ROM. Flag and explain if not.
B17: Column F 100% CD / Contractor SOV | C17: Construction Documents / GMP | D17: At ALDi Gate 3 (GMP execution) | E17: The contracted number. All future change orders are additions to this column. Defines the budget baseline.
B18: Column G Actual Cost | C18: Construction Closeout | D18: Updated monthly during construction | E18: Running total of all committed costs: executed SOV + approved COs + owner direct costs.
B20: CORE RULES FOR THIS WORKBOOK
B21: 1. | C21: Column D (M4Di ROM) is LOCKED after ALDi Gate 0. It never changes. It is the reference baseline for every downstream comparison.
B22: 2. | C22: Column E (75% DD) is entered at Gate 2. If the DD estimate exceeds Column D by more than 15%, a written explanation is required in the VARIANCE LOG before the gate is cleared.
B23: 3. | C23: Column F (100% CD / SOV) is entered at Gate 3 from the executed Contractor Schedule of Values. This is the contracted hard cost. Soft costs in this column come from executed consultant agreements.
B24: 4. | C24: Column G (Actual Cost) is updated monthly. It equals Column F plus all approved change orders plus all owner direct costs incurred to date. It is never projected — only committed costs.
B25: 5. | C25: Every line item in this tracker maps to a line item in the M4Di OI Tool (BID SUMMARY, SOFT COSTS, or TOTAL PROJECT BUDGET). The M4Di project lead maintains both files in sync.
B26: 6. | C26: This workbook is an M4Di ALDi deliverable. It is issued to the Owner and AE at Gate 0 setup. The Owner and AE receive read-only PDF exports monthly. The live Excel file is M4Di-controlled.

Sheet BUDGET TRACKER
B1: M4Di | ALDi Design & Construction Budget Tracker
B2: =IF(COVER!C4="","[Project Name — complete COVER tab]",COVER!C4&" | "& COVER!C6&" | ALDi Start: "&TEXT(COVER!C10,"mm/dd/yyyy")) -> [Project Name — complete COVER tab]
B4: Budget Item | C4: CSI / Ref | D4: M4Di ROM (LOCKED BASELINE) | E4: 75% DD ESTIMATE (Gate 2) | F4: 100% CD / SOV (Gate 3 — Contracted) | G4: ACTUAL COST (Running Total) | H4: ROM vs. DD Variance | I4: GC QUOTE / PROPOSAL (Pre-SOV) | J4: GC ACTUALS (Running Total) | K4: ROM vs. GC Quote Variance | L4: CD vs. Actual Variance | N4: Notes / Status
B5: Budget Item | C5: CSI / Ref | D5: $ Amount | E5: $ Amount | F5: $ Amount | G5: $ Amount | H5: $ Variance | I5: $ Amount | J5: $ Amount | K5: $ Variance | L5: $ Variance | M5: % Var | N5: Notes / Flag
B6: ► Col D: M4Di ROM (locked Gate 0) ► Col E: Enter at Gate 2 (75% DD) ► Col F: Enter at Gate 3 from GMP/SOV ► Col G: Update monthly ► Col I: GC Quote/Proposal (pre-SOV) ► Col J: GC Actuals (monthly)
B7: SECTION 1 — HARD COSTS (Construction)
B8: 1A — Procurement & General Requirements
B9: General Conditions (GC Time & Overhead) | C9: DIV 00/01 | H9: =IF(AND(ISNUMBER(D9),ISNUMBER(E9)),E9-D9,"") | K9: =IF(AND(ISNUMBER(D9),ISNUMBER(I9)),I9-D9,"")
B10: Temporary Facilities, Utilities & Hoarding | C10: DIV 01-TF | H10: =IF(AND(ISNUMBER(D10),ISNUMBER(E10)),E10-D10,"") | K10: =IF(AND(ISNUMBER(D10),ISNUMBER(I10)),I10-D10,"") | L10: =IFERROR(G10-F10,"-") -> 0 | M10: =IFERROR((G10-F10)/F10,"-") -> - | N10: Per takeoff; hazmat TBD pending survey
B11: Site Safety, Security & Signage | C11: DIV 01-SS | H11: =IF(AND(ISNUMBER(D11),ISNUMBER(E11)),E11-D11,"") | K11: =IF(AND(ISNUMBER(D11),ISNUMBER(I11)),I11-D11,"") | L11: =IFERROR(G11-F11,"-") -> 0 | M11: =IFERROR((G11-F11)/F11,"-") -> - | N11: Housekeeping pads; structural repairs
B12: Dumpsters / Debris Removal | C12: DIV 01-DR | H12: =IF(AND(ISNUMBER(D12),ISNUMBER(E12)),E12-D12,"") | K12: =IF(AND(ISNUMBER(D12),ISNUMBER(I12)),I12-D12,"") | L12: =IFERROR(G12-F12,"-") -> 0 | M12: =IFERROR((G12-F12)/F12,"-") -> - | N12: Misc. metals; stair rails; lintels
B13: Payment & Performance Bond | C13: DIV 00-BD | H13: =IF(AND(ISNUMBER(D13),ISNUMBER(E13)),E13-D13,"") | K13: =IF(AND(ISNUMBER(D13),ISNUMBER(I13)),I13-D13,"") | L13: =IFERROR(G13-F13,"-") -> 0 | M13: =IFERROR((G13-F13)/F13,"-") -> - | N13: Interior partition framing
B14: Builder's Risk Insurance | C14: DIV 00-BR | H14: =IF(AND(ISNUMBER(D14),ISNUMBER(E14)),E14-D14,"") | K14: =IF(AND(ISNUMBER(D14),ISNUMBER(I14)),I14-D14,"") | L14: =IFERROR(G14-F14,"-") -> 0 | M14: =IFERROR((G14-F14)/F14,"-") -> - | N14: Roof repairs; waterproofing; sealants
B15: GC Fee / Overhead & Profit | C15: DIV 00-OH | H15: =IF(AND(ISNUMBER(D15),ISNUMBER(E15)),E15-D15,"") | K15: =IF(AND(ISNUMBER(D15),ISNUMBER(I15)),I15-D15,"") | L15: =IFERROR(G15-F15,"-") -> 0 | M15: =IFERROR((G15-F15)/F15,"-") -> - | N15: Anti-ligature hardware; ADA entries
B16: 1B — Existing Conditions | L16: =IFERROR(G16-F16,"-") -> 0 | M16: =IFERROR((G16-F16)/F16,"-") -> - | N16: Rubber athletic; resilient; carpet tile
B17: Selective Demolition — Interior | C17: DIV 02-DI | H17: =IF(AND(ISNUMBER(D17),ISNUMBER(E17)),E17-D17,"") | K17: =IF(AND(ISNUMBER(D17),ISNUMBER(I17)),I17-D17,"") | L17: =IFERROR(G17-F17,"-") -> 0 | M17: =IFERROR((G17-F17)/F17,"-") -> - | N17: High-perf coatings + standard paint
B18: Selective Demolition — Exterior / Site | C18: DIV 02-DE | H18: =IF(AND(ISNUMBER(D18),ISNUMBER(E18)),E18-D18,"") | K18: =IF(AND(ISNUMBER(D18),ISNUMBER(I18)),I18-D18,"") | L18: =IFERROR(G18-F18,"-") -> 0 | M18: =IFERROR((G18-F18)/F18,"-") -> - | N18: ACT; GWB ceilings; soffits
B19: Hazardous Materials Survey / Testing | C19: DIV 02-HT | H19: =IF(AND(ISNUMBER(D19),ISNUMBER(E19)),E19-D19,"") | K19: =IF(AND(ISNUMBER(D19),ISNUMBER(I19)),I19-D19,"") | L19: =IFERROR(G19-F19,"-") -> 0 | M19: =IFERROR((G19-F19)/F19,"-") -> - | N19: Bathroom accessories; millwork
B20: Hazardous Materials Abatement (ACM/Lead/Mold) | C20: DIV 02-HA | H20: =IF(AND(ISNUMBER(D20),ISNUMBER(E20)),E20-D20,"") | K20: =IF(AND(ISNUMBER(D20),ISNUMBER(I20)),I20-D20,"")
B21: Dewatering / Site Preparation | C21: DIV 02-SP | H21: =IF(AND(ISNUMBER(D21),ISNUMBER(E21)),E21-D21,"") | K21: =IF(AND(ISNUMBER(D21),ISNUMBER(I21)),I21-D21,"") | L21: =IFERROR(G21-F21,"-") -> 0 | M21: =IFERROR((G21-F21)/F21,"-") -> - | N21: Full building in Phase 1A per Program Guide
B22: 1C — Concrete | L22: =IFERROR(G22-F22,"-") -> 0 | M22: =IFERROR((G22-F22)/F22,"-") -> - | N22: Full building; NFPA 72 compliant
B23: Cast-in-Place Concrete — Foundations / Slabs | C23: DIV 03-CF | H23: =IF(AND(ISNUMBER(D23),ISNUMBER(E23)),E23-D23,"") | K23: =IF(AND(ISNUMBER(D23),ISNUMBER(I23)),I23-D23,"") | L23: =IFERROR(G23-F23,"-") -> 0 | M23: =IFERROR((G23-F23)/F23,"-") -> - | N23: Sized for full building future build-out
B24: Concrete Repair / Patching | C24: DIV 03-CR | H24: =IF(AND(ISNUMBER(D24),ISNUMBER(E24)),E24-D24,"") | K24: =IF(AND(ISNUMBER(D24),ISNUMBER(I24)),I24-D24,"") | L24: =IFERROR(G24-F24,"-") -> 0 | M24: =IFERROR((G24-F24)/F24,"-") -> - | N24: Partial area; backbone for Phase 1B tie-in
B25: Precast Concrete Elements | C25: DIV 03-PC | H25: =IF(AND(ISNUMBER(D25),ISNUMBER(E25)),E25-D25,"") | K25: =IF(AND(ISNUMBER(D25),ISNUMBER(I25)),I25-D25,"") | L25: =IFERROR(G25-F25,"-") -> 0 | M25: =IFERROR((G25-F25)/F25,"-") -> - | N25: Scalable panels; risers; branch circuits
B26: 1D — Masonry | L26: =IFERROR(G26-F26,"-") -> 0 | M26: =IFERROR((G26-F26)/F26,"-") -> - | N26: Staff monitoring; access control; data
B27: Masonry — New CMU / Brick | C27: DIV 04-NM | H27: =IF(AND(ISNUMBER(D27),ISNUMBER(E27)),E27-D27,"") | K27: =IF(AND(ISNUMBER(D27),ISNUMBER(I27)),I27-D27,"") | L27: =IFERROR(G27-F27,"-") -> 0 | M27: =IFERROR((G27-F27)/F27,"-") -> - | N27: Structural + enclosure allowance; no cab
B28: Masonry Repair / Repointing | C28: DIV 04-MR | H28: =IF(AND(ISNUMBER(D28),ISNUMBER(E28)),E28-D28,"") | K28: =IF(AND(ISNUMBER(D28),ISNUMBER(I28)),I28-D28,"")
B29: 1E — Metals | L29: =IFERROR(G29-F29,"-") -> 0 | M29: =IFERROR((G29-F29)/F29,"-") -> - | N29: Backstops, bleachers, scoreboard — PENDING
B30: Structural Steel — Framing & Connections | C30: DIV 05-SS | H30: =IF(AND(ISNUMBER(D30),ISNUMBER(E30)),E30-D30,"") | K30: =IF(AND(ISNUMBER(D30),ISNUMBER(I30)),I30-D30,"") | L30: =IFERROR(G30-F30,"-") -> 0 | M30: =IFERROR((G30-F30)/F30,"-") -> - | N30: Wall padding, boxing ring, bag systems
B31: Stairs — Structural Steel / Metal Pan | C31: DIV 05-ST | H31: =IF(AND(ISNUMBER(D31),ISNUMBER(E31)),E31-D31,"") | K31: =IF(AND(ISNUMBER(D31),ISNUMBER(I31)),I31-D31,"") | L31: =IFERROR(G31-F31,"-") -> 0 | M31: =IFERROR((G31-F31)/F31,"-") -> - | N31: OT/PT; sensory room; de-escalation rooms
B32: Miscellaneous Metals — Rails, Lintels, Angles | C32: DIV 05-MM | H32: =IF(AND(ISNUMBER(D32),ISNUMBER(E32)),E32-D32,"") | K32: =IF(AND(ISNUMBER(D32),ISNUMBER(I32)),I32-D32,"") | L32: =IFERROR(G32-F32,"-") -> 0 | M32: =IFERROR((G32-F32)/F32,"-") -> - | N32: Commercial kitchen package — PENDING
B33: Metal Decking | C33: DIV 05-MD | H33: =IF(AND(ISNUMBER(D33),ISNUMBER(E33)),E33-D33,"") | K33: =IF(AND(ISNUMBER(D33),ISNUMBER(I33)),I33-D33,"") | L33: =IFERROR(G33-F33,"-") -> 0 | M33: =IFERROR((G33-F33)/F33,"-") -> - | N33: PA, cameras, access control hardware
B34: 1F — Wood, Plastics & Composites | L34: =IFERROR(G34-F34,"-") -> 0 | M34: =IFERROR((G34-F34)/F34,"-") -> -
B35: Rough Carpentry — Blocking, Nailers, Backing | C35: DIV 06-RC | H35: =IF(AND(ISNUMBER(D35),ISNUMBER(E35)),E35-D35,"") | K35: =IF(AND(ISNUMBER(D35),ISNUMBER(I35)),I35-D35,"")
B36: Finish Carpentry — Millwork & Casework | C36: DIV 06-FC | H36: =IF(AND(ISNUMBER(D36),ISNUMBER(E36)),E36-D36,"") | K36: =IF(AND(ISNUMBER(D36),ISNUMBER(I36)),I36-D36,"") | L36: =IFERROR(G36-F36,"-") -> 0 | M36: =IFERROR((G36-F36)/F36,"-") -> - | N36: 8.0% of base
B37: Architectural Woodwork / Custom Millwork | C37: DIV 06-AW | H37: =IF(AND(ISNUMBER(D37),ISNUMBER(E37)),E37-D37,"") | K37: =IF(AND(ISNUMBER(D37),ISNUMBER(I37)),I37-D37,"") | L37: =IFERROR(G37-F37,"-") -> 0 | M37: =IFERROR((G37-F37)/F37,"-") -> - | N37: 10.0% of base + GC
B38: 1G — Thermal & Moisture Protection | L38: =IFERROR(G38-F38,"-") -> 0 | M38: =IFERROR((G38-F38)/F38,"-") -> - | N38: 12.0% — reduce at SD, DD, GMP
B39: Roofing — Membrane System (TPO/EPDM/BUR) | C39: DIV 07-RF | H39: =IF(AND(ISNUMBER(D39),ISNUMBER(E39)),E39-D39,"") | K39: =IF(AND(ISNUMBER(D39),ISNUMBER(I39)),I39-D39,"") | L39: =IFERROR(G39-F39,"-") -> 0 | M39: =IFERROR((G39-F39)/F39,"-") -> - | N39: 12.0% — pre-1980 building; reduce after hazmat survey
B40: Roof Insulation & Cover Board | C40: DIV 07-RI | H40: =IF(AND(ISNUMBER(D40),ISNUMBER(E40)),E40-D40,"") | K40: =IF(AND(ISNUMBER(D40),ISNUMBER(I40)),I40-D40,"") | L40: =IFERROR(G40-F40,"-") -> 0 | M40: =IFERROR((G40-F40)/F40,"-") -> - | N40: 5.0% — reduce as equipment selections confirmed
B41: Wall Insulation (Batt / Rigid / Spray) | C41: DIV 07-WI | H41: =IF(AND(ISNUMBER(D41),ISNUMBER(E41)),E41-D41,"") | K41: =IF(AND(ISNUMBER(D41),ISNUMBER(I41)),I41-D41,"") | L41: =IFERROR(G41-F41,"-") -> 0 | M41: =IFERROR((G41-F41)/F41,"-") -> - | N41: 2.0% of total
B42: Acoustic Insulation (STC / NRC Assemblies) | C42: DIV 07-AI | H42: =IF(AND(ISNUMBER(D42),ISNUMBER(E42)),E42-D42,"") | K42: =IF(AND(ISNUMBER(D42),ISNUMBER(I42)),I42-D42,"") | L42: =IFERROR(G42-F42,"-") -> 0 | M42: =IFERROR((G42-F42)/F42,"-") -> -
B43: Air Barrier / Vapor Retarder | C43: DIV 07-AB | H43: =IF(AND(ISNUMBER(D43),ISNUMBER(E43)),E43-D43,"") | K43: =IF(AND(ISNUMBER(D43),ISNUMBER(I43)),I43-D43,"")
B44: Waterproofing — Below Grade / Foundation | C44: DIV 07-WP | H44: =IF(AND(ISNUMBER(D44),ISNUMBER(E44)),E44-D44,"") | K44: =IF(AND(ISNUMBER(D44),ISNUMBER(I44)),I44-D44,"")
B45: Caulking, Sealants & Joint Fillers | C45: DIV 07-JS | H45: =IF(AND(ISNUMBER(D45),ISNUMBER(E45)),E45-D45,"") | K45: =IF(AND(ISNUMBER(D45),ISNUMBER(I45)),I45-D45,"")
B46: 1H — Openings | L46: =IFERROR(G46-F46,"-") -> 0 | M46: =IFERROR((G46-F46)/F46,"-") -> - | N46: Per AIA fee schedule, Type C renovation + premium
B47: Hollow Metal Doors, Frames & Hardware | C47: DIV 08-HM | H47: =IF(AND(ISNUMBER(D47),ISNUMBER(E47)),E47-D47,"") | K47: =IF(AND(ISNUMBER(D47),ISNUMBER(I47)),I47-D47,"") | L47: =IFERROR(G47-F47,"-") -> 0 | M47: =IFERROR((G47-F47)/F47,"-") -> - | N47: Project Management per fee agreement
B48: Wood Doors & Frames | C48: DIV 08-WD | H48: =IF(AND(ISNUMBER(D48),ISNUMBER(E48)),E48-D48,"") | K48: =IF(AND(ISNUMBER(D48),ISNUMBER(I48)),I48-D48,"") | L48: =IFERROR(G48-F48,"-") -> 0 | M48: =IFERROR((G48-F48)/F48,"-") -> - | N48: 1.5% of hard cost
B49: Storefront / Curtain Wall / Aluminum Glazing | C49: DIV 08-CW | H49: =IF(AND(ISNUMBER(D49),ISNUMBER(E49)),E49-D49,"") | K49: =IF(AND(ISNUMBER(D49),ISNUMBER(I49)),I49-D49,"") | L49: =IFERROR(G49-F49,"-") -> 0 | M49: =IFERROR((G49-F49)/F49,"-") -> - | N49: 1.8% of hard cost
B50: Windows — New / Replacement | C50: DIV 08-WN | H50: =IF(AND(ISNUMBER(D50),ISNUMBER(E50)),E50-D50,"") | K50: =IF(AND(ISNUMBER(D50),ISNUMBER(I50)),I50-D50,"") | L50: =IFERROR(G50-F50,"-") -> 0 | M50: =IFERROR((G50-F50)/F50,"-") -> - | N50: 1.5% of hard cost
B51: Overhead / Coiling Doors | C51: DIV 08-OD | H51: =IF(AND(ISNUMBER(D51),ISNUMBER(E51)),E51-D51,"") | K51: =IF(AND(ISNUMBER(D51),ISNUMBER(I51)),I51-D51,"") | L51: =IFERROR(G51-F51,"-") -> 0 | M51: =IFERROR((G51-F51)/F51,"-") -> - | N51: 1.0% of hard cost
B52: Accessible Entry — Operators, Ramp, Hardware | C52: DIV 08-AE | H52: =IF(AND(ISNUMBER(D52),ISNUMBER(E52)),E52-D52,"") | K52: =IF(AND(ISNUMBER(D52),ISNUMBER(I52)),I52-D52,"") | L52: =IFERROR(G52-F52,"-") -> 0 | M52: =IFERROR((G52-F52)/F52,"-") -> - | N52: 0.8% of hard cost
B53: 1I — Finishes | L53: =IFERROR(G53-F53,"-") -> 0 | M53: =IFERROR((G53-F53)/F53,"-") -> - | N53: Limited site coordination only
B54: Drywall — Partitions, Shafts & Soffits | C54: DIV 09-DW | H54: =IF(AND(ISNUMBER(D54),ISNUMBER(E54)),E54-D54,"") | K54: =IF(AND(ISNUMBER(D54),ISNUMBER(I54)),I54-D54,"") | L54: =IFERROR(G54-F54,"-") -> 0 | M54: =IFERROR((G54-F54)/F54,"-") -> - | N54: Fixed fee — required before Phase 1A foundation work
B55: Drywall — Acoustic / STC Assemblies | C55: DIV 09-AC | H55: =IF(AND(ISNUMBER(D55),ISNUMBER(E55)),E55-D55,"") | K55: =IF(AND(ISNUMBER(D55),ISNUMBER(I55)),I55-D55,"") | L55: =IFERROR(G55-F55,"-") -> 0 | M55: =IFERROR((G55-F55)/F55,"-") -> - | N55: 0.5% — required for HUD/CDFI-funded projects
B56: Plaster / Stucco / EIFS | C56: DIV 09-PL | H56: =IF(AND(ISNUMBER(D56),ISNUMBER(E56)),E56-D56,"") | K56: =IF(AND(ISNUMBER(D56),ISNUMBER(I56)),I56-D56,"") | L56: =IFERROR(G56-F56,"-") -> 0 | M56: =IFERROR((G56-F56)/F56,"-") -> - | N56: Gates 0–4 + monthly reporting through closeout
B57: Tile — Ceramic / Porcelain (Floors & Walls) | C57: DIV 09-TL | H57: =IF(AND(ISNUMBER(D57),ISNUMBER(E57)),E57-D57,"") | K57: =IF(AND(ISNUMBER(D57),ISNUMBER(I57)),I57-D57,"")
B58: Flooring — LVT / VCT / Vinyl Sheet | C58: DIV 09-FV | H58: =IF(AND(ISNUMBER(D58),ISNUMBER(E58)),E58-D58,"") | K58: =IF(AND(ISNUMBER(D58),ISNUMBER(I58)),I58-D58,"") | L58: =IFERROR(G58-F58,"-") -> 0 | M58: =IFERROR((G58-F58)/F58,"-") -> - | N58: 2.0% of hard cost — NCC + state agencies
B59: Flooring — Carpet / Carpet Tile | C59: DIV 09-FC | H59: =IF(AND(ISNUMBER(D59),ISNUMBER(E59)),E59-D59,"") | K59: =IF(AND(ISNUMBER(D59),ISNUMBER(I59)),I59-D59,"") | L59: =IFERROR(G59-F59,"-") -> 0 | M59: =IFERROR((G59-F59)/F59,"-") -> - | N59: 0.8% — confirm with owner’s insurance agent
B60: Flooring — Wood / Bamboo / Specialty | C60: DIV 09-FW | H60: =IF(AND(ISNUMBER(D60),ISNUMBER(E60)),E60-D60,"") | K60: =IF(AND(ISNUMBER(D60),ISNUMBER(I60)),I60-D60,"") | L60: =IFERROR(G60-F60,"-") -> 0 | M60: =IFERROR((G60-F60)/F60,"-") -> - | N60: IBC-required inspections; materials testing
B61: Flooring — Polished / Sealed Concrete | C61: DIV 09-FP | H61: =IF(AND(ISNUMBER(D61),ISNUMBER(E61)),E61-D61,"") | K61: =IF(AND(ISNUMBER(D61),ISNUMBER(I61)),I61-D61,"") | L61: =IFERROR(G61-F61,"-") -> 0 | M61: =IFERROR((G61-F61)/F61,"-") -> - | N61: Required for CDFI/HUD financing
B62: Acoustical Ceiling Tile (ACT) & Grid | C62: DIV 09-CT | H62: =IF(AND(ISNUMBER(D62),ISNUMBER(E62)),E62-D62,"") | K62: =IF(AND(ISNUMBER(D62),ISNUMBER(I62)),I62-D62,"") | L62: =IFERROR(G62-F62,"-") -> 0 | M62: =IFERROR((G62-F62)/F62,"-") -> - | N62: Pre-1980 building — asbestos/lead survey required
B63: Gypsum Ceiling / Drywall Ceiling | C63: DIV 09-CC | H63: =IF(AND(ISNUMBER(D63),ISNUMBER(E63)),E63-D63,"") | K63: =IF(AND(ISNUMBER(D63),ISNUMBER(I63)),I63-D63,"") | L63: =IFERROR(G63-F63,"-") -> 0 | M63: =IFERROR((G63-F63)/F63,"-") -> - | N63: Contract review; property matters
B64: Paint & Wall Coatings — Interior | C64: DIV 09-PI | H64: =IF(AND(ISNUMBER(D64),ISNUMBER(E64)),E64-D64,"") | K64: =IF(AND(ISNUMBER(D64),ISNUMBER(I64)),I64-D64,"") | L64: =IFERROR(G64-F64,"-") -> 0 | M64: =IFERROR((G64-F64)/F64,"-") -> - | N64: 1.0% of CDFI loan amount
B65: Paint & Coatings — Exterior | C65: DIV 09-PE | H65: =IF(AND(ISNUMBER(D65),ISNUMBER(E65)),E65-D65,"") | K65: =IF(AND(ISNUMBER(D65),ISNUMBER(I65)),I65-D65,"") | L65: =IFERROR(G65-F65,"-") -> 0 | M65: =IFERROR((G65-F65)/F65,"-") -> - | N65: Grant consultant; application support
B66: Wall Covering / Specialty Wall Finish | C66: DIV 09-WC | H66: =IF(AND(ISNUMBER(D66),ISNUMBER(E66)),E66-D66,"") | K66: =IF(AND(ISNUMBER(D66),ISNUMBER(I66)),I66-D66,"") | L66: =IFERROR(G66-F66,"-") -> 0 | M66: =IFERROR((G66-F66)/F66,"-") -> - | N66: Fixed fee; required for adaptive reuse
B67: 1J — Specialties | L67: =IFERROR(G67-F67,"-") -> 0 | M67: =IFERROR((G67-F67)/F67,"-") -> -
B68: Toilet Partitions & Accessories | C68: DIV 10-TP | H68: =IF(AND(ISNUMBER(D68),ISNUMBER(E68)),E68-D68,"") | K68: =IF(AND(ISNUMBER(D68),ISNUMBER(I68)),I68-D68,"")
B69: ADA Restroom Accessories & Grab Bars | C69: DIV 10-ADA | H69: =IF(AND(ISNUMBER(D69),ISNUMBER(E69)),E69-D69,"") | K69: =IF(AND(ISNUMBER(D69),ISNUMBER(I69)),I69-D69,"")
B70: Fire Extinguishers & Cabinets | C70: DIV 10-FE | H70: =IF(AND(ISNUMBER(D70),ISNUMBER(E70)),E70-D70,"") | K70: =IF(AND(ISNUMBER(D70),ISNUMBER(I70)),I70-D70,"") | L70: =IFERROR(G70-F70,"-") -> 0 | M70: =IFERROR((G70-F70)/F70,"-") -> - | N70: 5% of hard cost — reduce as design advances
B71: Signage — Code-Required (Egress / Room ID) | C71: DIV 10-SC | H71: =IF(AND(ISNUMBER(D71),ISNUMBER(E71)),E71-D71,"") | K71: =IF(AND(ISNUMBER(D71),ISNUMBER(I71)),I71-D71,"") | L71: =IFERROR(G71-F71,"-") -> 0 | M71: =IFERROR((G71-F71)/F71,"-") -> - | N71: Enter actual owner FF&E budget
B72: Signage — Branding / Wayfinding (Program) | C72: DIV 10-SB | H72: =IF(AND(ISNUMBER(D72),ISNUMBER(E72)),E72-D72,"") | K72: =IF(AND(ISNUMBER(D72),ISNUMBER(I72)),I72-D72,"") | L72: =IFERROR(G72-F72,"-") -> 0 | M72: =IFERROR((G72-F72)/F72,"-") -> - | N72: Owner-procured systems outside contract
B73: Lockers / Storage Units | C73: DIV 10-LK | H73: =IF(AND(ISNUMBER(D73),ISNUMBER(E73)),E73-D73,"") | K73: =IF(AND(ISNUMBER(D73),ISNUMBER(I73)),I73-D73,"") | L73: =IFERROR(G73-F73,"-") -> 0 | M73: =IFERROR((G73-F73)/F73,"-") -> - | N73: If applicable
B74: Folding Partitions / Operable Walls | C74: DIV 10-FP | H74: =IF(AND(ISNUMBER(D74),ISNUMBER(E74)),E74-D74,"") | K74: =IF(AND(ISNUMBER(D74),ISNUMBER(I74)),I74-D74,"") | L74: =IFERROR(G74-F74,"-") -> 0 | M74: =IFERROR((G74-F74)/F74,"-") -> - | N74: P1 $8K + P2 $14K + P3 $22K — already incurred
B75: Loading Dock Equipment | C75: DIV 10-LD | H75: =IF(AND(ISNUMBER(D75),ISNUMBER(E75)),E75-D75,"") | K75: =IF(AND(ISNUMBER(D75),ISNUMBER(I75)),I75-D75,"") | L75: =IFERROR(G75-F75,"-") -> 0 | M75: =IFERROR((G75-F75)/F75,"-") -> - | N75: Funder exhibits; CDFI package; 3 grants
B76: 1K — Equipment (Program-Specific) | L76: =IFERROR(G76-F76,"-") -> 0 | M76: =IFERROR((G76-F76)/F76,"-") -> - | N76: 3–8% of total — enter when funding stack confirmed
B77: Equipment Allowance 1 — [Define per project] | C77: EQP-01 | H77: =IF(AND(ISNUMBER(D77),ISNUMBER(E77)),E77-D77,"") | K77: =IF(AND(ISNUMBER(D77),ISNUMBER(I77)),I77-D77,"") | L77: =IFERROR(G77-F77,"-") -> 0 | M77: =IFERROR((G77-F77)/F77,"-") -> -
B78: Equipment Allowance 2 — [Define per project] | C78: EQP-02 | H78: =IF(AND(ISNUMBER(D78),ISNUMBER(E78)),E78-D78,"") | K78: =IF(AND(ISNUMBER(D78),ISNUMBER(I78)),I78-D78,"")
B79: Equipment Allowance 3 — [Define per project] | C79: EQP-03 | H79: =IF(AND(ISNUMBER(D79),ISNUMBER(E79)),E79-D79,"") | K79: =IF(AND(ISNUMBER(D79),ISNUMBER(I79)),I79-D79,"")
B80: Equipment Allowance 4 — [Define per project] | C80: EQP-04 | H80: =IF(AND(ISNUMBER(D80),ISNUMBER(E80)),E80-D80,"") | K80: =IF(AND(ISNUMBER(D80),ISNUMBER(I80)),I80-D80,"") | L80: =IFERROR(G80-F80,"-") -> 0 | M80: =IFERROR((G80-F80)/F80,"-") -> -
B81: Kitchen / Food Service Equipment | C81: EQP-KIT | H81: =IF(AND(ISNUMBER(D81),ISNUMBER(E81)),E81-D81,"") | K81: =IF(AND(ISNUMBER(D81),ISNUMBER(I81)),I81-D81,"")
B82: Stage / Platform / Performance Equipment | C82: EQP-STG | H82: =IF(AND(ISNUMBER(D82),ISNUMBER(E82)),E82-D82,"") | K82: =IF(AND(ISNUMBER(D82),ISNUMBER(I82)),I82-D82,"")
B83: 1L — Furnishings
B84: FF&E — Fixed Furnishings Allowance | C84: DIV 12-FF | H84: =IF(AND(ISNUMBER(D84),ISNUMBER(E84)),E84-D84,"") | K84: =IF(AND(ISNUMBER(D84),ISNUMBER(I84)),I84-D84,"")
B85: Window Treatments — Blinds / Shades / Acoustic | C85: DIV 12-WT | H85: =IF(AND(ISNUMBER(D85),ISNUMBER(E85)),E85-D85,"") | K85: =IF(AND(ISNUMBER(D85),ISNUMBER(I85)),I85-D85,"")
B86: Casework — Lab / Medical / Specialty | C86: DIV 12-CW | H86: =IF(AND(ISNUMBER(D86),ISNUMBER(E86)),E86-D86,"") | K86: =IF(AND(ISNUMBER(D86),ISNUMBER(I86)),I86-D86,"")
B87: 1M — Special Construction
B88: Special Construction — [Define per project] | C88: DIV 13 | H88: =IF(AND(ISNUMBER(D88),ISNUMBER(E88)),E88-D88,"") | K88: =IF(AND(ISNUMBER(D88),ISNUMBER(I88)),I88-D88,"")
B89: 1N — Conveying Equipment
B90: Elevator — Traction / Hydraulic | C90: DIV 14-EL | H90: =IF(AND(ISNUMBER(D90),ISNUMBER(E90)),E90-D90,"") | K90: =IF(AND(ISNUMBER(D90),ISNUMBER(I90)),I90-D90,"")
B91: Elevator — Shaft Provisions Only | C91: DIV 14-SP | H91: =IF(AND(ISNUMBER(D91),ISNUMBER(E91)),E91-D91,"") | K91: =IF(AND(ISNUMBER(D91),ISNUMBER(I91)),I91-D91,"")
B92: Wheelchair Lift / Vertical Platform Lift | C92: DIV 14-WL | H92: =IF(AND(ISNUMBER(D92),ISNUMBER(E92)),E92-D92,"") | K92: =IF(AND(ISNUMBER(D92),ISNUMBER(I92)),I92-D92,"")
B93: 1O — Fire Suppression
B94: Sprinkler System — NFPA 13 (Full Building) | C94: DIV 21-SP | H94: =IF(AND(ISNUMBER(D94),ISNUMBER(E94)),E94-D94,"") | K94: =IF(AND(ISNUMBER(D94),ISNUMBER(I94)),I94-D94,"")
B95: Sprinkler System — NFPA 13R / 13D (Residential) | C95: DIV 21-SR | H95: =IF(AND(ISNUMBER(D95),ISNUMBER(E95)),E95-D95,"") | K95: =IF(AND(ISNUMBER(D95),ISNUMBER(I95)),I95-D95,"")
B96: Standpipe / Fire Pump | C96: DIV 21-FP | H96: =IF(AND(ISNUMBER(D96),ISNUMBER(E96)),E96-D96,"") | K96: =IF(AND(ISNUMBER(D96),ISNUMBER(I96)),I96-D96,"")
B97: 1P — Plumbing
B98: Plumbing — Sanitary DWV (Drain/Waste/Vent) | C98: DIV 22-DWV | H98: =IF(AND(ISNUMBER(D98),ISNUMBER(E98)),E98-D98,"") | K98: =IF(AND(ISNUMBER(D98),ISNUMBER(I98)),I98-D98,"")
B99: Plumbing — Domestic Water Supply (Hot/Cold) | C99: DIV 22-DW | H99: =IF(AND(ISNUMBER(D99),ISNUMBER(E99)),E99-D99,"") | K99: =IF(AND(ISNUMBER(D99),ISNUMBER(I99)),I99-D99,"")
B100: Plumbing Fixtures & Trim | C100: DIV 22-FX | H100: =IF(AND(ISNUMBER(D100),ISNUMBER(E100)),E100-D100,"") | K100: =IF(AND(ISNUMBER(D100),ISNUMBER(I100)),I100-D100,"")
B101: Natural Gas Rough-in & Distribution | C101: DIV 22-GS | H101: =IF(AND(ISNUMBER(D101),ISNUMBER(E101)),E101-D101,"") | K101: =IF(AND(ISNUMBER(D101),ISNUMBER(I101)),I101-D101,"")
...

Sheet VARIANCE LOG
B1: VARIANCE LOG — Cost Changes Requiring Documentation
B2: Any variance >5% between estimate columns must be documented here before the next ALDi gate is cleared.
B4: Line Item / Budget Category | C4: Gate | D4: ROM Amt ($) | E4: New Est. Amt ($) | F4: Var ($) | G4: Var (%) | H4: Status | I4: Root Cause & Resolution | J4: Approved By
B5: Existing Conditions Contingency — higher than ROM | C5: Gate 2 | D5: 347000 | E5: 420000 | F5: 73,000 | G5: 21.0% | H5: Approved | I5: Hazmat survey confirmed asbestos in 3 locations. Abatement scope added. Owner approved $73K increase. | J5: T. Maxwell / M4Di
B6: HVAC — Phase 1A scope expanded per DDDS requirements | C6: Gate 2 | D6: 310000 | E6: 365000 | F6: 55,000 | G6: 17.7% | H6: Watch | I6: DDDS licensing pre-app required supplemental ventilation for clinical areas. Engineering confirmed scope. | J6: Pending owner
B7: [Next Variance Item — enter as identified] | H7: On Track

Sheet CHANGE ORDER LOG
B1: CHANGE ORDER LOG — ALDi Gate 3–4
B2: All changes to the contracted GMP/SOV (Column F) must be logged here. Actual Cost (Column G) = Column F + approved COs below.
B4: CO # | C4: Description | D4: Date | E4: GC Amount ($) | F4: Owner Cost ($) | G4: Cumulative COs ($) | H4: CO Running % of GMP | I4: Status | J4: Category | K4: Notes / Justification
B5: CO-001 | C5: Hazardous Materials Abatement — Phase 1 (asbestos, 3 locations) | D5: 04/15/2026 | E5: 73000 | F5: 0 | G5: 73000 | H5: 2.1% | I5: Approved | J5: Existing Conditions | K5: Required; covered by existing conditions contingency draw
B6: CO-002 | C6: Additional HVAC ductwork — DDDS ventilation compliance | D6: 05/01/2026 | E6: 55000 | F6: 0 | G6: 128000 | H6: 3.7% | I6: Pending | J6: Regulatory | K6: DDDS licensing requirement; pending owner authorization
B7: [Future CO — enter as issued] | I7: Pending
B9: TOTAL APPROVED COs | E9: =SUM(F5:F7) -> 0

Sheet DRAW SCHEDULE
B1: FUNDING DRAW SCHEDULE — Budget vs. Actual Spend
B2: Track each funding source draw against actual project expenditures. Updated monthly with each pay application.
B4: Funding Source | C4: Total Committed ($) | D4: Draw 1 ($) | E4: Draw 2 ($) | F4: Draw 3 ($) | G4: Draw 4 ($) | H4: Draw 5 ($) | I4: Total Drawn ($) | J4: Remaining ($) | K4: % Drawn
B5: Owner / Developer Equity (Dr. Maxwell) | C5: 2500000 | I5: =SUM(D5:H5) -> 0 | J5: =C5-I5 -> 2500000 | K5: =IFERROR(I5/C5,0) -> 0
B6: CDFI Construction Loan (NCALL) | C6: 3500000 | I6: =SUM(D6:H6) -> 0 | J6: =C6-I6 -> 3500000 | K6: =IFERROR(I6/C6,0) -> 0
B7: HUD CDBG Grant | C7: 750000 | I7: =SUM(D7:H7) -> 0 | J7: =C7-I7 -> 750000 | K7: =IFERROR(I7/C7,0) -> 0
B8: Delaware DDDS Capital Support | C8: 500000 | I8: =SUM(D8:H8) -> 0 | J8: =C8-I8 -> 500000 | K8: =IFERROR(I8/C8,0) -> 0
B9: Philanthropic Grants (Longwood / Welfare Fdn) | C9: 750000 | I9: =SUM(D9:H9) -> 0 | J9: =C9-I9 -> 750000 | K9: =IFERROR(I9/C9,0) -> 0
B10: Owner Contingency Reserve (escrowed) | C10: 300000 | I10: =SUM(D10:H10) -> 0 | J10: =C10-I10 -> 300000 | K10: =IFERROR(I10/C10,0) -> 0
B11: TOTAL FUNDING | C11: =SUM(C5:C10) -> 8300000 | D11: =SUM(D5:D10) -> 0 | E11: =SUM(E5:E10) -> 0 | F11: =SUM(F5:F10) -> 0 | G11: =SUM(G5:G10) -> 0 | H11: =SUM(H5:H10) -> 0 | I11: =SUM(I5:I10) -> 0 | J11: =SUM(J5:J10) -> 8300000 | K11: =SUM(K5:K10) -> 0

Sheet GATE DASHBOARD
B1: ALDi GATE DASHBOARD — Project Status Summary
B2: One-page project status for owner, AE, and lender reporting. Update at each gate.
B4: Project | C4: =COVER!C4 -> 0
B5: Owner | C5: =COVER!C6 -> 0
B6: AE | C6: =COVER!C7 -> 0
B7: M4Di Lead | C7: =COVER!C8 -> 0
B8: Building SF | C8: =COVER!C9 -> 0
B9: ALDi Start | C9: =COVER!C10 -> 0
B10: M4Di ROM (Locked Baseline) | C10: ='BUDGET TRACKER'!D80 -> 0
B11: 75% DD Estimate | C11: ='BUDGET TRACKER'!E80 -> 0
B12: 100% CD / GMP (Contracted) | C12: ='BUDGET TRACKER'!F80 -> 0
B13: Actual Cost to Date | C13: ='BUDGET TRACKER'!G80 -> 0
B14: GC Quote Total (pre-SOV) | C14: ='BUDGET TRACKER'!I171 -> 0
B15: GC Actuals to Date | C15: ='BUDGET TRACKER'!J171 -> 0
B16: ROM vs. GC Quote Variance | C16: ='BUDGET TRACKER'!K171
B17: ALDi GATE STATUS
B18: Gate | C18: Name | D18: Target Date | E18: Actual Date | F18: Status | G18: Budget Check | H18: Key Conditions / Notes
B19: Gate 0 | C19: Controls Setup + Budget Baseline Lock | F19: In Progress | G19: ROM Locked | H19: Project charter issued. Budget baseline = Column D. Procurement calendar set.
B20: Gate 1 | C20: Schematic Design Review | F20: Pending | G20: Target ±15% | H20: SD documents reviewed. Constructability input provided. DDDS pre-app status confirmed.
B21: Gate 2 | C21: Design Development + 75% DD Estimate | F21: Pending | G21: Column E entered | H21: DD estimate entered in Column E. Variance log updated. Owner contingency reviewed.
B22: Gate 3 | C22: GMP Execution + SOV Entry | F22: Pending | G22: Column F = GMP | H22: Contractor SOV entered in Column F. GMP executed. Financing closed.
B23: Gate 4 | C23: Construction Controls + Closeout | F23: Pending | G23: Column G current | H23: Monthly actual cost updates. CO log maintained. HISTORICAL DB row completed.

Sheet STRATEGY MEMO
B1: M4Di STRATEGY MEMO — The ALDi Budget Tracker as a Revenue Growth Engine
B3: WHAT THIS TOOL IS
B4: The ALDi Design & Construction Budget Tracker is M4Di’s most direct revenue-generating product after the P1–P3 feasibility packages. Where the OI Tool establishes credibility at the predevelopment stage, the Tracker sustains M4Di’s role — and M4Di’s fees — through the full design and construction lifecycle of every project. This memo outlines the strategic case for how M4Di positions, prices, and grows this product.
B6: THE CORE VALUE PROPOSITION
B7: Every AE firm has a fee agreement. Every contractor has a schedule of values. Every owner has a checkbook. What none of them has is a single document that ties all three to the original feasibility estimate and tracks variance across the full project life. That gap is exactly what this Tracker fills — and it is a gap that costs project owners real money every time a design decision quietly moves the budget without anyone’s explicit awareness.
B8: M4Di owns this Tracker. M4Di controls it. The AE and contractor provide inputs at defined gate milestones; M4Di synthesizes, interprets, and reports. This is not an administrative function — it is the delivery backbone that the M4Di strategy describes as ALDi. The Tracker is the physical artifact of that backbone.
B10: THE FOUR-COLUMN ARCHITECTURE IS THE PRODUCT
B11: The four columns — ROM, 75% DD, 100% CD/SOV, Actual — are not an accident of format. They are the intellectual property. Each column transition is a gate event where M4Di adds specific, billable value:
B12: ▶ Gate 0 → Column D locked M4Di establishes the baseline. No one can move the ROM without going through M4Di. This is leverage — the ROM is the anchor against which every subsequent decision is measured.
B13: ▶ Gate 2 → Column E entered M4Di reviews the 75% DD estimate from the AE. If it exceeds Column D by more than 15%, M4Di flags it, investigates the cause, and either documents a scope-driven explanation or pushes back on the design team. This review function is not available to any other party because only M4Di holds the original takeoff assumptions.
B14: ▶ Gate 3 → Column F = GMP M4Di reviews the contractor SOV against Column D. M4Di identifies any scope that was added during design but not authorized through the ALDi gate process. This review catches overruns before they become change orders.
B15: ▶ Gate 4 → Column G updated monthly M4Di maintains the running actual cost total from contractor pay applications and owner direct costs. M4Di is the single source of truth for how much has been spent, how much remains, and how the project tracks against the original feasibility commitment.
... B34: TEMPLATE VERSION NOTE — This is the M4Di Generic CSI Template v1.0 (April 2026). Built to MasterFormat division structure with subcategories for high-cost divisions. Gray rows = divisions rarely applicable — leave blank rather than delete. Columns I–K are the GC/Contractor mirror columns (Quote + Actuals). Populate project-specific data in COVER tab. ROM values in Column D are locked at Gate 0.
